Workbook
Name Causa: #REF!
Name CC: #REF!
Name Comp_Auxil: #REF!
Name COMPOSIÇÃO: #REF!
Name encarregado: #REF!
Name EQUIPAMENTO: #REF!
Name função: #REF!
Name FUNCIONARIO: #REF!
Name INSUMP: #REF!
Name LOCAIS: #REF!
Name MATERIAL: #REF!
Name MO: #REF!
Name MVP_05: #REF!
Name NUMER_COMPOSIÇÃO: #REF!
Name Panilha_Resumo: #REF!
Name REGISTRO: #REF!
Name SEMANA: #REF!
Name TUNEL_0: #REF!+#REF!
Name TURNO: #REF!
Name UP_15: #REF!

Sheet Report Consolidado Semanal
BS2: Terraplanagem (C+A) Média m³/d | BU2: PCTE 4/5 | BV2: PCTE 06 | BW2: PCTE 7/8
D4: =Y7 -> 46217 | G4: ACOMPANHAMENTO SEMANAL 15 a 21/06 | K4: ACOMPANHAMENTO SEMANAL 22 a 28/06 | O4: ACOMPANHAMENTO SEMANAL 29 a 05/07 | S4: ACOMPANHAMENTO SEMANAL 06 a 12/07 | W4: ACOMPANHAMENTO DIÁRIO | AA4: ACOMPANHAMENTO SEMANAL | AK4: META MENSAL JUNHO/26 (Cronograma Corrente) | AP4: ACUMULADO BASELINE | AT4: ESCOPO CONTRATUAL | AW4: MÉDIA DIÁRIA (un/dia) | BS4: Média PLANEJADA MÊS | BU4: =SUM(AM13:AM18)+SUM(AM33:AM38) -> 628891.72 | BV4: =SUM(Gráficos!#REF!+Quadros!#REF!) -> #REF! | BW4: =Gráficos!#REF!+Gráficos!H7 -> #REF!
G5: 46054 | K5: 46054 | O5: 46054 | S5: 46054 | W5: 46054 | AA5: 46054 | AK5: 46054 | AW5: 46054 | AX5: 46054 | AY5: 46054
D6: ATIVIDADE | E6: UN | G6: P | R | H6: QUANT. | I6: ADERÊN. | K6: P | R | L6: QUANT. | M6: ADERÊN. | O6: P | R | P6: QUANT. | Q6: ADERÊN. | S6: P | R | T6: QUANT. | U6: ADERÊN. | W6: PRODUÇÃO DO DIA | Y6: =TEXT(Y7,"dDD") -> ter | AA6: =TEXT(AA7,"dDD") -> seg | AB6: =TEXT(AB7,"dDD") -> ter | AC6: =TEXT(AC7,"dDD") -> qua | AD6: =TEXT(AD7,"dDD") -> qui | AE6: =TEXT(AE7,"dDD") -> sex | AF6: =TEXT(AF7,"dDD") -> sáb | AG6: =TEXT(AG7,"dDD") -> dom | AH6: TOTAL SEMANA | AI6: ADERÊN CIA | AK6: PLANEJADO MÊS | AL6: PLANEJADO ATÉ A DATA | AM6: REAL MÊS | AN6: ADERÊN CIA | AP6: REAL ACUMULADO | AQ6: PREVISTO ACUMUL. BL | AR6: ADERÊN CIA | AT6: QUANT. TOTAL | AU6: SALDO | AW6: MÉDIA PLANEJADA | AX6: MÉDIA REAL MÊS | AY6: MÉDIA NECESSÁRIA | BS6: Média PLANEJADA MÊS | BU6: =SUM(Quadros!J12:J12)+SUM(Quadros!J37:J42) -> 628892.11 | BV6: =SUM(Quadros!J25+Gráficos!I3) -> #VALUE! | BW6: =Gráficos!#REF!+Quadros!#REF! -> #REF!
Y7: 46217 | AA7: 46216 | AB7: =AA7+1 -> 46217 | AC7: =AB7+1 -> 46218 | AD7: =AC7+1 -> 46219 | AE7: =AD7+1 -> 46220 | AF7: =AE7+1 -> 46221 | AG7: =AF7+1 -> 46222
D9: Escavação 1ª e 2ª categoria | E9: m³ | G9: P | H9: 377729.91 | I9: =IFERROR((H10/H9),"-") -> 0.87665404 | K9: P | L9: 477872 | M9: =IFERROR((L10/L9),"-") -> 0.90767756 | O9: P | P9: 381250.71 | Q9: =IFERROR((P10/P9),"-") -> 0.93445367 | S9: P | T9: 386884.07 | U9: 0.88993553 | W9: P | X9: =X13+X17+X21+X25 -> 66753.042 | Y9: =IFERROR((X10/X9),"-") -> 0.90809629 | AA9: =AA13+AA17+AA21+AA25 -> 66753.042 | AB9: =AB13+AB17+AB21+AB25 -> 66753.042 | AC9: =AC13+AC17+AC21+AC25 -> 66753.042 | AD9: =AD13+AD17+AD21+AD25 -> 66683.042 | AE9: =AE13+AE17+AE21+AE25 -> 62913.042 | AF9: =AF13+AF17+AF21+AF25 -> 62413.042 | AG9: =AG13+AG17+AG21+AG25 -> 0 | AH9: =SUMIF($AA$7:$AG$7,"<="&$D$4,$AA9:$AG9) -> 133506.08 | AI9: =IFERROR((AH10/AH9),"-") -> 0.92258874 | AK9: =AK13+AK17+AK21+AK25 -> 1739662.6 | AL9: =AL13+AL17+AL21+AL25 -> 906340.84 | AM9: =AM13+AM17+AM21+AM25 -> 718852.56 | AN9: =IFERROR((AM9/AL9),"-") -> 0.79313712 | AP9: =AP13+AP17+AP21+AP25 -> 4570782.1 | AQ9: =AQ13+AQ17+AQ21+AQ25 -> 6396534.4 | AR9: =IFERROR((AP9/AQ9),"-") -> 0.71457165 | AT9: =AT13+AT17+AT21+AT25 -> 15273579 | AU9: =AU13+AU17+AU21+AU25 -> 4621763.3 | AW9: =AW13+AW17+AW21+AW25 -> 64431.948 | AX9: =AX13+AX17+AX21+AX25 -> 59904.38 | AY9: =IF((AK9-AM9)/(Quadros!$D$4-Quadros!$D$6)<0,"-",(AK9-AM9)/(Quadros!$D$4-Quadros!$D$6)) -> 68054.003
G10: R | H10: 331138.45 | K10: R | L10: 433753.69 | O10: R | P10: 356261.13 | S10: R | T10: 344301.88 | W10: R | X10: =X14+X18+X22+X26 -> 60618.19 | AA10: =AA14+AA18+AA22+AA26 -> 62553.02 | AB10: =AB14+AB18+AB22+AB26 -> 60618.19 | AC10: =AC14+AC18+AC22+AC26 -> 0 | AD10: =AD14+AD18+AD22+AD26 -> 0 | AE10: =AE14+AE18+AE22+AE26 -> 0 | AF10: =AF14+AF18+AF22+AF26 -> 0 | AG10: =AG14+AG18+AG22+AG26 -> 0 | AH10: =SUMIF($AA$7:$AG$7,"<="&$D$4,$AA10:$AG10) -> 123171.21
A13: Pacote 04 - Segmento 2.2B- Km 104+500 a Km 116+400 | D13: Pacote 04 - km 104+500 a 131+260 | E13: m³ | G13: P | H13: 28760 | I13: =IFERROR((H14/H13),"-") -> 1.2764256 | K13: P | L13: 25160 | M13: =IFERROR((L14/L13),"-") -> 2.3211447 | O13: P | P13: 14920 | Q13: =IFERROR((P14/P13),"-") -> 1.9825737 | S13: P | T13: 32120 | U13: 0.87048568 | W13: P | X13: =SUMIF($AA$7:$AG$7,"="&$D$4,$AA13:$AG13) -> 7920 | Y13: =IFERROR((X14/X13),"-") -> 0.46969697 | AA13: =SUMIFS('Report Pacote 0405'!P:P,'Report Pacote 0405'!$AV:$AV,$D$9,'Report Pacote 0405'!$AW:$AW,$A$13,'Report Pacote 0405'!$H:$H,$W13)+SUMIFS('Report Pacote 0405'!P:P,'Report Pacote 0405'!$AV:$AV,$D$9,'Report Pacote 0405'!$AW:$AW,$A$14,'Report Pacote 0405'!$H:$H,$W13) -> 7920 | AB13: =SUMIFS('Report Pacote 0405'!Q:Q,'Report Pacote 0405'!$AV:$AV,$D$9,'Report Pacote 0405'!$AW:$AW,$A$13,'Report Pacote 0405'!$H:$H,$W13)+SUMIFS('Report Pacote 0405'!Q:Q,'Report Pacote 0405'!$AV:$AV,$D$9,'Report Pacote 0405'!$AW:$AW,$A$14,'Report Pacote 0405'!$H:$H,$W13) -> 7920 | AC13: =SUMIFS('Report Pacote 0405'!R:R,'Report Pacote 0405'!$AV:$AV,$D$9,'Report Pacote 0405'!$AW:$AW,$A$13,'Report Pacote 0405'!$H:$H,$W13)+SUMIFS('Report Pacote 0405'!R:R,'Report Pacote 0405'!$AV:$AV,$D$9,'Report Pacote 0405'!$AW:$AW,$A$14,'Report Pacote 0405'!$H:$H,$W13) -> 7920 | AD13: =SUMIFS('Report Pacote 0405'!S:S,'Report Pacote 0405'!$AV:$AV,$D$9,'Report Pacote 0405'!$AW:$AW,$A$13,'Report Pacote 0405'!$H:$H,$W13)+SUMIFS('Report Pacote 0405'!S:S,'Report Pacote 0405'!$AV:$AV,$D$9,'Report Pacote 0405'!$AW:$AW,$A$14,'Report Pacote 0405'!$H:$H,$W13) -> 7850 | AE13: =SUMIFS('Report Pacote 0405'!T:T,'Report Pacote 0405'!$AV:$AV,$D$9,'Report Pacote 0405'!$AW:$AW,$A$13,'Report Pacote 0405'!$H:$H,$W13)+SUMIFS('Report Pacote 0405'!T:T,'Report Pacote 0405'!$AV:$AV,$D$9,'Report Pacote 0405'!$AW:$AW,$A$14,'Report Pacote 0405'!$H:$H,$W13) -> 6880 | AF13: =SUMIFS('Report Pacote 0405'!U:U,'Report Pacote 0405'!$AV:$AV,$D$9,'Report Pacote 0405'!$AW:$AW,$A$13,'Report Pacote 0405'!$H:$H,$W13)+SUMIFS('Report Pacote 0405'!U:U,'Report Pacote 0405'!$AV:$AV,$D$9,'Report Pacote 0405'!$AW:$AW,$A$14,'Report Pacote 0405'!$H:$H,$W13) -> 6880 | AG13: =SUMIFS('Report Pacote 0405'!V:V,'Report Pacote 0405'!$AV:$AV,$D$9,'Report Pacote 0405'!$AW:$AW,$A$13,'Report Pacote 0405'!$H:$H,$W13)+SUMIFS('Report Pacote 0405'!V:V,'Report Pacote 0405'!$AV:$AV,$D$9,'Report Pacote 0405'!$AW:$AW,$A$14,'Report Pacote 0405'!$H:$H,$W13) -> 0 | AH13: =SUMIF($AA$7:$AG$7,"<="&$D$4,$AA13:$AG13) -> 15840 | AI13: =IFERROR((AH14/AH13),"-") -> 0.44002525 | AK13: =SUMIFS('Report Pacote 0405'!AA:AA,'Report Pacote 0405'!$AV:$AV,$D$9,'Report Pacote 0405'!$AW:$AW,$A$13,'Report Pacote 0405'!$H:$H,$W13)+SUMIFS('Report Pacote 0405'!AA:AA,'Report Pacote 0405'!$AV:$AV,$D$9,'Report Pacote 0405'!$AW:$AW,$A$14,'Report Pacote 0405'!$H:$H,$W13) -> 254338.81 | AL13: =SUMIFS('Report Pacote 0405'!AB:AB,'Report Pacote 0405'!$AV:$AV,$D$9,'Report Pacote 0405'!$AW:$AW,$A$13,'Report Pacote 0405'!$H:$H,$W13)+SUMIFS('Report Pacote 0405'!AB:AB,'Report Pacote 0405'!$AV:$AV,$D$9,'Report Pacote 0405'!$AW:$AW,$A$14,'Report Pacote 0405'!$H:$H,$W13) -> 197189.92 | AM13: =SUMIFS('Report Pacote 0405'!AC:AC,'Report Pacote 0405'!$AV:$AV,$D$9,'Report Pacote 0405'!$AW:$AW,$A$13,'Report Pacote 0405'!$H:$H,$W13)+SUMIFS('Report Pacote 0405'!AC:AC,'Report Pacote 0405'!$AV:$AV,$D$9,'Report Pacote 0405'!$AW:$AW,$A$14,'Report Pacote 0405'!$H:$H,$W13) -> 55110 | AN13: =IFERROR((AM13/AL13),"-") -> 0.27947676 | AP13: =SUMIFS('Report Pacote 0405'!AK:AK,'Report Pacote 0405'!$AV:$AV,$D$9,'Report Pacote 0405'!$AW:$AW,$A$13,'Report Pacote 0405'!$H:$H,$W13)+SUMIFS('Report Pacote 0405'!AK:AK,'Report Pacote 0405'!$AV:$AV,$D$9,'Report Pacote 0405'!$AW:$AW,$A$14,'Report Pacote 0405'!$H:$H,$W13) -> 3043207.2 | AQ13: =SUMIFS('Report Pacote 0405'!AL:AL,'Report Pacote 0405'!$AV:$AV,$D$9,'Report Pacote 0405'!$AW:$AW,$A$13,'Report Pacote 0405'!$H:$H,$W13)+SUMIFS('Report Pacote 0405'!AL:AL,'Report Pacote 0405'!$AV:$AV,$D$9,'Report Pacote 0405'!$AW:$AW,$A$14,'Report Pacote 0405'!$H:$H,$W13) -> 3163942.7 | AR13: =IFERROR((AP13/AQ13),"-") -> 0.96184016 | AT13: =SUMIFS('Report Pacote 0405'!AO:AO,'Report Pacote 0405'!$AV:$AV,$D$9,'Report Pacote 0405'!$AW:$AW,$A$13,'Report Pacote 0405'!$H:$H,$W13)+SUMIFS('Report Pacote 0405'!AO:AO,'Report Pacote 0405'!$AV:$AV,$D$9,'Report Pacote 0405'!$AW:$AW,$A$14,'Report Pacote 0405'!$H:$H,$W13) -> 3405031.3 | AU13: =SUMIFS('Report Pacote 0405'!AP:AP,'Report Pacote 0405'!$AV:$AV,$D$9,'Report Pacote 0405'!$AW:$AW,$A$13,'Report Pacote 0405'!$H:$H,$W13)+SUMIFS('Report Pacote 0405'!AP:AP,'Report Pacote 0405'!$AV:$AV,$D$9,'Report Pacote 0405'!$AW:$AW,$A$14,'Report Pacote 0405'!$H:$H,$W13) -> 361824.16 | AW13: =AK13/Quadros!$D$4 -> 9419.9559 | AX13: =AM13/Quadros!$D$6 -> 4592.5 | AY13: =IF((AK13-AM13)/(Quadros!$D$4-Quadros!$D$6)<0,"-",(AK13-AM13)/(Quadros!$D$4-Quadros!$D$6)) -> 13281.921
A14: Pacote 04 - Segmento 2.3 - Km 116+517 a 131+241 | G14: R | H14: 36710 | K14: R | L14: 58400 | O14: R | P14: 29580 | S14: R | T14: 27960 | W14: R | X14: =SUMIF($AA$7:$AG$7,"="&$D$4,$AA14:$AG14) -> 3720 | AA14: =SUMIFS('Report Pacote 0405'!P:P,'Report Pacote 0405'!$AV:$AV,$D$9,'Report Pacote 0405'!$AW:$AW,$A$13,'Report Pacote 0405'!$H:$H,$W14)+SUMIFS('Report Pacote 0405'!P:P,'Report Pacote 0405'!$AV:$AV,$D$9,'Report Pacote 0405'!$AW:$AW,$A$14,'Report Pacote 0405'!$H:$H,$W14) -> 3250 | AB14: =SUMIFS('Report Pacote 0405'!Q:Q,'Report Pacote 0405'!$AV:$AV,$D$9,'Report Pacote 0405'!$AW:$AW,$A$13,'Report Pacote 0405'!$H:$H,$W14)+SUMIFS('Report Pacote 0405'!Q:Q,'Report Pacote 0405'!$AV:$AV,$D$9,'Report Pacote 0405'!$AW:$AW,$A$14,'Report Pacote 0405'!$H:$H,$W14) -> 3720 | AC14: =SUMIFS('Report Pacote 0405'!R:R,'Report Pacote 0405'!$AV:$AV,$D$9,'Report Pacote 0405'!$AW:$AW,$A$13,'Report Pacote 0405'!$H:$H,$W14)+SUMIFS('Report Pacote 0405'!R:R,'Report Pacote 0405'!$AV:$AV,$D$9,'Report Pacote 0405'!$AW:$AW,$A$14,'Report Pacote 0405'!$H:$H,$W14) -> 0 | AD14: =SUMIFS('Report Pacote 0405'!S:S,'Report Pacote 0405'!$AV:$AV,$D$9,'Report Pacote 0405'!$AW:$AW,$A$13,'Report Pacote 0405'!$H:$H,$W14)+SUMIFS('Report Pacote 0405'!S:S,'Report Pacote 0405'!$AV:$AV,$D$9,'Report Pacote 0405'!$AW:$AW,$A$14,'Report Pacote 0405'!$H:$H,$W14) -> 0 | AE14: =SUMIFS('Report Pacote 0405'!T:T,'Report Pacote 0405'!$AV:$AV,$D$9,'Report Pacote 0405'!$AW:$AW,$A$13,'Report Pacote 0405'!$H:$H,$W14)+SUMIFS('Report Pacote 0405'!T:T,'Report Pacote 0405'!$AV:$AV,$D$9,'Report Pacote 0405'!$AW:$AW,$A$14,'Report Pacote 0405'!$H:$H,$W14) -> 0 | AF14: =SUMIFS('Report Pacote 0405'!U:U,'Report Pacote 0405'!$AV:$AV,$D$9,'Report Pacote 0405'!$AW:$AW,$A$13,'Report Pacote 0405'!$H:$H,$W14)+SUMIFS('Report Pacote 0405'!U:U,'Report Pacote 0405'!$AV:$AV,$D$9,'Report Pacote 0405'!$AW:$AW,$A$14,'Report Pacote 0405'!$H:$H,$W14) -> 0 | AG14: =SUMIFS('Report Pacote 0405'!V:V,'Report Pacote 0405'!$AV:$AV,$D$9,'Report Pacote 0405'!$AW:$AW,$A$13,'Report Pacote 0405'!$H:$H,$W14)+SUMIFS('Report Pacote 0405'!V:V,'Report Pacote 0405'!$AV:$AV,$D$9,'Report Pacote 0405'!$AW:$AW,$A$14,'Report Pacote 0405'!$H:$H,$W14) -> 0 | AH14: =SUMIF($AA$7:$AG$7,"<="&$D$4,$AA14:$AG14) -> 6970
A17: Pacote 05 - Segmento 2.4 - Km 131+260 a Km 138+000 | D17: Pacote 05 - km 131+260 a 167+300 | E17: m³ | G17: P | H17: 146880 | I17: =IFERROR((H18/H17),"-") -> 0.75909586 | K17: P | L17: 230520 | M17: =IFERROR((L18/L17),"-") -> 0.8181763 | O17: P | P17: 154880 | Q17: =IFERROR((P18/P17),"-") -> 0.99347882 | S17: P | T17: 149000 | U17: 0.99872483 | W17: P | X17: =SUMIF($AA$7:$AG$7,"="&$D$4,$AA17:$AG17) -> 25960 | Y17: =IFERROR((X18/X17),"-") -> 1.0805085 | AA17: =SUMIFS('Report Pacote 0405'!P:P,'Report Pacote 0405'!$AV:$AV,$D$9,'Report Pacote 0405'!$AW:$AW,$A$17,'Report Pacote 0405'!$H:$H,$W17)+SUMIFS('Report Pacote 0405'!P:P,'Report Pacote 0405'!$AV:$AV,$D$9,'Report Pacote 0405'!$AW:$AW,$A$18,'Report Pacote 0405'!$H:$H,$W17)+SUMIFS('Report Pacote 0405'!P:P,'Report Pacote 0405'!$AV:$AV,$D$9,'Report Pacote 0405'!$AW:$AW,$A$19,'Report Pacote 0405'!$H:$H,$W17) -> 25960 | AB17: =SUMIFS('Report Pacote 0405'!Q:Q,'Report Pacote 0405'!$AV:$AV,$D$9,'Report Pacote 0405'!$AW:$AW,$A$17,'Report Pacote 0405'!$H:$H,$W17)+SUMIFS('Report Pacote 0405'!Q:Q,'Report Pacote 0405'!$AV:$AV,$D$9,'Report Pacote 0405'!$AW:$AW,$A$18,'Report Pacote 0405'!$H:$H,$W17)+SUMIFS('Report Pacote 0405'!Q:Q,'Report Pacote 0405'!$AV:$AV,$D$9,'Report Pacote 0405'!$AW:$AW,$A$19,'Report Pacote 0405'!$H:$H,$W17) -> 25960 | AC17: =SUMIFS('Report Pacote 0405'!R:R,'Report Pacote 0405'!$AV:$AV,$D$9,'Report Pacote 0405'!$AW:$AW,$A$17,'Report Pacote 0405'!$H:$H,$W17)+SUMIFS('Report Pacote 0405'!R:R,'Report Pacote 0405'!$AV:$AV,$D$9,'Report Pacote 0405'!$AW:$AW,$A$18,'Report Pacote 0405'!$H:$H,$W17)+SUMIFS('Report Pacote 0405'!R:R,'Report Pacote 0405'!$AV:$AV,$D$9,'Report Pacote 0405'!$AW:$AW,$A$19,'Report Pacote 0405'!$H:$H,$W17) -> 25960 | AD17: =SUMIFS('Report Pacote 0405'!S:S,'Report Pacote 0405'!$AV:$AV,$D$9,'Report Pacote 0405'!$AW:$AW,$A$17,'Report Pacote 0405'!$H:$H,$W17)+SUMIFS('Report Pacote 0405'!S:S,'Report Pacote 0405'!$AV:$AV,$D$9,'Report Pacote 0405'!$AW:$AW,$A$18,'Report Pacote 0405'!$H:$H,$W17)+SUMIFS('Report Pacote 0405'!S:S,'Report Pacote 0405'!$AV:$AV,$D$9,'Report Pacote 0405'!$AW:$AW,$A$19,'Report Pacote 0405'!$H:$H,$W17) -> 25960 | AE17: =SUMIFS('Report Pacote 0405'!T:T,'Report Pacote 0405'!$AV:$AV,$D$9,'Report Pacote 0405'!$AW:$AW,$A$17,'Report Pacote 0405'!$H:$H,$W17)+SUMIFS('Report Pacote 0405'!T:T,'Report Pacote 0405'!$AV:$AV,$D$9,'Report Pacote 0405'!$AW:$AW,$A$18,'Report Pacote 0405'!$H:$H,$W17)+SUMIFS('Report Pacote 0405'!T:T,'Report Pacote 0405'!$AV:$AV,$D$9,'Report Pacote 0405'!$AW:$AW,$A$19,'Report Pacote 0405'!$H:$H,$W17) -> 23160 | AF17: =SUMIFS('Report Pacote 0405'!U:U,'Report Pacote 0405'!$AV:$AV,$D$9,'Report Pacote 0405'!$AW:$AW,$A$17,'Report Pacote 0405'!$H:$H,$W17)+SUMIFS('Report Pacote 0405'!U:U,'Report Pacote 0405'!$AV:$AV,$D$9,'Report Pacote 0405'!$AW:$AW,$A$18,'Report Pacote 0405'!$H:$H,$W17)+SUMIFS('Report Pacote 0405'!U:U,'Report Pacote 0405'!$AV:$AV,$D$9,'Report Pacote 0405'!$AW:$AW,$A$19,'Report Pacote 0405'!$H:$H,$W17) -> 23160 | AG17: =SUMIFS('Report Pacote 0405'!V:V,'Report Pacote 0405'!$AV:$AV,$D$9,'Report Pacote 0405'!$AW:$AW,$A$17,'Report Pacote 0405'!$H:$H,$W17)+SUMIFS('Report Pacote 0405'!V:V,'Report Pacote 0405'!$AV:$AV,$D$9,'Report Pacote 0405'!$AW:$AW,$A$18,'Report Pacote 0405'!$H:$H,$W17)+SUMIFS('Report Pacote 0405'!V:V,'Report Pacote 0405'!$AV:$AV,$D$9,'Report Pacote 0405'!$AW:$AW,$A$19,'Report Pacote 0405'!$H:$H,$W17) -> 0 | AH17: =SUMIF($AA$7:$AG$7,"<="&$D$4,$AA17:$AG17) -> 51920 | AI17: =IFERROR((AH18/AH17),"-") -> 1.1155624 | AK17: =SUMIFS('Report Pacote 0405'!AA:AA,'Report Pacote 0405'!$AV:$AV,$D$9,'Report Pacote 0405'!$AW:$AW,$A$18,'Report Pacote 0405'!$H:$H,$W17)+SUMIFS('Report Pacote 0405'!AA:AA,'Report Pacote 0405'!$AV:$AV,$D$9,'Report Pacote 0405'!$AW:$AW,$A$17,'Report Pacote 0405'!$H:$H,$W17)+SUMIFS('Report Pacote 0405'!AA:AA,'Report Pacote 0405'!$AV:$AV,$D$9,'Report Pacote 0405'!$AW:$AW,$A$19,'Report Pacote 0405'!$H:$H,$W17) -> 691424.32 | AL17: =SUMIFS('Report Pacote 0405'!AB:AB,'Report Pacote 0405'!$AV:$AV,$D$9,'Report Pacote 0405'!$AW:$AW,$A$18,'Report Pacote 0405'!$H:$H,$W17)+SUMIFS('Report Pacote 0405'!AB:AB,'Report Pacote 0405'!$AV:$AV,$D$9,'Report Pacote 0405'!$AW:$AW,$A$17,'Report Pacote 0405'!$H:$H,$W17)+SUMIFS('Report Pacote 0405'!AB:AB,'Report Pacote 0405'!$AV:$AV,$D$9,'Report Pacote 0405'!$AW:$AW,$A$19,'Report Pacote 0405'!$H:$H,$W17) -> 337781.76 | AM17: =SUMIFS('Report Pacote 0405'!AC:AC,'Report Pacote 0405'!$AV:$AV,$D$9,'Report Pacote 0405'!$AW:$AW,$A$18,'Report Pacote 0405'!$H:$H,$W17)+SUMIFS('Report Pacote 0405'!AC:AC,'Report Pacote 0405'!$AV:$AV,$D$9,'Report Pacote 0405'!$AW:$AW,$A$17,'Report Pacote 0405'!$H:$H,$W17)+SUMIFS('Report Pacote 0405'!AC:AC,'Report Pacote 0405'!$AV:$AV,$D$9,'Report Pacote 0405'!$AW:$AW,$A$19,'Report Pacote 0405'!$H:$H,$W17) -> 311650 | AN17: =IFERROR((AM17/AL17),"-") -> 0.92263715 | AP17: =SUMIFS('Report Pacote 0405'!AL:AL,'Report Pacote 0405'!$AV:$AV,$D$9,'Report Pacote 0405'!$AW:$AW,$A$18,'Report Pacote 0405'!$H:$H,$W17)+SUMIFS('Report Pacote 0405'!AL:AL,'Report Pacote 0405'!$AV:$AV,$D$9,'Report Pacote 0405'!$AW:$AW,$A$17,'Report Pacote 0405'!$H:$H,$W17)+SUMIFS('Report Pacote 0405'!AJ:AJ,'Report Pacote 0405'!$AV:$AV,$D$9,'Report Pacote 0405'!$AW:$AW,$A$19,'Report Pacote 0405'!$H:$H,$W17) -> 1463075.2 | AQ17: =SUMIFS('Report Pacote 0405'!AL:AL,'Report Pacote 0405'!$AV:$AV,$D$9,'Report Pacote 0405'!$AW:$AW,$A$13,'Report Pacote 0405'!$H:$H,$W17)+SUMIFS('Report Pacote 0405'!AL:AL,'Report Pacote 0405'!$AV:$AV,$D$9,'Report Pacote 0405'!$AW:$AW,$A$14,'Report Pacote 0405'!$H:$H,$W17) -> 3163942.7 | AR17: =IFERROR((AP17/AQ17),"-") -> 0.46242154 | AT17: =SUMIFS('Report Pacote 0405'!AO:AO,'Report Pacote 0405'!$AV:$AV,$D$9,'Report Pacote 0405'!$AW:$AW,$A$18,'Report Pacote 0405'!$H:$H,$W17)+SUMIFS('Report Pacote 0405'!AO:AO,'Report Pacote 0405'!$AV:$AV,$D$9,'Report Pacote 0405'!$AW:$AW,$A$17,'Report Pacote 0405'!$H:$H,$W17)+SUMIFS('Report Pacote 0405'!AN:AN,'Report Pacote 0405'!$AV:$AV,$D$9,'Report Pacote 0405'!$AW:$AW,$A$19,'Report Pacote 0405'!$H:$H,$W17) -> 2745772.9 | AU17: =SUMIFS('Report Pacote 0405'!AP:AP,'Report Pacote 0405'!$AV:$AV,$D$9,'Report Pacote 0405'!$AW:$AW,$A$18,'Report Pacote 0405'!$H:$H,$W17)+SUMIFS('Report Pacote 0405'!AP:AP,'Report Pacote 0405'!$AV:$AV,$D$9,'Report Pacote 0405'!$AW:$AW,$A$17,'Report Pacote 0405'!$H:$H,$W17)+SUMIFS('Report Pacote 0405'!AO:AO,'Report Pacote 0405'!$AV:$AV,$D$9,'Report Pacote 0405'!$AW:$AW,$A$19,'Report Pacote 0405'!$H:$H,$W17) -> 2422679.4 | AW17: =AK17/Quadros!$D$4 -> 25608.308 | AX17: =AM17/Quadros!$D$6 -> 25970.833 | AY17: =IF((AK17-AM17)/(Quadros!$D$4-Quadros!$D$6)<0,"-",(AK17-AM17)/(Quadros!$D$4-Quadros!$D$6)) -> 25318.288
A18: Pacote 05 - Segmento 2.5 - 138+160 a 153+420 | G18: R | H18: 111496 | K18: R | L18: 188606 | O18: R | P18: 153870 | S18: R | T18: 148810 | W18: R | X18: =SUMIF($AA$7:$AG$7,"="&$D$4,$AA18:$AG18) -> 28050 | AA18: =SUMIFS('Report Pacote 0405'!P:P,'Report Pacote 0405'!$AV:$AV,$D$9,'Report Pacote 0405'!$AW:$AW,$A$17,'Report Pacote 0405'!$H:$H,$W18)+SUMIFS('Report Pacote 0405'!P:P,'Report Pacote 0405'!$AV:$AV,$D$9,'Report Pacote 0405'!$AW:$AW,$A$18,'Report Pacote 0405'!$H:$H,$W18)+SUMIFS('Report Pacote 0405'!P:P,'Report Pacote 0405'!$AV:$AV,$D$9,'Report Pacote 0405'!$AW:$AW,$A$19,'Report Pacote 0405'!$H:$H,$W18) -> 29870 | AB18: =SUMIFS('Report Pacote 0405'!Q:Q,'Report Pacote 0405'!$AV:$AV,$D$9,'Report Pacote 0405'!$AW:$AW,$A$17,'Report Pacote 0405'!$H:$H,$W18)+SUMIFS('Report Pacote 0405'!Q:Q,'Report Pacote 0405'!$AV:$AV,$D$9,'Report Pacote 0405'!$AW:$AW,$A$18,'Report Pacote 0405'!$H:$H,$W18)+SUMIFS('Report Pacote 0405'!Q:Q,'Report Pacote 0405'!$AV:$AV,$D$9,'Report Pacote 0405'!$AW:$AW,$A$19,'Report Pacote 0405'!$H:$H,$W18) -> 28050 | AC18: =SUMIFS('Report Pacote 0405'!R:R,'Report Pacote 0405'!$AV:$AV,$D$9,'Report Pacote 0405'!$AW:$AW,$A$17,'Report Pacote 0405'!$H:$H,$W18)+SUMIFS('Report Pacote 0405'!R:R,'Report Pacote 0405'!$AV:$AV,$D$9,'Report Pacote 0405'!$AW:$AW,$A$18,'Report Pacote 0405'!$H:$H,$W18)+SUMIFS('Report Pacote 0405'!R:R,'Report Pacote 0405'!$AV:$AV,$D$9,'Report Pacote 0405'!$AW:$AW,$A$19,'Report Pacote 0405'!$H:$H,$W18) -> 0 | AD18: =SUMIFS('Report Pacote 0405'!S:S,'Report Pacote 0405'!$AV:$AV,$D$9,'Report Pacote 0405'!$AW:$AW,$A$17,'Report Pacote 0405'!$H:$H,$W18)+SUMIFS('Report Pacote 0405'!S:S,'Report Pacote 0405'!$AV:$AV,$D$9,'Report Pacote 0405'!$AW:$AW,$A$18,'Report Pacote 0405'!$H:$H,$W18)+SUMIFS('Report Pacote 0405'!S:S,'Report Pacote 0405'!$AV:$AV,$D$9,'Report Pacote 0405'!$AW:$AW,$A$19,'Report Pacote 0405'!$H:$H,$W18) -> 0 | AE18: =SUMIFS('Report Pacote 0405'!T:T,'Report Pacote 0405'!$AV:$AV,$D$9,'Report Pacote 0405'!$AW:$AW,$A$17,'Report Pacote 0405'!$H:$H,$W18)+SUMIFS('Report Pacote 0405'!T:T,'Report Pacote 0405'!$AV:$AV,$D$9,'Report Pacote 0405'!$AW:$AW,$A$18,'Report Pacote 0405'!$H:$H,$W18)+SUMIFS('Report Pacote 0405'!T:T,'Report Pacote 0405'!$AV:$AV,$D$9,'Report Pacote 0405'!$AW:$AW,$A$19,'Report Pacote 0405'!$H:$H,$W18) -> 0 | AF18: =SUMIFS('Report Pacote 0405'!U:U,'Report Pacote 0405'!$AV:$AV,$D$9,'Report Pacote 0405'!$AW:$AW,$A$17,'Report Pacote 0405'!$H:$H,$W18)+SUMIFS('Report Pacote 0405'!U:U,'Report Pacote 0405'!$AV:$AV,$D$9,'Report Pacote 0405'!$AW:$AW,$A$18,'Report Pacote 0405'!$H:$H,$W18)+SUMIFS('Report Pacote 0405'!U:U,'Report Pacote 0405'!$AV:$AV,$D$9,'Report Pacote 0405'!$AW:$AW,$A$19,'Report Pacote 0405'!$H:$H,$W18) -> 0 | AG18: =SUMIFS('Report Pacote 0405'!V:V,'Report Pacote 0405'!$AV:$AV,$D$9,'Report Pacote 0405'!$AW:$AW,$A$17,'Report Pacote 0405'!$H:$H,$W18)+SUMIFS('Report Pacote 0405'!V:V,'Report Pacote 0405'!$AV:$AV,$D$9,'Report Pacote 0405'!$AW:$AW,$A$18,'Report Pacote 0405'!$H:$H,$W18)+SUMIFS('Report Pacote 0405'!V:V,'Report Pacote 0405'!$AV:$AV,$D$9,'Report Pacote 0405'!$AW:$AW,$A$19,'Report Pacote 0405'!$H:$H,$W18) -> 0 | AH18: =SUMIF($AA$7:$AG$7,"<="&$D$4,$AA18:$AG18) -> 57920
A19: Pacote 05 - Segmento 3.1 - 153+000 a 167+400
D21: Pacote 06 - km 167+300 0 a 225+000 | E21: m³ | G21: P | H21: 154200 | I21: =IFERROR((H22/H21),"-") -> 0.78111219 | K21: P | L21: 160200 | M21: =IFERROR((L22/L21),"-") -> 0.78200687 | O21: P | P21: 145500 | Q21: =IFERROR((P22/P21),"-") -> 0.79949485 | S21: P | T21: 165700 | U21: 0.69180447 | W21: P | X21: =SUMIF($AA$7:$AG$7,"="&$D$4,$AA21:$AG21) -> 27200 | Y21: =IFERROR((X22/X21),"-") -> 0.74713235 | AA21: =SUMIFS('Report Pacote 06'!AG:AG,'Report Pacote 06'!$CH:$CH,$D$9,'Report Pacote 06'!$G:$G,'Report Consolidado Semanal'!$W21) -> 27200 | AB21: =SUMIFS('Report Pacote 06'!AH:AH,'Report Pacote 06'!$CH:$CH,$D$9,'Report Pacote 06'!$G:$G,'Report Consolidado Semanal'!$W21) -> 27200 | AC21: =SUMIFS('Report Pacote 06'!AI:AI,'Report Pacote 06'!$CH:$CH,$D$9,'Report Pacote 06'!$G:$G,'Report Consolidado Semanal'!$W21) -> 27200 | AD21: =SUMIFS('Report Pacote 06'!AJ:AJ,'Report Pacote 06'!$CH:$CH,$D$9,'Report Pacote 06'!$G:$G,'Report Consolidado Semanal'!$W21) -> 27200 | AE21: =SUMIFS('Report Pacote 06'!AK:AK,'Report Pacote 06'!$CH:$CH,$D$9,'Report Pacote 06'!$G:$G,'Report Consolidado Semanal'!$W21) -> 27200 | AF21: =SUMIFS('Report Pacote 06'!AL:AL,'Report Pacote 06'!$CH:$CH,$D$9,'Report Pacote 06'!$G:$G,'Report Consolidado Semanal'!$W21) -> 26700 | AG21: =SUMIFS('Report Pacote 06'!AM:AM,'Report Pacote 06'!$CH:$CH,$D$9,'Report Pacote 06'!$G:$G,'Report Consolidado Semanal'!$W21) -> 0 | AH21: =SUMIF($AA$7:$AG$7,"<="&$D$4,$AA21:$AG21) -> 54400 | AI21: =IFERROR((AH22/AH21),"-") -> 0.75565257 | AK21: =SUMIFS('Report Pacote 06'!BN:BN,'Report Pacote 06'!$CH:$CH,$D$9,'Report Pacote 06'!$G:$G,'Report Consolidado Semanal'!$W21) -> 571518.65 | AL21: =SUMIFS('Report Pacote 06'!BO:BO,'Report Pacote 06'!$CH:$CH,$D$9,'Report Pacote 06'!$G:$G,'Report Consolidado Semanal'!$W21) -> 254008.29 | AM21: =SUMIFS('Report Pacote 06'!BP:BP,'Report Pacote 06'!$CH:$CH,$D$9,'Report Pacote 06'!$G:$G,'Report Consolidado Semanal'!$W21) -> 226880 | AN21: =IFERROR((AM21/AL21),"-") -> 0.8931992 | AP21: =SUMIFS('Report Pacote 06'!BU:BU,'Report Pacote 06'!$CH:$CH,'Report Consolidado Semanal'!$D$49,'Report Pacote 06'!$G:$G,'Report Consolidado Semanal'!$W21) -> 57822.38 | AQ21: =SUMIFS('Report Pacote 06'!BX:BX,'Report Pacote 06'!$CH:$CH,'Report Consolidado Semanal'!$D$49,'Report Pacote 06'!$G:$G,'Report Consolidado Semanal'!$W21) -> 61971.608 | AR21: =IFERROR((AP21/AQ21),"-") -> 0.93304631 | AT21: =SUMIFS('Report Pacote 06'!CA:CA,'Report Pacote 06'!$CH:$CH,$D$9,'Report Pacote 06'!$G:$G,'Report Consolidado Semanal'!$W21) -> 6620711 | AU21: =SUMIFS('Report Pacote 06'!CB:CB,'Report Pacote 06'!$CH:$CH,$D$9,'Report Pacote 06'!$G:$G,'Report Consolidado Semanal'!$W21) -> 1473376.6 | AW21: =AK21/Quadros!$D$4 -> 21167.357 | AX21: =AM21/Quadros!$D$6 -> 18906.667 | AY21: =IF((AK21-AM21)/(Quadros!$D$4-Quadros!$D$6)<0,"-",(AK21-AM21)/(Quadros!$D$4-Quadros!$D$6)) -> 22975.91
G22: R | H22: 120447.5 | K22: R | L22: 125277.5 | O22: R | P22: 116326.5 | S22: R | T22: 114632 | W22: R | X22: =SUMIF($AA$7:$AG$7,"="&$D$4,$AA22:$AG22) -> 20322 | AA22: =SUMIFS('Report Pacote 06'!AG:AG,'Report Pacote 06'!$CH:$CH,$D$9,'Report Pacote 06'!$G:$G,'Report Consolidado Semanal'!$W22) -> 20785.5 | AB22: =SUMIFS('Report Pacote 06'!AH:AH,'Report Pacote 06'!$CH:$CH,$D$9,'Report Pacote 06'!$G:$G,'Report Consolidado Semanal'!$W22) -> 20322 | AC22: =SUMIFS('Report Pacote 06'!AI:AI,'Report Pacote 06'!$CH:$CH,$D$9,'Report Pacote 06'!$G:$G,'Report Consolidado Semanal'!$W22) -> 0 | AD22: =SUMIFS('Report Pacote 06'!AJ:AJ,'Report Pacote 06'!$CH:$CH,$D$9,'Report Pacote 06'!$G:$G,'Report Consolidado Semanal'!$W22) -> 0 | AE22: =SUMIFS('Report Pacote 06'!AK:AK,'Report Pacote 06'!$CH:$CH,$D$9,'Report Pacote 06'!$G:$G,'Report Consolidado Semanal'!$W22) -> 0 | AF22: =SUMIFS('Report Pacote 06'!AL:AL,'Report Pacote 06'!$CH:$CH,$D$9,'Report Pacote 06'!$G:$G,'Report Consolidado Semanal'!$W22) -> 0 | AG22: =SUMIFS('Report Pacote 06'!AM:AM,'Report Pacote 06'!$CH:$CH,$D$9,'Report Pacote 06'!$G:$G,'Report Consolidado Semanal'!$W22) -> 0 | AH22: =SUMIF($AA$7:$AG$7,"<="&$D$4,$AA22:$AG22) -> 41107.5
A25: Corte | D25: Pacote 07/08 - km 227+200 a 292+260 | E25: m³ | G25: P | H25: 47889.906 | I25: =IFERROR((H26/H25),"-") -> 1.3047624 | K25: P | L25: 61992 | M25: =IFERROR((L26/L25),"-") -> 0.99158262 | O25: P | P25: 65950.713 | Q25: =IFERROR((P26/P25),"-") -> 0.85646731 | S25: P | T25: 40064.071 | U25: 1.320382 | W25: P | X25: =SUMIF($AA$7:$AG$7,"="&$D$4,$AA25:$AG25) -> 5673.0421 | Y25: =IFERROR((X26/X25),"-") -> 1.5029309 | AA25: =SUMIFS('Report Pacote 07-08'!AL:AL,'Report Pacote 07-08'!$CB:$CB,$A25,'Report Pacote 07-08'!$J:$J,$W25) -> 5673.0421 | AB25: =SUMIFS('Report Pacote 07-08'!AM:AM,'Report Pacote 07-08'!$CB:$CB,$A25,'Report Pacote 07-08'!$J:$J,$W25) -> 5673.0421 | AC25: =SUMIFS('Report Pacote 07-08'!AN:AN,'Report Pacote 07-08'!$CB:$CB,$A25,'Report Pacote 07-08'!$J:$J,$W25) -> 5673.0421 | AD25: =SUMIFS('Report Pacote 07-08'!AO:AO,'Report Pacote 07-08'!$CB:$CB,$A25,'Report Pacote 07-08'!$J:$J,$W25) -> 5673.0421 | AE25: =SUMIFS('Report Pacote 07-08'!AP:AP,'Report Pacote 07-08'!$CB:$CB,$A25,'Report Pacote 07-08'!$J:$J,$W25) -> 5673.0421 | AF25: =SUMIFS('Report Pacote 07-08'!AQ:AQ,'Report Pacote 07-08'!$CB:$CB,$A25,'Report Pacote 07-08'!$J:$J,$W25) -> 5673.0421 | AG25: =SUMIFS('Report Pacote 07-08'!AR:AR,'Report Pacote 07-08'!$CB:$CB,$A25,'Report Pacote 07-08'!$J:$J,$W25) -> 0 | AH25: =SUMIF($AA$7:$AG$7,"<="&$D$4,$AA25:$AG25) -> 11346.084 | AI25: =IFERROR((AH26/AH25),"-") -> 1.5136244 | AK25: =SUMIFS('Report Pacote 07-08'!BM:BM,'Report Pacote 07-08'!$CB:$CB,$A25,'Report Pacote 07-08'!$J:$J,$W25) -> 222380.83 | AL25: =SUMIFS('Report Pacote 07-08'!BN:BN,'Report Pacote 07-08'!$CB:$CB,$A25,'Report Pacote 07-08'!$J:$J,$W25) -> 117360.87 | AM25: =SUMIFS('Report Pacote 07-08'!BO:BO,'Report Pacote 07-08'!$CB:$CB,$A25,'Report Pacote 07-08'!$J:$J,$W25) -> 125212.56 | AN25: =IFERROR((AM25/AL25),"-") -> 1.0669021 | AP25: =SUMIFS('Report Pacote 07-08'!AD:AD,'Report Pacote 07-08'!$CB:$CB,$A25,'Report Pacote 07-08'!$J:$J,$W25) -> 6677.3452 | AQ25: =SUMIFS('Report Pacote 07-08'!AI:AI,'Report Pacote 07-08'!$CB:$CB,$A25,'Report Pacote 07-08'!$J:$J,$W25) -> 6677.3452 | AR25: =IFERROR((AP25/AQ25),"-") -> 1 | AT25: =SUMIFS('Report Pacote 07-08'!BV:BV,'Report Pacote 07-08'!$CB:$CB,$A25,'Report Pacote 07-08'!$J:$J,$W25) -> 2502064 | AU25: =SUMIFS('Report Pacote 07-08'!BW:BW,'Report Pacote 07-08'!$CB:$CB,$A25,'Report Pacote 07-08'!$J:$J,$W25) -> 363883.14 | AW25: =AK25/Quadros!$D$4 -> 8236.327 | AX25: =AM25/Quadros!$D$6 -> 10434.38 | AY25: =IF((AK25-AM25)/(Quadros!$D$4-Quadros!$D$6)<0,"-",(AK25-AM25)/(Quadros!$D$4-Quadros!$D$6)) -> 6477.8846
A26: Corte | G26: R | H26: 62484.95 | K26: R | L26: 61470.19 | O26: R | P26: 56484.63 | S26: R | T26: 52899.88 | W26: R | X26: =SUMIF($AA$7:$AG$7,"="&$D$4,$AA26:$AG26) -> 8526.19 | AA26: =SUMIFS('Report Pacote 07-08'!AL:AL,'Report Pacote 07-08'!$CB:$CB,$A26,'Report Pacote 07-08'!$J:$J,$W26) -> 8647.52 | AB26: =SUMIFS('Report Pacote 07-08'!AM:AM,'Report Pacote 07-08'!$CB:$CB,$A26,'Report Pacote 07-08'!$J:$J,$W26) -> 8526.19 | AC26: =SUMIFS('Report Pacote 07-08'!AN:AN,'Report Pacote 07-08'!$CB:$CB,$A26,'Report Pacote 07-08'!$J:$J,$W26) -> 0 | AD26: =SUMIFS('Report Pacote 07-08'!AO:AO,'Report Pacote 07-08'!$CB:$CB,$A26,'Report Pacote 07-08'!$J:$J,$W26) -> 0 | AE26: =SUMIFS('Report Pacote 07-08'!AP:AP,'Report Pacote 07-08'!$CB:$CB,$A26,'Report Pacote 07-08'!$J:$J,$W26) -> 0 | AF26: =SUMIFS('Report Pacote 07-08'!AQ:AQ,'Report Pacote 07-08'!$CB:$CB,$A26,'Report Pacote 07-08'!$J:$J,$W26) -> 0 | AG26: =SUMIFS('Report Pacote 07-08'!AR:AR,'Report Pacote 07-08'!$CB:$CB,$A26,'Report Pacote 07-08'!$J:$J,$W26) -> 0 | AH26: =SUMIF($AA$7:$AG$7,"<="&$D$4,$AA26:$AG26) -> 17173.71 | AP26: =SUMIFS('Report Pacote 07-08'!AC:AC,'Report Pacote 07-08'!$CB:$CB,$A26,'Report Pacote 07-08'!$J:$J,$W26) -> 0 | AQ26: =SUMIFS('Report Pacote 07-08'!AD:AD,'Report Pacote 07-08'!$CB:$CB,$A26,'Report Pacote 07-08'!$J:$J,$W26) -> 11151.33
A29: Aterro e compactação | D29: Aterro e compactação | E29: m³ | G29: P | H29: 253268.36 | I29: =IFERROR((H30/H29),"-") -> 0.92736943 | K29: P | L29: =L33+L37+L41+L45 -> 276798.64 | M29: =IFERROR((L30/L29),"-") -> 0.91432222 | O29: P | P29: 243811.32 | Q29: =IFERROR((P30/P29),"-") -> 1.0837369 | S29: P | T29: 292078.48 | U29: 0.85425102 | W29: P | X29: =X33+X37+X41+X45 -> 48323.852 | Y29: =IFERROR((X30/X29),"-") -> 0.95484371 | AA29: =AA33+AA37+AA41+AA45 -> 48323.852 | AB29: =AB33+AB37+AB41+AB45 -> 48323.852 | AC29: =AC33+AC37+AC41+AC45 -> 48323.852 | AD29: =AD33+AD37+AD41+AD45 -> 48323.852 | AE29: =AE33+AE37+AE41+AE45 -> 45383.852 | AF29: =AF33+AF37+AF41+AF45 -> 45383.852 | AG29: =AG33+AG37+AG41+AG45 -> 0 | AH29: =SUMIF($AA$7:$AG$7,"<="&$D$4,$AA29:$AG29) -> 96647.705 | AI29: =IFERROR((AH30/AH29),"-") -> 0.94654542 | AK29: =AK33+AK37+AK41+AK45 -> 1313421.3 | AL29: =AL33+AL37+AL41+AL45 -> 576798.85 | AM29: =AM33+AM37+AM41+AM45 -> 530966.13 | AN29: =IFERROR((AM29/AL29),"-") -> 0.92053951 | AP29: =AP33+AP37+AP41+AP45 -> 2923690.2 | AQ29: =AQ33+AQ37+AQ41+AQ45 -> 2363923 | AR29: =IFERROR((AP29/AQ29),"-") -> 1.2367958 | AT29: =AT33+AT37+AT41+AT45 -> 9986485.6 | AU29: =AU33+AU37+AU41+AU45 -> 2433678 | AW29: =AW33+AW37+AW41+AW45 -> 48645.234 | AX29: =AX33+AX37+AX41+AX45 -> 44247.178 | AY29: =IF((AK29-AM29)/(Quadros!$D$4-Quadros!$D$6)<0,"-",(AK29-AM29)/(Quadros!$D$4-Quadros!$D$6)) -> 52163.679
G30: R | H30: 234873.34 | K30: R | L30: =L34+L38+L42+L46 -> 253083.15 | O30: R | P30: 264227.31 | S30: R | T30: 249508.34 | W30: R | X30: =X34+X38+X42+X46 -> 46141.727 | AA30: =AA34+AA38+AA42+AA46 -> 45339.716 | AB30: =AB34+AB38+AB42+AB46 -> 46141.727 | AC30: =AC34+AC38+AC42+AC46 -> 0 | AD30: =AD34+AD38+AD42+AD46 -> 0 | AE30: =AE34+AE38+AE42+AE46 -> 0 | AF30: =AF34+AF38+AF42+AF46 -> 0 | AG30: =AG34+AG38+AG42+AG46 -> 0 | AH30: =SUMIF($AA$7:$AG$7,"<="&$D$4,$AA30:$AG30) -> 91481.443
A33: Pacote 04 - Segmento 2.2B- Km 104+500 a Km 116+400 | D33: Pacote 04 - km 104+500 a 131+260 | E33: m³ | G33: P | H33: 4620 | I33: =IFERROR((H34/H33),"-") -> 0.8664329 | K33: P | L33: 11577 | M33: =IFERROR((L34/L33),"-") -> 0.5807584 | O33: P | P33: 12880 | Q33: =IFERROR((P34/P33),"-") -> 0.53054037 | S33: P | T33: 20539 | U33: 0.24082964 | W33: P | X33: =SUMIF($AA$7:$AG$7,"="&$D$4,$AA33:$AG33) -> 4900 | Y33: =IFERROR((X34/X33),"-") -> 0.40191837 | AA33: =SUMIFS('Report Pacote 0405'!P:P,'Report Pacote 0405'!$AV:$AV,$D$29,'Report Pacote 0405'!$AW:$AW,$A$33,'Report Pacote 0405'!$H:$H,$W33)+SUMIFS('Report Pacote 0405'!P:P,'Report Pacote 0405'!$AV:$AV,$D$29,'Report Pacote 0405'!$AW:$AW,$A$34,'Report Pacote 0405'!$H:$H,$W33) -> 4900 | AB33: =SUMIFS('Report Pacote 0405'!Q:Q,'Report Pacote 0405'!$AV:$AV,$D$29,'Report Pacote 0405'!$AW:$AW,$A$33,'Report Pacote 0405'!$H:$H,$W33)+SUMIFS('Report Pacote 0405'!Q:Q,'Report Pacote 0405'!$AV:$AV,$D$29,'Report Pacote 0405'!$AW:$AW,$A$34,'Report Pacote 0405'!$H:$H,$W33) -> 4900 | AC33: =SUMIFS('Report Pacote 0405'!R:R,'Report Pacote 0405'!$AV:$AV,$D$29,'Report Pacote 0405'!$AW:$AW,$A$33,'Report Pacote 0405'!$H:$H,$W33)+SUMIFS('Report Pacote 0405'!R:R,'Report Pacote 0405'!$AV:$AV,$D$29,'Report Pacote 0405'!$AW:$AW,$A$34,'Report Pacote 0405'!$H:$H,$W33) -> 4900 | AD33: =SUMIFS('Report Pacote 0405'!S:S,'Report Pacote 0405'!$AV:$AV,$D$29,'Report Pacote 0405'!$AW:$AW,$A$33,'Report Pacote 0405'!$H:$H,$W33)+SUMIFS('Report Pacote 0405'!S:S,'Report Pacote 0405'!$AV:$AV,$D$29,'Report Pacote 0405'!$AW:$AW,$A$34,'Report Pacote 0405'!$H:$H,$W33) -> 4900 | AE33: =SUMIFS('Report Pacote 0405'!T:T,'Report Pacote 0405'!$AV:$AV,$D$29,'Report Pacote 0405'!$AW:$AW,$A$33,'Report Pacote 0405'!$H:$H,$W33)+SUMIFS('Report Pacote 0405'!T:T,'Report Pacote 0405'!$AV:$AV,$D$29,'Report Pacote 0405'!$AW:$AW,$A$34,'Report Pacote 0405'!$H:$H,$W33) -> 4200 | AF33: =SUMIFS('Report Pacote 0405'!U:U,'Report Pacote 0405'!$AV:$AV,$D$29,'Report Pacote 0405'!$AW:$AW,$A$33,'Report Pacote 0405'!$H:$H,$W33)+SUMIFS('Report Pacote 0405'!U:U,'Report Pacote 0405'!$AV:$AV,$D$29,'Report Pacote 0405'!$AW:$AW,$A$34,'Report Pacote 0405'!$H:$H,$W33) -> 4200 | AG33: =SUMIFS('Report Pacote 0405'!V:V,'Report Pacote 0405'!$AV:$AV,$D$29,'Report Pacote 0405'!$AW:$AW,$A$33,'Report Pacote 0405'!$H:$H,$W33)+SUMIFS('Report Pacote 0405'!V:V,'Report Pacote 0405'!$AV:$AV,$D$29,'Report Pacote 0405'!$AW:$AW,$A$34,'Report Pacote 0405'!$H:$H,$W33) -> 0 | AH33: =SUMIF($AA$7:$AG$7,"<="&$D$4,$AA33:$AG33) -> 9800 | AI33: =IFERROR((AH34/AH33),"-") -> 0.24208571 | AK33: =SUMIFS('Report Pacote 0405'!AA:AA,'Report Pacote 0405'!$AV:$AV,$D$29,'Report Pacote 0405'!$AW:$AW,$A$33,'Report Pacote 0405'!$H:$H,$W33)+SUMIFS('Report Pacote 0405'!AA:AA,'Report Pacote 0405'!$AV:$AV,$D$29,'Report Pacote 0405'!$AW:$AW,$A$34,'Report Pacote 0405'!$H:$H,$W33) -> 58977.56 | AL33: =SUMIFS('Report Pacote 0405'!AB:AB,'Report Pacote 0405'!$AV:$AV,$D$29,'Report Pacote 0405'!$AW:$AW,$A$34,'Report Pacote 0405'!$H:$H,$W33)+SUMIFS('Report Pacote 0405'!AB:AB,'Report Pacote 0405'!$AV:$AV,$D$29,'Report Pacote 0405'!$AW:$AW,$A$33,'Report Pacote 0405'!$H:$H,$W33) -> 21542.52 | AM33: =SUMIFS('Report Pacote 0405'!AC:AC,'Report Pacote 0405'!$AV:$AV,$D$29,'Report Pacote 0405'!$AW:$AW,$A$33,'Report Pacote 0405'!$H:$H,$W33)+SUMIFS('Report Pacote 0405'!AC:AC,'Report Pacote 0405'!$AV:$AV,$D$29,'Report Pacote 0405'!$AW:$AW,$A$34,'Report Pacote 0405'!$H:$H,$W33) -> 12851.48 | AN33: =IFERROR((AM33/AL33),"-") -> 0.59656345 | AP33: =SUMIFS('Report Pacote 0405'!AK:AK,'Report Pacote 0405'!$AV:$AV,$D$29,'Report Pacote 0405'!$AW:$AW,$A$33,'Report Pacote 0405'!$H:$H,$W33)+SUMIFS('Report Pacote 0405'!AK:AK,'Report Pacote 0405'!$AV:$AV,$D$29,'Report Pacote 0405'!$AW:$AW,$A$34,'Report Pacote 0405'!$H:$H,$W33) -> 1715348.1 | AQ33: =SUMIFS('Report Pacote 0405'!AL:AL,'Report Pacote 0405'!$AV:$AV,$D$29,'Report Pacote 0405'!$AW:$AW,$A$33,'Report Pacote 0405'!$H:$H,$W33)+SUMIFS('Report Pacote 0405'!AL:AL,'Report Pacote 0405'!$AV:$AV,$D$29,'Report Pacote 0405'!$AW:$AW,$A$34,'Report Pacote 0405'!$H:$H,$W33) -> 1011217.9 | AR33: =IFERROR((AP33/AQ33),"-") -> 1.6963189 | AT33: =SUMIFS('Report Pacote 0405'!AO:AO,'Report Pacote 0405'!$AV:$AV,$D$29,'Report Pacote 0405'!$AW:$AW,$A$33,'Report Pacote 0405'!$H:$H,$W33)+SUMIFS('Report Pacote 0405'!AO:AO,'Report Pacote 0405'!$AV:$AV,$D$29,'Report Pacote 0405'!$AW:$AW,$A$34,'Report Pacote 0405'!$H:$H,$W33) -> 1082483.1 | AU33: =SUMIFS('Report Pacote 0405'!AP:AP,'Report Pacote 0405'!$AV:$AV,$D$29,'Report Pacote 0405'!$AW:$AW,$A$33,'Report Pacote 0405'!$H:$H,$W33)+SUMIFS('Report Pacote 0405'!AP:AP,'Report Pacote 0405'!$AV:$AV,$D$29,'Report Pacote 0405'!$AW:$AW,$A$34,'Report Pacote 0405'!$H:$H,$W33) -> -631582.56 | AW33: =AK33/Quadros!$D$4 -> 2184.3541 | AX33: =AM33/Quadros!$D$6 -> 1070.9567 | AY33: =IF((AK33-AM33)/(Quadros!$D$4-Quadros!$D$6)<0,"-",(AK33-AM33)/(Quadros!$D$4-Quadros!$D$6)) -> 3075.072
A34: Pacote 04 - Segmento 2.3 - Km 116+517 a 131+241 | G34: R | H34: 4002.92 | K34: R | L34: 6723.44 | O34: R | P34: 6833.36 | S34: R | T34: 4946.4 | W34: R | X34: =SUMIF($AA$7:$AG$7,"="&$D$4,$AA34:$AG34) -> 1969.4 | AA34: =SUMIFS('Report Pacote 0405'!P:P,'Report Pacote 0405'!$AV:$AV,$D$29,'Report Pacote 0405'!$AW:$AW,$A$33,'Report Pacote 0405'!$H:$H,$W34)+SUMIFS('Report Pacote 0405'!P:P,'Report Pacote 0405'!$AV:$AV,$D$29,'Report Pacote 0405'!$AW:$AW,$A$34,'Report Pacote 0405'!$H:$H,$W34) -> 403.04 | AB34: =SUMIFS('Report Pacote 0405'!Q:Q,'Report Pacote 0405'!$AV:$AV,$D$29,'Report Pacote 0405'!$AW:$AW,$A$33,'Report Pacote 0405'!$H:$H,$W34)+SUMIFS('Report Pacote 0405'!Q:Q,'Report Pacote 0405'!$AV:$AV,$D$29,'Report Pacote 0405'!$AW:$AW,$A$34,'Report Pacote 0405'!$H:$H,$W34) -> 1969.4 | AC34: =SUMIFS('Report Pacote 0405'!R:R,'Report Pacote 0405'!$AV:$AV,$D$29,'Report Pacote 0405'!$AW:$AW,$A$33,'Report Pacote 0405'!$H:$H,$W34)+SUMIFS('Report Pacote 0405'!R:R,'Report Pacote 0405'!$AV:$AV,$D$29,'Report Pacote 0405'!$AW:$AW,$A$34,'Report Pacote 0405'!$H:$H,$W34) -> 0 | AD34: =SUMIFS('Report Pacote 0405'!S:S,'Report Pacote 0405'!$AV:$AV,$D$29,'Report Pacote 0405'!$AW:$AW,$A$33,'Report Pacote 0405'!$H:$H,$W34)+SUMIFS('Report Pacote 0405'!S:S,'Report Pacote 0405'!$AV:$AV,$D$29,'Report Pacote 0405'!$AW:$AW,$A$34,'Report Pacote 0405'!$H:$H,$W34) -> 0 | AE34: =SUMIFS('Report Pacote 0405'!T:T,'Report Pacote 0405'!$AV:$AV,$D$29,'Report Pacote 0405'!$AW:$AW,$A$33,'Report Pacote 0405'!$H:$H,$W34)+SUMIFS('Report Pacote 0405'!T:T,'Report Pacote 0405'!$AV:$AV,$D$29,'Report Pacote 0405'!$AW:$AW,$A$34,'Report Pacote 0405'!$H:$H,$W34) -> 0 | AF34: =SUMIFS('Report Pacote 0405'!U:U,'Report Pacote 0405'!$AV:$AV,$D$29,'Report Pacote 0405'!$AW:$AW,$A$33,'Report Pacote 0405'!$H:$H,$W34)+SUMIFS('Report Pacote 0405'!U:U,'Report Pacote 0405'!$AV:$AV,$D$29,'Report Pacote 0405'!$AW:$AW,$A$34,'Report Pacote 0405'!$H:$H,$W34) -> 0 | AG34: =SUMIFS('Report Pacote 0405'!V:V,'Report Pacote 0405'!$AV:$AV,$D$29,'Report Pacote 0405'!$AW:$AW,$A$33,'Report Pacote 0405'!$H:$H,$W34)+SUMIFS('Report Pacote 0405'!V:V,'Report Pacote 0405'!$AV:$AV,$D$29,'Report Pacote 0405'!$AW:$AW,$A$34,'Report Pacote 0405'!$H:$H,$W34) -> 0 | AH34: =SUMIF($AA$7:$AG$7,"<="&$D$4,$AA34:$AG34) -> 2372.44
A37: Pacote 05 - Segmento 2.4 - Km 131+260 a Km 138+000 | D37: Pacote 05 - km 131+260 a 167+300 | E37: m³ | G37: P | H37: 84672 | I37: =IFERROR((H38/H37),"-") -> 1.1132951 | K37: P | L37: 84352 | M37: =IFERROR((L38/L37),"-") -> 1.2425597 | O37: P | P37: 90752 | Q37: =IFERROR((P38/P37),"-") -> 1.3887566 | S37: P | T37: 112496 | U37: 1.0341804 | W37: P | X37: =SUMIF($AA$7:$AG$7,"="&$D$4,$AA37:$AG37) -> 18536 | Y37: =IFERROR((X38/X37),"-") -> 1.204795 | AA37: =SUMIFS('Report Pacote 0405'!P:P,'Report Pacote 0405'!$AV:$AV,$D$29,'Report Pacote 0405'!$AW:$AW,$A$37,'Report Pacote 0405'!$H:$H,$W37)+SUMIFS('Report Pacote 0405'!P:P,'Report Pacote 0405'!$AV:$AV,$D$29,'Report Pacote 0405'!$AW:$AW,$A$38,'Report Pacote 0405'!$H:$H,$W37)+SUMIFS('Report Pacote 0405'!P:P,'Report Pacote 0405'!$AV:$AV,$D$29,'Report Pacote 0405'!$AW:$AW,$A$39,'Report Pacote 0405'!$H:$H,$W37) -> 18536 | AB37: =SUMIFS('Report Pacote 0405'!Q:Q,'Report Pacote 0405'!$AV:$AV,$D$29,'Report Pacote 0405'!$AW:$AW,$A$37,'Report Pacote 0405'!$H:$H,$W37)+SUMIFS('Report Pacote 0405'!Q:Q,'Report Pacote 0405'!$AV:$AV,$D$29,'Report Pacote 0405'!$AW:$AW,$A$38,'Report Pacote 0405'!$H:$H,$W37)+SUMIFS('Report Pacote 0405'!Q:Q,'Report Pacote 0405'!$AV:$AV,$D$29,'Report Pacote 0405'!$AW:$AW,$A$39,'Report Pacote 0405'!$H:$H,$W37) -> 18536 | AC37: =SUMIFS('Report Pacote 0405'!R:R,'Report Pacote 0405'!$AV:$AV,$D$29,'Report Pacote 0405'!$AW:$AW,$A$37,'Report Pacote 0405'!$H:$H,$W37)+SUMIFS('Report Pacote 0405'!R:R,'Report Pacote 0405'!$AV:$AV,$D$29,'Report Pacote 0405'!$AW:$AW,$A$38,'Report Pacote 0405'!$H:$H,$W37)+SUMIFS('Report Pacote 0405'!R:R,'Report Pacote 0405'!$AV:$AV,$D$29,'Report Pacote 0405'!$AW:$AW,$A$39,'Report Pacote 0405'!$H:$H,$W37) -> 18536 | AD37: =SUMIFS('Report Pacote 0405'!S:S,'Report Pacote 0405'!$AV:$AV,$D$29,'Report Pacote 0405'!$AW:$AW,$A$37,'Report Pacote 0405'!$H:$H,$W37)+SUMIFS('Report Pacote 0405'!S:S,'Report Pacote 0405'!$AV:$AV,$D$29,'Report Pacote 0405'!$AW:$AW,$A$38,'Report Pacote 0405'!$H:$H,$W37)+SUMIFS('Report Pacote 0405'!S:S,'Report Pacote 0405'!$AV:$AV,$D$29,'Report Pacote 0405'!$AW:$AW,$A$39,'Report Pacote 0405'!$H:$H,$W37) -> 18536 | AE37: =SUMIFS('Report Pacote 0405'!T:T,'Report Pacote 0405'!$AV:$AV,$D$29,'Report Pacote 0405'!$AW:$AW,$A$37,'Report Pacote 0405'!$H:$H,$W37)+SUMIFS('Report Pacote 0405'!T:T,'Report Pacote 0405'!$AV:$AV,$D$29,'Report Pacote 0405'!$AW:$AW,$A$38,'Report Pacote 0405'!$H:$H,$W37)+SUMIFS('Report Pacote 0405'!T:T,'Report Pacote 0405'!$AV:$AV,$D$29,'Report Pacote 0405'!$AW:$AW,$A$39,'Report Pacote 0405'!$H:$H,$W37) -> 16296 | AF37: =SUMIFS('Report Pacote 0405'!U:U,'Report Pacote 0405'!$AV:$AV,$D$29,'Report Pacote 0405'!$AW:$AW,$A$37,'Report Pacote 0405'!$H:$H,$W37)+SUMIFS('Report Pacote 0405'!U:U,'Report Pacote 0405'!$AV:$AV,$D$29,'Report Pacote 0405'!$AW:$AW,$A$38,'Report Pacote 0405'!$H:$H,$W37)+SUMIFS('Report Pacote 0405'!U:U,'Report Pacote 0405'!$AV:$AV,$D$29,'Report Pacote 0405'!$AW:$AW,$A$39,'Report Pacote 0405'!$H:$H,$W37) -> 16296 | AG37: =SUMIFS('Report Pacote 0405'!V:V,'Report Pacote 0405'!$AV:$AV,$D$29,'Report Pacote 0405'!$AW:$AW,$A$37,'Report Pacote 0405'!$H:$H,$W37)+SUMIFS('Report Pacote 0405'!V:V,'Report Pacote 0405'!$AV:$AV,$D$29,'Report Pacote 0405'!$AW:$AW,$A$38,'Report Pacote 0405'!$H:$H,$W37)+SUMIFS('Report Pacote 0405'!V:V,'Report Pacote 0405'!$AV:$AV,$D$29,'Report Pacote 0405'!$AW:$AW,$A$39,'Report Pacote 0405'!$H:$H,$W37) -> 0 | AH37: =SUMIF($AA$7:$AG$7,"<="&$D$4,$AA37:$AG37) -> 37072 | AI37: =IFERROR((AH38/AH37),"-") -> 1.2376575 | AK37: =SUMIFS('Report Pacote 0405'!AA:AA,'Report Pacote 0405'!$AV:$AV,$D$29,'Report Pacote 0405'!$AW:$AW,$A$38,'Report Pacote 0405'!$H:$H,$W37)+SUMIFS('Report Pacote 0405'!AA:AA,'Report Pacote 0405'!$AV:$AV,$D$29,'Report Pacote 0405'!$AW:$AW,$A$37,'Report Pacote 0405'!$H:$H,$W37)+SUMIFS('Report Pacote 0405'!AA:AA,'Report Pacote 0405'!$AV:$AV,$D$29,'Report Pacote 0405'!$AW:$AW,$A$39,'Report Pacote 0405'!$H:$H,$W37) -> 613003.13 | AL37: =SUMIFS('Report Pacote 0405'!AB:AB,'Report Pacote 0405'!$AV:$AV,$D$29,'Report Pacote 0405'!$AW:$AW,$A$38,'Report Pacote 0405'!$H:$H,$W37)+SUMIFS('Report Pacote 0405'!AB:AB,'Report Pacote 0405'!$AV:$AV,$D$29,'Report Pacote 0405'!$AW:$AW,$A$37,'Report Pacote 0405'!$H:$H,$W37)+SUMIFS('Report Pacote 0405'!AB:AB,'Report Pacote 0405'!$AV:$AV,$D$29,'Report Pacote 0405'!$AW:$AW,$A$39,'Report Pacote 0405'!$H:$H,$W37) -> 264642.37 | AM37: =SUMIFS('Report Pacote 0405'!AC:AC,'Report Pacote 0405'!$AV:$AV,$D$29,'Report Pacote 0405'!$AW:$AW,$A$38,'Report Pacote 0405'!$H:$H,$W37)+SUMIFS('Report Pacote 0405'!AC:AC,'Report Pacote 0405'!$AV:$AV,$D$29,'Report Pacote 0405'!$AW:$AW,$A$37,'Report Pacote 0405'!$H:$H,$W37)+SUMIFS('Report Pacote 0405'!AC:AC,'Report Pacote 0405'!$AV:$AV,$D$29,'Report Pacote 0405'!$AW:$AW,$A$39,'Report Pacote 0405'!$H:$H,$W37) -> 249280.24 | AN37: =IFERROR((AM37/AL37),"-") -> 0.94195136 | AP37: =SUMIFS('Report Pacote 0405'!AK:AK,'Report Pacote 0405'!$AV:$AV,$D$29,'Report Pacote 0405'!$AW:$AW,$A$38,'Report Pacote 0405'!$H:$H,$W37)+SUMIFS('Report Pacote 0405'!AK:AK,'Report Pacote 0405'!$AV:$AV,$D$29,'Report Pacote 0405'!$AW:$AW,$A$37,'Report Pacote 0405'!$H:$H,$W37)+SUMIFS('Report Pacote 0405'!AJ:AJ,'Report Pacote 0405'!$AV:$AV,$D$29,'Report Pacote 0405'!$AW:$AW,$A$39,'Report Pacote 0405'!$H:$H,$W37) -> 1144541.8 | AQ37: =SUMIFS('Report Pacote 0405'!AL:AL,'Report Pacote 0405'!$AV:$AV,$D$29,'Report Pacote 0405'!$AW:$AW,$A$38,'Report Pacote 0405'!$H:$H,$W37)+SUMIFS('Report Pacote 0405'!AL:AL,'Report Pacote 0405'!$AV:$AV,$D$29,'Report Pacote 0405'!$AW:$AW,$A$37,'Report Pacote 0405'!$H:$H,$W37)+SUMIFS('Report Pacote 0405'!AK:AK,'Report Pacote 0405'!$AV:$AV,$D$29,'Report Pacote 0405'!$AW:$AW,$A$39,'Report Pacote 0405'!$H:$H,$W37) -> 1284755.6 | AR37: =IFERROR((AP37/AQ37),"-") -> 0.89086346 | AT37: =SUMIFS('Report Pacote 0405'!AO:AO,'Report Pacote 0405'!$AV:$AV,$D$29,'Report Pacote 0405'!$AW:$AW,$A$38,'Report Pacote 0405'!$H:$H,$W37)+SUMIFS('Report Pacote 0405'!AO:AO,'Report Pacote 0405'!$AV:$AV,$D$29,'Report Pacote 0405'!$AW:$AW,$A$37,'Report Pacote 0405'!$H:$H,$W37)+SUMIFS('Report Pacote 0405'!AN:AN,'Report Pacote 0405'!$AV:$AV,$D$29,'Report Pacote 0405'!$AW:$AW,$A$39,'Report Pacote 0405'!$H:$H,$W37) -> 2263498 | AU37: =SUMIFS('Report Pacote 0405'!AP:AP,'Report Pacote 0405'!$AV:$AV,$D$29,'Report Pacote 0405'!$AW:$AW,$A$38,'Report Pacote 0405'!$H:$H,$W37)+SUMIFS('Report Pacote 0405'!AP:AP,'Report Pacote 0405'!$AV:$AV,$D$29,'Report Pacote 0405'!$AW:$AW,$A$37,'Report Pacote 0405'!$H:$H,$W37)+SUMIFS('Report Pacote 0405'!AO:AO,'Report Pacote 0405'!$AV:$AV,$D$29,'Report Pacote 0405'!$AW:$AW,$A$39,'Report Pacote 0405'!$H:$H,$W37) -> 1421654.8 | AW37: =AK37/Quadros!$D$4 -> 22703.82 | AX37: =AM37/Quadros!$D$6 -> 20773.353 | AY37: =IF((AK37-AM37)/(Quadros!$D$4-Quadros!$D$6)<0,"-",(AK37-AM37)/(Quadros!$D$4-Quadros!$D$6)) -> 24248.193
A38: Pacote 05 - Segmento 2.5 - 138+160 a 153+420 | G38: R | H38: 94264.92 | K38: R | L38: 104812.4 | O38: R | P38: 126032.44 | S38: R | T38: 116341.16 | W38: R | X38: =SUMIF($AA$7:$AG$7,"="&$D$4,$AA38:$AG38) -> 22332.08 | AA38: =SUMIFS('Report Pacote 0405'!P:P,'Report Pacote 0405'!$AV:$AV,$D$29,'Report Pacote 0405'!$AW:$AW,$A$37,'Report Pacote 0405'!$H:$H,$W38)+SUMIFS('Report Pacote 0405'!P:P,'Report Pacote 0405'!$AV:$AV,$D$29,'Report Pacote 0405'!$AW:$AW,$A$38,'Report Pacote 0405'!$H:$H,$W38)+SUMIFS('Report Pacote 0405'!P:P,'Report Pacote 0405'!$AV:$AV,$D$29,'Report Pacote 0405'!$AW:$AW,$A$39,'Report Pacote 0405'!$H:$H,$W38) -> 23550.36 | AB38: =SUMIFS('Report Pacote 0405'!Q:Q,'Report Pacote 0405'!$AV:$AV,$D$29,'Report Pacote 0405'!$AW:$AW,$A$37,'Report Pacote 0405'!$H:$H,$W38)+SUMIFS('Report Pacote 0405'!Q:Q,'Report Pacote 0405'!$AV:$AV,$D$29,'Report Pacote 0405'!$AW:$AW,$A$38,'Report Pacote 0405'!$H:$H,$W38)+SUMIFS('Report Pacote 0405'!Q:Q,'Report Pacote 0405'!$AV:$AV,$D$29,'Report Pacote 0405'!$AW:$AW,$A$39,'Report Pacote 0405'!$H:$H,$W38) -> 22332.08 | AC38: =SUMIFS('Report Pacote 0405'!R:R,'Report Pacote 0405'!$AV:$AV,$D$29,'Report Pacote 0405'!$AW:$AW,$A$37,'Report Pacote 0405'!$H:$H,$W38)+SUMIFS('Report Pacote 0405'!R:R,'Report Pacote 0405'!$AV:$AV,$D$29,'Report Pacote 0405'!$AW:$AW,$A$38,'Report Pacote 0405'!$H:$H,$W38)+SUMIFS('Report Pacote 0405'!R:R,'Report Pacote 0405'!$AV:$AV,$D$29,'Report Pacote 0405'!$AW:$AW,$A$39,'Report Pacote 0405'!$H:$H,$W38) -> 0 | AD38: =SUMIFS('Report Pacote 0405'!S:S,'Report Pacote 0405'!$AV:$AV,$D$29,'Report Pacote 0405'!$AW:$AW,$A$37,'Report Pacote 0405'!$H:$H,$W38)+SUMIFS('Report Pacote 0405'!S:S,'Report Pacote 0405'!$AV:$AV,$D$29,'Report Pacote 0405'!$AW:$AW,$A$38,'Report Pacote 0405'!$H:$H,$W38)+SUMIFS('Report Pacote 0405'!S:S,'Report Pacote 0405'!$AV:$AV,$D$29,'Report Pacote 0405'!$AW:$AW,$A$39,'Report Pacote 0405'!$H:$H,$W38) -> 0 | AE38: =SUMIFS('Report Pacote 0405'!T:T,'Report Pacote 0405'!$AV:$AV,$D$29,'Report Pacote 0405'!$AW:$AW,$A$37,'Report Pacote 0405'!$H:$H,$W38)+SUMIFS('Report Pacote 0405'!T:T,'Report Pacote 0405'!$AV:$AV,$D$29,'Report Pacote 0405'!$AW:$AW,$A$38,'Report Pacote 0405'!$H:$H,$W38)+SUMIFS('Report Pacote 0405'!T:T,'Report Pacote 0405'!$AV:$AV,$D$29,'Report Pacote 0405'!$AW:$AW,$A$39,'Report Pacote 0405'!$H:$H,$W38) -> 0 | AF38: =SUMIFS('Report Pacote 0405'!U:U,'Report Pacote 0405'!$AV:$AV,$D$29,'Report Pacote 0405'!$AW:$AW,$A$37,'Report Pacote 0405'!$H:$H,$W38)+SUMIFS('Report Pacote 0405'!U:U,'Report Pacote 0405'!$AV:$AV,$D$29,'Report Pacote 0405'!$AW:$AW,$A$38,'Report Pacote 0405'!$H:$H,$W38)+SUMIFS('Report Pacote 0405'!U:U,'Report Pacote 0405'!$AV:$AV,$D$29,'Report Pacote 0405'!$AW:$AW,$A$39,'Report Pacote 0405'!$H:$H,$W38) -> 0 | AG38: =SUMIFS('Report Pacote 0405'!V:V,'Report Pacote 0405'!$AV:$AV,$D$29,'Report Pacote 0405'!$AW:$AW,$A$37,'Report Pacote 0405'!$H:$H,$W38)+SUMIFS('Report Pacote 0405'!V:V,'Report Pacote 0405'!$AV:$AV,$D$29,'Report Pacote 0405'!$AW:$AW,$A$38,'Report Pacote 0405'!$H:$H,$W38)+SUMIFS('Report Pacote 0405'!V:V,'Report Pacote 0405'!$AV:$AV,$D$29,'Report Pacote 0405'!$AW:$AW,$A$39,'Report Pacote 0405'!$H:$H,$W38) -> 0 | AH38: =SUMIF($AA$7:$AG$7,"<="&$D$4,$AA38:$AG38) -> 45882.44
A39: Pacote 05 - Segmento 3.1 - 153+000 a 167+400
D41: Pacote 06 - km 167+300 0 a 225+000 | E41: m³ | G41: P | H41: 135586.47 | I41: =IFERROR((H42/H41),"-") -> 0.65637163 | K41: P | L41: 144455.64 | M41: =IFERROR((L42/L41),"-") -> 0.64035077 | O41: P | P41: 109394.08 | Q41: =IFERROR((P42/P41),"-") -> 0.79851343 | S41: P | T41: 123176.39 | U41: 0.71795487 | W41: P | X41: =SUMIFS('Report Pacote 06'!H:H,'Report Pacote 06'!$CH:$CH,$D$29,'Report Pacote 06'!$G:$G,'Report Consolidado Semanal'!$W41) -> 20449.398 | Y41: =IFERROR((X42/X41),"-") -> 0.76158964 | AA41: =SUMIFS('Report Pacote 06'!AG:AG,'Report Pacote 06'!$CH:$CH,$D$29,'Report Pacote 06'!$G:$G,'Report Consolidado Semanal'!$W41) -> 20449.398 | AB41: =SUMIFS('Report Pacote 06'!AH:AH,'Report Pacote 06'!$CH:$CH,$D$29,'Report Pacote 06'!$G:$G,'Report Consolidado Semanal'!$W41) -> 20449.398 | AC41: =SUMIFS('Report Pacote 06'!AI:AI,'Report Pacote 06'!$CH:$CH,$D$29,'Report Pacote 06'!$G:$G,'Report Consolidado Semanal'!$W41) -> 20449.398 | AD41: =SUMIFS('Report Pacote 06'!AJ:AJ,'Report Pacote 06'!$CH:$CH,$D$29,'Report Pacote 06'!$G:$G,'Report Consolidado Semanal'!$W41) -> 20449.398 | AE41: =SUMIFS('Report Pacote 06'!AK:AK,'Report Pacote 06'!$CH:$CH,$D$29,'Report Pacote 06'!$G:$G,'Report Consolidado Semanal'!$W41) -> 20449.398 | AF41: =SUMIFS('Report Pacote 06'!AL:AL,'Report Pacote 06'!$CH:$CH,$D$29,'Report Pacote 06'!$G:$G,'Report Consolidado Semanal'!$W41) -> 20449.398 | AG41: =SUMIFS('Report Pacote 06'!AM:AM,'Report Pacote 06'!$CH:$CH,$D$29,'Report Pacote 06'!$G:$G,'Report Consolidado Semanal'!$W41) -> 0 | AH41: =SUMIF($AA$7:$AG$7,"<="&$D$4,$AA41:$AG41) -> 40898.797 | AI41: =IFERROR((AH42/AH41),"-") -> 0.75864848 | AK41: =SUMIFS('Report Pacote 06'!BN:BN,'Report Pacote 06'!$CH:$CH,$D$29,'Report Pacote 06'!$G:$G,'Report Consolidado Semanal'!$W41) -> 483940.63 | AL41: =SUMIFS('Report Pacote 06'!BO:BO,'Report Pacote 06'!$CH:$CH,$D$29,'Report Pacote 06'!$G:$G,'Report Consolidado Semanal'!$W41) -> 215084.72 | AM41: =SUMIFS('Report Pacote 06'!BP:BP,'Report Pacote 06'!$CH:$CH,$D$29,'Report Pacote 06'!$G:$G,'Report Consolidado Semanal'!$W41) -> 172841.1 | AN41: =IFERROR((AM41/AL41),"-") -> 0.80359541 | AP41: =SUMIFS('Report Pacote 06'!BU:BU,'Report Pacote 06'!$CH:$CH,'Report Consolidado Semanal'!$D$49,'Report Pacote 06'!$G:$G,'Report Consolidado Semanal'!$W41) -> 57822.38 | AQ41: =SUMIFS('Report Pacote 06'!BX:BX,'Report Pacote 06'!$CH:$CH,'Report Consolidado Semanal'!$D$49,'Report Pacote 06'!$G:$G,'Report Consolidado Semanal'!$W41) -> 61971.608 | AR41: =IFERROR((AP41/AQ41),"-") -> 0.93304631 | AT41: =SUMIFS('Report Pacote 06'!CA:CA,'Report Pacote 06'!$CH:$CH,$D$29,'Report Pacote 06'!$G:$G,'Report Consolidado Semanal'!$W41) -> 4651600 | AU41: =SUMIFS('Report Pacote 06'!CB:CB,'Report Pacote 06'!$CH:$CH,$D$29,'Report Pacote 06'!$G:$G,'Report Consolidado Semanal'!$W41) -> 1360270.6 | AW41: =AK41/Quadros!$D$4 -> 17923.727 | AX41: =AM41/Quadros!$D$6 -> 14403.425 | AY41: =IF((AK41-AM41)/(Quadros!$D$4-Quadros!$D$6)<0,"-",(AK41-AM41)/(Quadros!$D$4-Quadros!$D$6)) -> 20739.969
G42: R | H42: 88995.11 | K42: R | L42: 92502.28 | O42: R | P42: 87352.638 | S42: R | T42: 88435.09 | W42: R | X42: =SUMIFS('Report Pacote 06'!H:H,'Report Pacote 06'!$CH:$CH,$D$29,'Report Pacote 06'!$G:$G,'Report Consolidado Semanal'!$W42) -> 15574.05 | AA42: =SUMIFS('Report Pacote 06'!AG:AG,'Report Pacote 06'!$CH:$CH,$D$29,'Report Pacote 06'!$G:$G,'Report Consolidado Semanal'!$W42) -> 15453.76 | AB42: =SUMIFS('Report Pacote 06'!AH:AH,'Report Pacote 06'!$CH:$CH,$D$29,'Report Pacote 06'!$G:$G,'Report Consolidado Semanal'!$W42) -> 15574.05 | AC42: =SUMIFS('Report Pacote 06'!AI:AI,'Report Pacote 06'!$CH:$CH,$D$29,'Report Pacote 06'!$G:$G,'Report Consolidado Semanal'!$W42) -> 0 | AD42: =SUMIFS('Report Pacote 06'!AJ:AJ,'Report Pacote 06'!$CH:$CH,$D$29,'Report Pacote 06'!$G:$G,'Report Consolidado Semanal'!$W42) -> 0 | AE42: =SUMIFS('Report Pacote 06'!AK:AK,'Report Pacote 06'!$CH:$CH,$D$29,'Report Pacote 06'!$G:$G,'Report Consolidado Semanal'!$W42) -> 0 | AF42: =SUMIFS('Report Pacote 06'!AL:AL,'Report Pacote 06'!$CH:$CH,$D$29,'Report Pacote 06'!$G:$G,'Report Consolidado Semanal'!$W42) -> 0 | AG42: =SUMIFS('Report Pacote 06'!AM:AM,'Report Pacote 06'!$CH:$CH,$D$29,'Report Pacote 06'!$G:$G,'Report Consolidado Semanal'!$W42) -> 0 | AH42: =SUMIF($AA$7:$AG$7,"<="&$D$4,$AA42:$AG42) -> 31027.81
A45: Aterro | D45: Pacote 07/08 - km 227+200 a 292+260 | E45: m³ | G45: P | H45: 28389.897 | I45: =IFERROR((H46/H45),"-") -> 1.6770186 | K45: P | L45: 36414 | M45: =IFERROR((L46/L45),"-") -> 1.3468728 | O45: P | P45: 30785.244 | Q45: =IFERROR((P46/P45),"-") -> 1.4295445 | S45: P | T45: 35867.085 | U45: 1.1092534 | W45: P | X45: =SUMIF($AA$7:$AG$7,"="&$D$4,$AA45:$AG45) -> 4438.454 | Y45: =IFERROR((X46/X45),"-") -> 1.4117971 | AA45: =SUMIFS('Report Pacote 07-08'!AL:AL,'Report Pacote 07-08'!$CB:$CB,$A45,'Report Pacote 07-08'!$J:$J,$W45) -> 4438.454 | AB45: =SUMIFS('Report Pacote 07-08'!AM:AM,'Report Pacote 07-08'!$CB:$CB,$A45,'Report Pacote 07-08'!$J:$J,$W45) -> 4438.454 | AC45: =SUMIFS('Report Pacote 07-08'!AN:AN,'Report Pacote 07-08'!$CB:$CB,$A45,'Report Pacote 07-08'!$J:$J,$W45) -> 4438.454 | AD45: =SUMIFS('Report Pacote 07-08'!AO:AO,'Report Pacote 07-08'!$CB:$CB,$A45,'Report Pacote 07-08'!$J:$J,$W45) -> 4438.454 | AE45: =SUMIFS('Report Pacote 07-08'!AP:AP,'Report Pacote 07-08'!$CB:$CB,$A45,'Report Pacote 07-08'!$J:$J,$W45) -> 4438.454 | AF45: =SUMIFS('Report Pacote 07-08'!AQ:AQ,'Report Pacote 07-08'!$CB:$CB,$A45,'Report Pacote 07-08'!$J:$J,$W45) -> 4438.454 | AG45: =SUMIFS('Report Pacote 07-08'!AR:AR,'Report Pacote 07-08'!$CB:$CB,$A45,'Report Pacote 07-08'!$J:$J,$W45) -> 0 | AH45: =SUMIF($AA$7:$AG$7,"<="&$D$4,$AA45:$AG45) -> 8876.908 | AI45: =IFERROR((AH46/AH45),"-") -> 1.3742119 | AK45: =SUMIFS('Report Pacote 07-08'!BM:BM,'Report Pacote 07-08'!$CB:$CB,$A45,'Report Pacote 07-08'!$J:$J,$W45) -> 157499.99 | AL45: =SUMIFS('Report Pacote 07-08'!BN:BN,'Report Pacote 07-08'!$CB:$CB,$A45,'Report Pacote 07-08'!$J:$J,$W45) -> 75529.237 | AM45: =SUMIFS('Report Pacote 07-08'!BO:BO,'Report Pacote 07-08'!$CB:$CB,$A45,'Report Pacote 07-08'!$J:$J,$W45) -> 95993.317 | AN45: =IFERROR((AM45/AL45),"-") -> 1.2709425 | AP45: =SUMIFS('Report Pacote 07-08'!AD:AD,'Report Pacote 07-08'!$CB:$CB,$A45,'Report Pacote 07-08'!$J:$J,$W45) -> 5977.8476 | AQ45: =SUMIFS('Report Pacote 07-08'!AI:AI,'Report Pacote 07-08'!$CB:$CB,$A45,'Report Pacote 07-08'!$J:$J,$W45) -> 5977.8476 | AR45: =IFERROR((AP45/AQ45),"-") -> 1 | AT45: =SUMIFS('Report Pacote 07-08'!BV:BV,'Report Pacote 07-08'!$CB:$CB,$A45,'Report Pacote 07-08'!$J:$J,$W45) -> 1988904.4 | AU45: =SUMIFS('Report Pacote 07-08'!BW:BW,'Report Pacote 07-08'!$CB:$CB,$A45,'Report Pacote 07-08'!$J:$J,$W45) -> 283335.16 | AW45: =AK45/Quadros!$D$4 -> 5833.3331 | AX45: =AM45/Quadros!$D$6 -> 7999.443 | AY45: =IF((AK45-AM45)/(Quadros!$D$4-Quadros!$D$6)<0,"-",(AK45-AM45)/(Quadros!$D$4-Quadros!$D$6)) -> 4100.4451
A46: Aterro | G46: R | H46: 47610.387 | K46: R | L46: 49045.027 | O46: R | P46: 44008.876 | S46: R | T46: 39785.688 | W46: R | X46: =SUMIF($AA$7:$AG$7,"="&$D$4,$AA46:$AG46) -> 6266.1965 | AA46: =SUMIFS('Report Pacote 07-08'!AL:AL,'Report Pacote 07-08'!$CB:$CB,$A46,'Report Pacote 07-08'!$J:$J,$W46) -> 5932.5563 | AB46: =SUMIFS('Report Pacote 07-08'!AM:AM,'Report Pacote 07-08'!$CB:$CB,$A46,'Report Pacote 07-08'!$J:$J,$W46) -> 6266.1965 | AC46: =SUMIFS('Report Pacote 07-08'!AN:AN,'Report Pacote 07-08'!$CB:$CB,$A46,'Report Pacote 07-08'!$J:$J,$W46) -> 0 | AD46: =SUMIFS('Report Pacote 07-08'!AO:AO,'Report Pacote 07-08'!$CB:$CB,$A46,'Report Pacote 07-08'!$J:$J,$W46) -> 0 | AE46: =SUMIFS('Report Pacote 07-08'!AP:AP,'Report Pacote 07-08'!$CB:$CB,$A46,'Report Pacote 07-08'!$J:$J,$W46) -> 0 | AF46: =SUMIFS('Report Pacote 07-08'!AQ:AQ,'Report Pacote 07-08'!$CB:$CB,$A46,'Report Pacote 07-08'!$J:$J,$W46) -> 0 | AG46: =SUMIFS('Report Pacote 07-08'!AR:AR,'Report Pacote 07-08'!$CB:$CB,$A46,'Report Pacote 07-08'!$J:$J,$W46) -> 0 | AH46: =SUMIF($AA$7:$AG$7,"<="&$D$4,$AA46:$AG46) -> 12198.753 | AP46: =SUMIFS('Report Pacote 07-08'!AC:AC,'Report Pacote 07-08'!$CB:$CB,$A46,'Report Pacote 07-08'!$J:$J,$W46) -> 0 | AQ46: =SUMIFS('Report Pacote 07-08'!AD:AD,'Report Pacote 07-08'!$CB:$CB,$A46,'Report Pacote 07-08'!$J:$J,$W46) -> 8772.1893
D49: Drenagem Superficial | E49: m | G49: P | H49: 9244.17 | I49: =IFERROR((H50/H49),"-") -> 0.70790563 | K49: P | L49: =L53+L57+L61+L65 -> 10980 | M49: =IFERROR((L50/L49),"-") -> 0.76466302 | O49: P | P49: 10525.979 | Q49: =IFERROR((P50/P49),"-") -> 0.64526065 | S49: P | T49: 11022.956 | U49: 0.820397 | W49: P | X49: =X53+X57+X61+X65 -> 1521.6726 | Y49: =IFERROR((X50/X49),"-") -> 1.1720655 | AA49: =AA53+AA57+AA61+AA65 -> 1406.6726 | AB49: =AB53+AB57+AB61+AB65 -> 1521.6726 | AC49: =AC53+AC57+AC61+AC65 -> 1632.6726 | AD49: =AD53+AD57+AD61+AD65 -> 1632.6726 | AE49: =AE53+AE57+AE61+AE65 -> 1542.6726 | AF49: =AF53+AF57+AF61+AF65 -> 1542.6726 | AG49: =AG53+AG57+AG61+AG65 -> 0 | AH49: =SUMIF($AA$7:$AG$7,"<="&$D$4,$AA49:$AG49) -> 2928.3452 | AI49: =IFERROR((AH50/AH49),"-") -> 1.1274286 | AK49: =AK53+AK57+AK61+AK65 -> 52401.283 | AL49: =AL53+AL57+AL61+AL65 -> 26120.494 | AM49: =AM53+AM57+AM61+AM65 -> 17411.2 | AN49: =IFERROR((AM49/AL49),"-") -> 0.6665724 | AP49: =AP53+AP57+AP61+AP65 -> 197382 | AQ49: =AQ53+AQ57+AQ61+AQ65 -> 215500.05 | AR49: =IFERROR((AP49/AQ49),"-") -> 0.91592553 | AT49: =AT53+AT57+AT61+AT65 -> 427960.15 | AU49: =AU53+AU57+AU61+AU65 -> 289361.64 | AW49: =AW53+AW57+AW61+AW65 -> 1940.7882 | AX49: =AX53+AX57+AX61+AX65 -> 1450.9333 | AY49: =IF((AK49-AM49)/(Quadros!$D$4-Quadros!$D$6)<0,"-",(AK49-AM49)/(Quadros!$D$4-Quadros!$D$6)) -> 2332.6722
G50: R | H50: 6544 | K50: R | L50: =L54+L58+L62+L66 -> 8396 | O50: R | P50: 6792 | S50: R | T50: 9043.2 | W50: R | X50: =X54+X58+X62+X66 -> 1783.5 | AA50: =AA54+AA58+AA62+AA66 -> 1518 | AB50: =AB54+AB58+AB62+AB66 -> 1783.5 | AC50: =AC54+AC58+AC62+AC66 -> 0 | AD50: =AD54+AD58+AD62+AD66 -> 0 | AE50: =AE54+AE58+AE62+AE66 -> 0 | AF50: =AF54+AF58+AF62+AF66 -> 0 | AG50: =AG54+AG58+AG62+AG66 -> 0 | AH50: =SUMIF($AA$7:$AG$7,"<="&$D$4,$AA50:$AG50) -> 3301.5 | BB50: saldo | BC50: necess 5
A53: Pacote 04 - Segmento 2.2B- Km 104+500 a Km 116+400 | D53: Pacote 04 - km 104+500 a 131+260 | E53: m | G53: P | H53: 2158 | I53: =IFERROR((H54/H53),"-") -> 0.62279889 | K53: P | L53: 2240 | M53: =IFERROR((L54/L53),"-") -> 0.74285714 | O53: P | P53: 2000 | Q53: =IFERROR((P54/P53),"-") -> 0.43175 | S53: P | T53: 2304 | U53: 0.73676215 | W53: P | X53: =SUMIF($AA$7:$AG$7,"="&$D$4,$AA53:$AG53) -> 280 | Y53: =IFERROR((X54/X53),"-") -> 0.82321429 | AA53: =SUMIFS('Report Pacote 0405'!P:P,'Report Pacote 0405'!$AV:$AV,$D$49,'Report Pacote 0405'!$AW:$AW,$A$53,'Report Pacote 0405'!$H:$H,$W53)+SUMIFS('Report Pacote 0405'!P:P,'Report Pacote 0405'!$AV:$AV,$D$49,'Report Pacote 0405'!$AW:$AW,$A$54,'Report Pacote 0405'!$H:$H,$W53) -> 315 | AB53: =SUMIFS('Report Pacote 0405'!Q:Q,'Report Pacote 0405'!$AV:$AV,$D$49,'Report Pacote 0405'!$AW:$AW,$A$53,'Report Pacote 0405'!$H:$H,$W53)+SUMIFS('Report Pacote 0405'!Q:Q,'Report Pacote 0405'!$AV:$AV,$D$49,'Report Pacote 0405'!$AW:$AW,$A$54,'Report Pacote 0405'!$H:$H,$W53) -> 280 | AC53: =SUMIFS('Report Pacote 0405'!R:R,'Report Pacote 0405'!$AV:$AV,$D$49,'Report Pacote 0405'!$AW:$AW,$A$53,'Report Pacote 0405'!$H:$H,$W53)+SUMIFS('Report Pacote 0405'!R:R,'Report Pacote 0405'!$AV:$AV,$D$49,'Report Pacote 0405'!$AW:$AW,$A$54,'Report Pacote 0405'!$H:$H,$W53) -> 280 | AD53: =SUMIFS('Report Pacote 0405'!S:S,'Report Pacote 0405'!$AV:$AV,$D$49,'Report Pacote 0405'!$AW:$AW,$A$53,'Report Pacote 0405'!$H:$H,$W53)+SUMIFS('Report Pacote 0405'!S:S,'Report Pacote 0405'!$AV:$AV,$D$49,'Report Pacote 0405'!$AW:$AW,$A$54,'Report Pacote 0405'!$H:$H,$W53) -> 280 | AE53: =SUMIFS('Report Pacote 0405'!T:T,'Report Pacote 0405'!$AV:$AV,$D$49,'Report Pacote 0405'!$AW:$AW,$A$53,'Report Pacote 0405'!$H:$H,$W53)+SUMIFS('Report Pacote 0405'!T:T,'Report Pacote 0405'!$AV:$AV,$D$49,'Report Pacote 0405'!$AW:$AW,$A$54,'Report Pacote 0405'!$H:$H,$W53) -> 240 | AF53: =SUMIFS('Report Pacote 0405'!U:U,'Report Pacote 0405'!$AV:$AV,$D$49,'Report Pacote 0405'!$AW:$AW,$A$53,'Report Pacote 0405'!$H:$H,$W53)+SUMIFS('Report Pacote 0405'!U:U,'Report Pacote 0405'!$AV:$AV,$D$49,'Report Pacote 0405'!$AW:$AW,$A$54,'Report Pacote 0405'!$H:$H,$W53) -> 240 | AG53: =SUMIFS('Report Pacote 0405'!V:V,'Report Pacote 0405'!$AV:$AV,$D$49,'Report Pacote 0405'!$AW:$AW,$A$53,'Report Pacote 0405'!$H:$H,$W53)+SUMIFS('Report Pacote 0405'!V:V,'Report Pacote 0405'!$AV:$AV,$D$49,'Report Pacote 0405'!$AW:$AW,$A$54,'Report Pacote 0405'!$H:$H,$W53) -> 0 | AH53: =SUMIF($AA$7:$AG$7,"<="&$D$4,$AA53:$AG53) -> 595 | AI53: =IFERROR((AH54/AH53),"-") -> 0.86134454 | AK53: =SUMIFS('Report Pacote 0405'!AA:AA,'Report Pacote 0405'!$AV:$AV,$D$49,'Report Pacote 0405'!$AW:$AW,$A$53,'Report Pacote 0405'!$H:$H,$W53)+SUMIFS('Report Pacote 0405'!AA:AA,'Report Pacote 0405'!$AV:$AV,$D$49,'Report Pacote 0405'!$AW:$AW,$A$54,'Report Pacote 0405'!$H:$H,$W53) -> 17422.16 | AL53: =SUMIFS('Report Pacote 0405'!AB:AB,'Report Pacote 0405'!$AV:$AV,$D$49,'Report Pacote 0405'!$AW:$AW,$A$53,'Report Pacote 0405'!$H:$H,$W53)+SUMIFS('Report Pacote 0405'!AB:AB,'Report Pacote 0405'!$AV:$AV,$D$49,'Report Pacote 0405'!$AW:$AW,$A$54,'Report Pacote 0405'!$H:$H,$W53) -> 9751.2 | AM53: =SUMIFS('Report Pacote 0405'!AC:AC,'Report Pacote 0405'!$AV:$AV,$D$49,'Report Pacote 0405'!$AW:$AW,$A$53,'Report Pacote 0405'!$H:$H,$W53)+SUMIFS('Report Pacote 0405'!AC:AC,'Report Pacote 0405'!$AV:$AV,$D$49,'Report Pacote 0405'!$AW:$AW,$A$54,'Report Pacote 0405'!$H:$H,$W53) -> 2941 | AN53: =IFERROR((AM53/AL53),"-") -> 0.30160391 | AP53: =SUMIFS('Report Pacote 0405'!AK:AK,'Report Pacote 0405'!$AV:$AV,$D$49,'Report Pacote 0405'!$AW:$AW,$A$53,'Report Pacote 0405'!$H:$H,$W53)+SUMIFS('Report Pacote 0405'!AK:AK,'Report Pacote 0405'!$AV:$AV,$D$49,'Report Pacote 0405'!$AW:$AW,$A$54,'Report Pacote 0405'!$H:$H,$W53) -> 64580.559 | AQ53: =SUMIFS('Report Pacote 0405'!AL:AL,'Report Pacote 0405'!$AV:$AV,$D$49,'Report Pacote 0405'!$AW:$AW,$A$53,'Report Pacote 0405'!$H:$H,$W53)+SUMIFS('Report Pacote 0405'!AL:AL,'Report Pacote 0405'!$AV:$AV,$D$49,'Report Pacote 0405'!$AW:$AW,$A$54,'Report Pacote 0405'!$H:$H,$W53) -> 76879.78 | AR53: =IFERROR((AP53/AQ53),"-") -> 0.84002008 | AT53: =SUMIFS('Report Pacote 0405'!AO:AO,'Report Pacote 0405'!$AV:$AV,$D$49,'Report Pacote 0405'!$AW:$AW,$A$53,'Report Pacote 0405'!$H:$H,$W53)+SUMIFS('Report Pacote 0405'!AO:AO,'Report Pacote 0405'!$AV:$AV,$D$49,'Report Pacote 0405'!$AW:$AW,$A$54,'Report Pacote 0405'!$H:$H,$W53) -> 120838.51 | AU53: =SUMIFS('Report Pacote 0405'!AP:AP,'Report Pacote 0405'!$AV:$AV,$D$49,'Report Pacote 0405'!$AW:$AW,$A$53,'Report Pacote 0405'!$H:$H,$W53)+SUMIFS('Report Pacote 0405'!AP:AP,'Report Pacote 0405'!$AV:$AV,$D$49,'Report Pacote 0405'!$AW:$AW,$A$54,'Report Pacote 0405'!$H:$H,$W53) -> 56257.951 | AW53: =AK53/Quadros!$D$4 -> 645.26519 | AX53: =AM53/Quadros!$D$6 -> 245.08333 | AY53: =IF((AK53-AM53)/(Quadros!$D$4-Quadros!$D$6)<0,"-",(AK53-AM53)/(Quadros!$D$4-Quadros!$D$6)) -> 965.41067 | BB53: =AU53/AK53 -> 3.2291031 | BC53: =AU53/5 -> 11251.59
A54: Pacote 04 - Segmento 2.3 - Km 116+517 a 131+241 | G54: R | H54: 1344 | K54: R | L54: 1664 | O54: R | P54: 863.5 | S54: R | T54: 1697.5 | W54: R | X54: =SUMIF($AA$7:$AG$7,"="&$D$4,$AA54:$AG54) -> 230.5 | AA54: =SUMIFS('Report Pacote 0405'!P:P,'Report Pacote 0405'!$AV:$AV,$D$49,'Report Pacote 0405'!$AW:$AW,$A$53,'Report Pacote 0405'!$H:$H,$W54)+SUMIFS('Report Pacote 0405'!P:P,'Report Pacote 0405'!$AV:$AV,$D$49,'Report Pacote 0405'!$AW:$AW,$A$54,'Report Pacote 0405'!$H:$H,$W54) -> 282 | AB54: =SUMIFS('Report Pacote 0405'!Q:Q,'Report Pacote 0405'!$AV:$AV,$D$49,'Report Pacote 0405'!$AW:$AW,$A$53,'Report Pacote 0405'!$H:$H,$W54)+SUMIFS('Report Pacote 0405'!Q:Q,'Report Pacote 0405'!$AV:$AV,$D$49,'Report Pacote 0405'!$AW:$AW,$A$54,'Report Pacote 0405'!$H:$H,$W54) -> 230.5 | AC54: =SUMIFS('Report Pacote 0405'!R:R,'Report Pacote 0405'!$AV:$AV,$D$49,'Report Pacote 0405'!$AW:$AW,$A$53,'Report Pacote 0405'!$H:$H,$W54)+SUMIFS('Report Pacote 0405'!R:R,'Report Pacote 0405'!$AV:$AV,$D$49,'Report Pacote 0405'!$AW:$AW,$A$54,'Report Pacote 0405'!$H:$H,$W54) -> 0 | AD54: =SUMIFS('Report Pacote 0405'!S:S,'Report Pacote 0405'!$AV:$AV,$D$49,'Report Pacote 0405'!$AW:$AW,$A$53,'Report Pacote 0405'!$H:$H,$W54)+SUMIFS('Report Pacote 0405'!S:S,'Report Pacote 0405'!$AV:$AV,$D$49,'Report Pacote 0405'!$AW:$AW,$A$54,'Report Pacote 0405'!$H:$H,$W54) -> 0 | AE54: =SUMIFS('Report Pacote 0405'!T:T,'Report Pacote 0405'!$AV:$AV,$D$49,'Report Pacote 0405'!$AW:$AW,$A$53,'Report Pacote 0405'!$H:$H,$W54)+SUMIFS('Report Pacote 0405'!T:T,'Report Pacote 0405'!$AV:$AV,$D$49,'Report Pacote 0405'!$AW:$AW,$A$54,'Report Pacote 0405'!$H:$H,$W54) -> 0 | AF54: =SUMIFS('Report Pacote 0405'!U:U,'Report Pacote 0405'!$AV:$AV,$D$49,'Report Pacote 0405'!$AW:$AW,$A$53,'Report Pacote 0405'!$H:$H,$W54)+SUMIFS('Report Pacote 0405'!U:U,'Report Pacote 0405'!$AV:$AV,$D$49,'Report Pacote 0405'!$AW:$AW,$A$54,'Report Pacote 0405'!$H:$H,$W54) -> 0 | AG54: =SUMIFS('Report Pacote 0405'!V:V,'Report Pacote 0405'!$AV:$AV,$D$49,'Report Pacote 0405'!$AW:$AW,$A$53,'Report Pacote 0405'!$H:$H,$W54)+SUMIFS('Report Pacote 0405'!V:V,'Report Pacote 0405'!$AV:$AV,$D$49,'Report Pacote 0405'!$AW:$AW,$A$54,'Report Pacote 0405'!$H:$H,$W54) -> 0 | AH54: =SUMIF($AA$7:$AG$7,"<="&$D$4,$AA54:$AG54) -> 512.5
A57: Pacote 05 - Segmento 2.4 - Km 131+260 a Km 138+000 | D57: Pacote 05 - km 131+260 a 167+300 | E57: m | G57: P | H57: 2666 | I57: =IFERROR((H58/H57),"-") -> 0.64403601 | K57: P | L57: 2960 | M57: =IFERROR((L58/L57),"-") -> 0.79155405 | O57: P | P57: 3400 | Q57: =IFERROR((P58/P57),"-") -> 0.55397059 | S57: P | T57: 3151 | U57: 0.66731196 | W57: P | X57: =SUMIF($AA$7:$AG$7,"="&$D$4,$AA57:$AG57) -> 539 | Y57: =IFERROR((X58/X57),"-") -> 0.89424861 | AA57: =SUMIFS('Report Pacote 0405'!P:P,'Report Pacote 0405'!$AV:$AV,$D$49,'Report Pacote 0405'!$AW:$AW,$A$57,'Report Pacote 0405'!$H:$H,$W57)+SUMIFS('Report Pacote 0405'!P:P,'Report Pacote 0405'!$AV:$AV,$D$49,'Report Pacote 0405'!$AW:$AW,$A$58,'Report Pacote 0405'!$H:$H,$W57)+SUMIFS('Report Pacote 0405'!P:P,'Report Pacote 0405'!$AV:$AV,$D$49,'Report Pacote 0405'!$AW:$AW,$A$59,'Report Pacote 0405'!$H:$H,$W57) -> 539 | AB57: =SUMIFS('Report Pacote 0405'!Q:Q,'Report Pacote 0405'!$AV:$AV,$D$49,'Report Pacote 0405'!$AW:$AW,$A$57,'Report Pacote 0405'!$H:$H,$W57)+SUMIFS('Report Pacote 0405'!Q:Q,'Report Pacote 0405'!$AV:$AV,$D$49,'Report Pacote 0405'!$AW:$AW,$A$58,'Report Pacote 0405'!$H:$H,$W57)+SUMIFS('Report Pacote 0405'!Q:Q,'Report Pacote 0405'!$AV:$AV,$D$49,'Report Pacote 0405'!$AW:$AW,$A$59,'Report Pacote 0405'!$H:$H,$W57) -> 539 | AC57: =SUMIFS('Report Pacote 0405'!R:R,'Report Pacote 0405'!$AV:$AV,$D$49,'Report Pacote 0405'!$AW:$AW,$A$57,'Report Pacote 0405'!$H:$H,$W57)+SUMIFS('Report Pacote 0405'!R:R,'Report Pacote 0405'!$AV:$AV,$D$49,'Report Pacote 0405'!$AW:$AW,$A$58,'Report Pacote 0405'!$H:$H,$W57)+SUMIFS('Report Pacote 0405'!R:R,'Report Pacote 0405'!$AV:$AV,$D$49,'Report Pacote 0405'!$AW:$AW,$A$59,'Report Pacote 0405'!$H:$H,$W57) -> 550 | AD57: =SUMIFS('Report Pacote 0405'!S:S,'Report Pacote 0405'!$AV:$AV,$D$49,'Report Pacote 0405'!$AW:$AW,$A$57,'Report Pacote 0405'!$H:$H,$W57)+SUMIFS('Report Pacote 0405'!S:S,'Report Pacote 0405'!$AV:$AV,$D$49,'Report Pacote 0405'!$AW:$AW,$A$58,'Report Pacote 0405'!$H:$H,$W57)+SUMIFS('Report Pacote 0405'!S:S,'Report Pacote 0405'!$AV:$AV,$D$49,'Report Pacote 0405'!$AW:$AW,$A$59,'Report Pacote 0405'!$H:$H,$W57) -> 550 | AE57: =SUMIFS('Report Pacote 0405'!T:T,'Report Pacote 0405'!$AV:$AV,$D$49,'Report Pacote 0405'!$AW:$AW,$A$57,'Report Pacote 0405'!$H:$H,$W57)+SUMIFS('Report Pacote 0405'!T:T,'Report Pacote 0405'!$AV:$AV,$D$49,'Report Pacote 0405'!$AW:$AW,$A$58,'Report Pacote 0405'!$H:$H,$W57)+SUMIFS('Report Pacote 0405'!T:T,'Report Pacote 0405'!$AV:$AV,$D$49,'Report Pacote 0405'!$AW:$AW,$A$59,'Report Pacote 0405'!$H:$H,$W57) -> 500 | AF57: =SUMIFS('Report Pacote 0405'!U:U,'Report Pacote 0405'!$AV:$AV,$D$49,'Report Pacote 0405'!$AW:$AW,$A$57,'Report Pacote 0405'!$H:$H,$W57)+SUMIFS('Report Pacote 0405'!U:U,'Report Pacote 0405'!$AV:$AV,$D$49,'Report Pacote 0405'!$AW:$AW,$A$58,'Report Pacote 0405'!$H:$H,$W57)+SUMIFS('Report Pacote 0405'!U:U,'Report Pacote 0405'!$AV:$AV,$D$49,'Report Pacote 0405'!$AW:$AW,$A$59,'Report Pacote 0405'!$H:$H,$W57) -> 500 | AG57: =SUMIFS('Report Pacote 0405'!V:V,'Report Pacote 0405'!$AV:$AV,$D$49,'Report Pacote 0405'!$AW:$AW,$A$57,'Report Pacote 0405'!$H:$H,$W57)+SUMIFS('Report Pacote 0405'!V:V,'Report Pacote 0405'!$AV:$AV,$D$49,'Report Pacote 0405'!$AW:$AW,$A$58,'Report Pacote 0405'!$H:$H,$W57)+SUMIFS('Report Pacote 0405'!V:V,'Report Pacote 0405'!$AV:$AV,$D$49,'Report Pacote 0405'!$AW:$AW,$A$59,'Report Pacote 0405'!$H:$H,$W57) -> 0 | AH57: =SUMIF($AA$7:$AG$7,"<="&$D$4,$AA57:$AG57) -> 1078 | AI57: =IFERROR((AH58/AH57),"-") -> 0.88961039 | AK57: =SUMIFS('Report Pacote 0405'!AA:AA,'Report Pacote 0405'!$AV:$AV,$D$49,'Report Pacote 0405'!$AW:$AW,$A$58,'Report Pacote 0405'!$H:$H,$W57)+SUMIFS('Report Pacote 0405'!AA:AA,'Report Pacote 0405'!$AV:$AV,$D$49,'Report Pacote 0405'!$AW:$AW,$A$57,'Report Pacote 0405'!$H:$H,$W57)+SUMIFS('Report Pacote 0405'!AA:AA,'Report Pacote 0405'!$AV:$AV,$D$49,'Report Pacote 0405'!$AW:$AW,$A$59,'Report Pacote 0405'!$H:$H,$W57) -> 7657.7 | AL57: =SUMIFS('Report Pacote 0405'!AB:AB,'Report Pacote 0405'!$AV:$AV,$D$49,'Report Pacote 0405'!$AW:$AW,$A$58,'Report Pacote 0405'!$H:$H,$W57)+SUMIFS('Report Pacote 0405'!AB:AB,'Report Pacote 0405'!$AV:$AV,$D$49,'Report Pacote 0405'!$AW:$AW,$A$57,'Report Pacote 0405'!$H:$H,$W57)+SUMIFS('Report Pacote 0405'!AB:AB,'Report Pacote 0405'!$AV:$AV,$D$49,'Report Pacote 0405'!$AW:$AW,$A$59,'Report Pacote 0405'!$H:$H,$W57) -> 3276.92 | AM57: =SUMIFS('Report Pacote 0405'!AC:AC,'Report Pacote 0405'!$AV:$AV,$D$49,'Report Pacote 0405'!$AW:$AW,$A$58,'Report Pacote 0405'!$H:$H,$W57)+SUMIFS('Report Pacote 0405'!AC:AC,'Report Pacote 0405'!$AV:$AV,$D$49,'Report Pacote 0405'!$AW:$AW,$A$57,'Report Pacote 0405'!$H:$H,$W57)+SUMIFS('Report Pacote 0405'!AC:AC,'Report Pacote 0405'!$AV:$AV,$D$49,'Report Pacote 0405'!$AW:$AW,$A$59,'Report Pacote 0405'!$H:$H,$W57) -> 4382.2 | AN57: =IFERROR((AM57/AL57),"-") -> 1.3372923 | AP57: =SUMIFS('Report Pacote 0405'!AK:AK,'Report Pacote 0405'!$AV:$AV,$D$49,'Report Pacote 0405'!$AW:$AW,$A$58,'Report Pacote 0405'!$H:$H,$W57)+SUMIFS('Report Pacote 0405'!AK:AK,'Report Pacote 0405'!$AV:$AV,$D$49,'Report Pacote 0405'!$AW:$AW,$A$57,'Report Pacote 0405'!$H:$H,$W57)+SUMIFS('Report Pacote 0405'!AJ:AJ,'Report Pacote 0405'!$AV:$AV,$D$49,'Report Pacote 0405'!$AW:$AW,$A$59,'Report Pacote 0405'!$H:$H,$W57) -> 11540.508 | AQ57: =SUMIFS('Report Pacote 0405'!AL:AL,'Report Pacote 0405'!$AV:$AV,$D$49,'Report Pacote 0405'!$AW:$AW,$A$58,'Report Pacote 0405'!$H:$H,$W57)+SUMIFS('Report Pacote 0405'!AL:AL,'Report Pacote 0405'!$AV:$AV,$D$49,'Report Pacote 0405'!$AW:$AW,$A$57,'Report Pacote 0405'!$H:$H,$W57)+SUMIFS('Report Pacote 0405'!AK:AK,'Report Pacote 0405'!$AV:$AV,$D$49,'Report Pacote 0405'!$AW:$AW,$A$59,'Report Pacote 0405'!$H:$H,$W57) -> 16133.081 | AR57: =IFERROR((AP57/AQ57),"-") -> 0.71533193 | AT57: =SUMIFS('Report Pacote 0405'!AO:AO,'Report Pacote 0405'!$AV:$AV,$D$49,'Report Pacote 0405'!$AW:$AW,$A$58,'Report Pacote 0405'!$H:$H,$W57)+SUMIFS('Report Pacote 0405'!AO:AO,'Report Pacote 0405'!$AV:$AV,$D$49,'Report Pacote 0405'!$AW:$AW,$A$57,'Report Pacote 0405'!$H:$H,$W57)+SUMIFS('Report Pacote 0405'!AN:AN,'Report Pacote 0405'!$AV:$AV,$D$49,'Report Pacote 0405'!$AW:$AW,$A$59,'Report Pacote 0405'!$H:$H,$W57) -> 81155.7 | AU57: =SUMIFS('Report Pacote 0405'!AP:AP,'Report Pacote 0405'!$AV:$AV,$D$49,'Report Pacote 0405'!$AW:$AW,$A$58,'Report Pacote 0405'!$H:$H,$W57)+SUMIFS('Report Pacote 0405'!AP:AP,'Report Pacote 0405'!$AV:$AV,$D$49,'Report Pacote 0405'!$AW:$AW,$A$57,'Report Pacote 0405'!$H:$H,$W57)+SUMIFS('Report Pacote 0405'!AO:AO,'Report Pacote 0405'!$AV:$AV,$D$49,'Report Pacote 0405'!$AW:$AW,$A$59,'Report Pacote 0405'!$H:$H,$W57) -> 124333.41 | AW57: =AK57/Quadros!$D$4 -> 283.61852 | AX57: =AM57/Quadros!$D$6 -> 365.18333 | AY57: =IF((AK57-AM57)/(Quadros!$D$4-Quadros!$D$6)<0,"-",(AK57-AM57)/(Quadros!$D$4-Quadros!$D$6)) -> 218.36667 | BB57: =AU57/AK57 -> 16.236391 | BC57: =AU57/5 -> 24866.682
A58: Pacote 05 - Segmento 2.5 - 138+160 a 153+420 | G58: R | H58: 1717 | K58: R | L58: 2343 | O58: R | P58: 1883.5 | S58: R | T58: 2102.7 | W58: R | X58: =SUMIF($AA$7:$AG$7,"="&$D$4,$AA58:$AG58) -> 482 | AA58: =SUMIFS('Report Pacote 0405'!P:P,'Report Pacote 0405'!$AV:$AV,$D$49,'Report Pacote 0405'!$AW:$AW,$A$57,'Report Pacote 0405'!$H:$H,$W58)+SUMIFS('Report Pacote 0405'!P:P,'Report Pacote 0405'!$AV:$AV,$D$49,'Report Pacote 0405'!$AW:$AW,$A$58,'Report Pacote 0405'!$H:$H,$W58)+SUMIFS('Report Pacote 0405'!P:P,'Report Pacote 0405'!$AV:$AV,$D$49,'Report Pacote 0405'!$AW:$AW,$A$59,'Report Pacote 0405'!$H:$H,$W58) -> 477 | AB58: =SUMIFS('Report Pacote 0405'!Q:Q,'Report Pacote 0405'!$AV:$AV,$D$49,'Report Pacote 0405'!$AW:$AW,$A$57,'Report Pacote 0405'!$H:$H,$W58)+SUMIFS('Report Pacote 0405'!Q:Q,'Report Pacote 0405'!$AV:$AV,$D$49,'Report Pacote 0405'!$AW:$AW,$A$58,'Report Pacote 0405'!$H:$H,$W58)+SUMIFS('Report Pacote 0405'!Q:Q,'Report Pacote 0405'!$AV:$AV,$D$49,'Report Pacote 0405'!$AW:$AW,$A$59,'Report Pacote 0405'!$H:$H,$W58) -> 482 | AC58: =SUMIFS('Report Pacote 0405'!R:R,'Report Pacote 0405'!$AV:$AV,$D$49,'Report Pacote 0405'!$AW:$AW,$A$57,'Report Pacote 0405'!$H:$H,$W58)+SUMIFS('Report Pacote 0405'!R:R,'Report Pacote 0405'!$AV:$AV,$D$49,'Report Pacote 0405'!$AW:$AW,$A$58,'Report Pacote 0405'!$H:$H,$W58)+SUMIFS('Report Pacote 0405'!R:R,'Report Pacote 0405'!$AV:$AV,$D$49,'Report Pacote 0405'!$AW:$AW,$A$59,'Report Pacote 0405'!$H:$H,$W58) -> 0 | AD58: =SUMIFS('Report Pacote 0405'!S:S,'Report Pacote 0405'!$AV:$AV,$D$49,'Report Pacote 0405'!$AW:$AW,$A$57,'Report Pacote 0405'!$H:$H,$W58)+SUMIFS('Report Pacote 0405'!S:S,'Report Pacote 0405'!$AV:$AV,$D$49,'Report Pacote 0405'!$AW:$AW,$A$58,'Report Pacote 0405'!$H:$H,$W58)+SUMIFS('Report Pacote 0405'!S:S,'Report Pacote 0405'!$AV:$AV,$D$49,'Report Pacote 0405'!$AW:$AW,$A$59,'Report Pacote 0405'!$H:$H,$W58) -> 0 | AE58: =SUMIFS('Report Pacote 0405'!T:T,'Report Pacote 0405'!$AV:$AV,$D$49,'Report Pacote 0405'!$AW:$AW,$A$57,'Report Pacote 0405'!$H:$H,$W58)+SUMIFS('Report Pacote 0405'!T:T,'Report Pacote 0405'!$AV:$AV,$D$49,'Report Pacote 0405'!$AW:$AW,$A$58,'Report Pacote 0405'!$H:$H,$W58)+SUMIFS('Report Pacote 0405'!T:T,'Report Pacote 0405'!$AV:$AV,$D$49,'Report Pacote 0405'!$AW:$AW,$A$59,'Report Pacote 0405'!$H:$H,$W58) -> 0 | AF58: =SUMIFS('Report Pacote 0405'!U:U,'Report Pacote 0405'!$AV:$AV,$D$49,'Report Pacote 0405'!$AW:$AW,$A$57,'Report Pacote 0405'!$H:$H,$W58)+SUMIFS('Report Pacote 0405'!U:U,'Report Pacote 0405'!$AV:$AV,$D$49,'Report Pacote 0405'!$AW:$AW,$A$58,'Report Pacote 0405'!$H:$H,$W58)+SUMIFS('Report Pacote 0405'!U:U,'Report Pacote 0405'!$AV:$AV,$D$49,'Report Pacote 0405'!$AW:$AW,$A$59,'Report Pacote 0405'!$H:$H,$W58) -> 0 | AG58: =SUMIFS('Report Pacote 0405'!V:V,'Report Pacote 0405'!$AV:$AV,$D$49,'Report Pacote 0405'!$AW:$AW,$A$57,'Report Pacote 0405'!$H:$H,$W58)+SUMIFS('Report Pacote 0405'!V:V,'Report Pacote 0405'!$AV:$AV,$D$49,'Report Pacote 0405'!$AW:$AW,$A$58,'Report Pacote 0405'!$H:$H,$W58)+SUMIFS('Report Pacote 0405'!V:V,'Report Pacote 0405'!$AV:$AV,$D$49,'Report Pacote 0405'!$AW:$AW,$A$59,'Report Pacote 0405'!$H:$H,$W58) -> 0 | AH58: =SUMIF($AA$7:$AG$7,"<="&$D$4,$AA58:$AG58) -> 959
A59: Pacote 05 - Segmento 3.1 - 153+000 a 167+400
A61: Pacote 05 - Segmento 3.1 - 153+000 a 167+400 | D61: Pacote 06 - km 167+300 0 a 225+000 | E61: m | G61: P | H61: 3250 | I61: =IFERROR((H62/H61),"-") -> 0.54892308 | K61: P | L61: 3380 | M61: =IFERROR((L62/L61),"-") -> 0.59408284 | O61: P | P61: 2340 | Q61: =IFERROR((P62/P61),"-") -> 0.85854701 | S61: P | T61: 2300 | U61: 0.63478261 | W61: P | X61: =SUMIF($AA$7:$AG$7,"="&$D$4,$AA61:$AG61) -> 250 | Y61: =IFERROR((X62/X61),"-") -> 1.304 | AA61: =SUMIFS('Report Pacote 06'!AG:AG,'Report Pacote 06'!$CH:$CH,$D$49,'Report Pacote 06'!$G:$G,'Report Consolidado Semanal'!$W61) -> 100 | AB61: =SUMIFS('Report Pacote 06'!AH:AH,'Report Pacote 06'!$CH:$CH,$D$49,'Report Pacote 06'!$G:$G,'Report Consolidado Semanal'!$W61) -> 250 | AC61: =SUMIFS('Report Pacote 06'!AI:AI,'Report Pacote 06'!$CH:$CH,$D$49,'Report Pacote 06'!$G:$G,'Report Consolidado Semanal'!$W61) -> 350 | AD61: =SUMIFS('Report Pacote 06'!AJ:AJ,'Report Pacote 06'!$CH:$CH,$D$49,'Report Pacote 06'!$G:$G,'Report Consolidado Semanal'!$W61) -> 350 | AE61: =SUMIFS('Report Pacote 06'!AK:AK,'Report Pacote 06'!$CH:$CH,$D$49,'Report Pacote 06'!$G:$G,'Report Consolidado Semanal'!$W61) -> 350 | AF61: =SUMIFS('Report Pacote 06'!AL:AL,'Report Pacote 06'!$CH:$CH,$D$49,'Report Pacote 06'!$G:$G,'Report Consolidado Semanal'!$W61) -> 350 | AG61: =SUMIFS('Report Pacote 06'!AM:AM,'Report Pacote 06'!$CH:$CH,$D$49,'Report Pacote 06'!$G:$G,'Report Consolidado Semanal'!$W61) -> 0 | AH61: =SUMIF($AA$7:$AG$7,"<="&$D$4,$AA61:$AG61) -> 350 | AI61: =IFERROR((AH62/AH61),"-") -> 1.36 | AK61: =SUMIFS('Report Pacote 06'!BN:BN,'Report Pacote 06'!$CH:$CH,$D$49,'Report Pacote 06'!$G:$G,'Report Consolidado Semanal'!$W61) -> 13799.46 | AL61: =SUMIFS('Report Pacote 06'!BO:BO,'Report Pacote 06'!$CH:$CH,$D$49,'Report Pacote 06'!$G:$G,'Report Consolidado Semanal'!$W61) -> 6133.0933 | AM61: =SUMIFS('Report Pacote 06'!BP:BP,'Report Pacote 06'!$CH:$CH,$D$49,'Report Pacote 06'!$G:$G,'Report Consolidado Semanal'!$W61) -> 2915 | AN61: =IFERROR((AM61/AL61),"-") -> 0.47529034 | AP61: =SUMIFS('Report Pacote 06'!BU:BU,'Report Pacote 06'!$CH:$CH,'Report Consolidado Semanal'!$D$49,'Report Pacote 06'!$G:$G,'Report Consolidado Semanal'!$W61) -> 57822.38 | AQ61: =SUMIFS('Report Pacote 06'!BX:BX,'Report Pacote 06'!$CH:$CH,'Report Consolidado Semanal'!$D$49,'Report Pacote 06'!$G:$G,'Report Consolidado Semanal'!$W61) -> 61971.608 | AR61: =IFERROR((AP61/AQ61),"-") -> 0.93304631 | AT61: =SUMIFS('Report Pacote 06'!CA:CA,'Report Pacote 06'!$CH:$CH,$D$49,'Report Pacote 06'!$G:$G,'Report Consolidado Semanal'!$W61) -> 127599 | AU61: =SUMIFS('Report Pacote 06'!CB:CB,'Report Pacote 06'!$CH:$CH,$D$49,'Report Pacote 06'!$G:$G,'Report Consolidado Semanal'!$W61) -> 69776.62 | AW61: =AK61/Quadros!$D$4 -> 511.09111 | AX61: =AM61/Quadros!$D$6 -> 242.91667 | AY61: =IF((AK61-AM61)/(Quadros!$D$4-Quadros!$D$6)<0,"-",(AK61-AM61)/(Quadros!$D$4-Quadros!$D$6)) -> 725.63067 | BB61: =AU61/AK61 -> 5.0564747 | BC61: =AU61/5 -> 13955.324
G62: R | H62: 1784 | K62: R | L62: 2008 | O62: R | P62: 2009 | S62: R | T62: 1460 | W62: R | X62: =SUMIF($AA$7:$AG$7,"="&$D$4,$AA62:$AG62) -> 326 | AA62: =SUMIFS('Report Pacote 06'!AG:AG,'Report Pacote 06'!$CH:$CH,$D$49,'Report Pacote 06'!$G:$G,'Report Consolidado Semanal'!$W62) -> 150 | AB62: =SUMIFS('Report Pacote 06'!AH:AH,'Report Pacote 06'!$CH:$CH,$D$49,'Report Pacote 06'!$G:$G,'Report Consolidado Semanal'!$W62) -> 326 | AC62: =SUMIFS('Report Pacote 06'!AI:AI,'Report Pacote 06'!$CH:$CH,$D$49,'Report Pacote 06'!$G:$G,'Report Consolidado Semanal'!$W62) -> 0 | AD62: =SUMIFS('Report Pacote 06'!AJ:AJ,'Report Pacote 06'!$CH:$CH,$D$49,'Report Pacote 06'!$G:$G,'Report Consolidado Semanal'!$W62) -> 0 | AE62: =SUMIFS('Report Pacote 06'!AK:AK,'Report Pacote 06'!$CH:$CH,$D$49,'Report Pacote 06'!$G:$G,'Report Consolidado Semanal'!$W62) -> 0 | AF62: =SUMIFS('Report Pacote 06'!AL:AL,'Report Pacote 06'!$CH:$CH,$D$49,'Report Pacote 06'!$G:$G,'Report Consolidado Semanal'!$W62) -> 0 | AG62: =SUMIFS('Report Pacote 06'!AM:AM,'Report Pacote 06'!$CH:$CH,$D$49,'Report Pacote 06'!$G:$G,'Report Consolidado Semanal'!$W62) -> 0 | AH62: =SUMIF($AA$7:$AG$7,"<="&$D$4,$AA62:$AG62) -> 476
A65: Drenagem superficial | D65: Pacote 07/08 - km 227+200 a 292+260 | E65: m | G65: P | H65: 1170.17 | I65: =IFERROR((H66/H65),"-") -> 1.4519258 | K65: P | L65: 2400 | M65: =IFERROR((L66/L65),"-") -> 0.99208333 | O65: P | P65: 2785.979 | Q65: =IFERROR((P66/P65),"-") -> 0.73080235 | S65: P | T65: 3267.956 | U65: 1.1576043 | W65: P | X65: =SUMIF($AA$7:$AG$7,"="&$D$4,$AA65:$AG65) -> 452.6726 | Y65: =IFERROR((X66/X65),"-") -> 1.6457811 | AA65: =SUMIFS('Report Pacote 07-08'!AL:AL,'Report Pacote 07-08'!$CB:$CB,$A65,'Report Pacote 07-08'!$J:$J,$W65) -> 452.6726 | AB65: =SUMIFS('Report Pacote 07-08'!AM:AM,'Report Pacote 07-08'!$CB:$CB,$A65,'Report Pacote 07-08'!$J:$J,$W65) -> 452.6726 | AC65: =SUMIFS('Report Pacote 07-08'!AN:AN,'Report Pacote 07-08'!$CB:$CB,$A65,'Report Pacote 07-08'!$J:$J,$W65) -> 452.6726 | AD65: =SUMIFS('Report Pacote 07-08'!AO:AO,'Report Pacote 07-08'!$CB:$CB,$A65,'Report Pacote 07-08'!$J:$J,$W65) -> 452.6726 | AE65: =SUMIFS('Report Pacote 07-08'!AP:AP,'Report Pacote 07-08'!$CB:$CB,$A65,'Report Pacote 07-08'!$J:$J,$W65) -> 452.6726 | AF65: =SUMIFS('Report Pacote 07-08'!AQ:AQ,'Report Pacote 07-08'!$CB:$CB,$A65,'Report Pacote 07-08'!$J:$J,$W65) -> 452.6726 | AG65: =SUMIFS('Report Pacote 07-08'!AR:AR,'Report Pacote 07-08'!$CB:$CB,$A65,'Report Pacote 07-08'!$J:$J,$W65) -> 0 | AH65: =SUMIF($AA$7:$AG$7,"<="&$D$4,$AA65:$AG65) -> 905.3452 | AI65: =IFERROR((AH66/AH65),"-") -> 1.4955621 | AK65: =SUMIFS('Report Pacote 07-08'!BM:BM,'Report Pacote 07-08'!$CB:$CB,$D49,'Report Pacote 07-08'!$J:$J,$W65) -> 13521.962 | AL65: =SUMIFS('Report Pacote 07-08'!BN:BN,'Report Pacote 07-08'!$CB:$CB,$D49,'Report Pacote 07-08'!$J:$J,$W65) -> 6959.2802 | AM65: =SUMIFS('Report Pacote 07-08'!BO:BO,'Report Pacote 07-08'!$CB:$CB,$D49,'Report Pacote 07-08'!$J:$J,$W65) -> 7173 | AN65: =IFERROR((AM65/AL65),"-") -> 1.03071 | AP65: =SUMIFS('Report Pacote 07-08'!BR:BR,'Report Pacote 07-08'!$CB:$CB,$A65,'Report Pacote 07-08'!$J:$J,$W65) -> 63438.553 | AQ65: =SUMIFS('Report Pacote 07-08'!BS:BS,'Report Pacote 07-08'!$CB:$CB,$A65,'Report Pacote 07-08'!$J:$J,$W65) -> 60515.583 | AR65: =IFERROR((AP65/AQ65),"-") -> 1.0483011 | AT65: =SUMIFS('Report Pacote 07-08'!BV:BV,'Report Pacote 07-08'!$CB:$CB,$A65,'Report Pacote 07-08'!$J:$J,$W65) -> 98366.94 | AU65: =SUMIFS('Report Pacote 07-08'!BW:BW,'Report Pacote 07-08'!$CB:$CB,$A65,'Report Pacote 07-08'!$J:$J,$W65) -> 38993.66 | AW65: =AK65/Quadros!$D$4 -> 500.81343 | AX65: =AM65/Quadros!$D$6 -> 597.75 | AY65: =IF((AK65-AM65)/(Quadros!$D$4-Quadros!$D$6)<0,"-",(AK65-AM65)/(Quadros!$D$4-Quadros!$D$6)) -> 423.26417 | BB65: =AU65/AK65 -> 2.8837279 | BC65: =AU65/5 -> 7798.732
A66: Drenagem superficial | G66: R | H66: 1699 | K66: R | L66: 2381 | O66: R | P66: 2036 | S66: R | T66: 3783 | W66: R | X66: =SUMIF($AA$7:$AG$7,"="&$D$4,$AA66:$AG66) -> 745 | AA66: =SUMIFS('Report Pacote 07-08'!AL:AL,'Report Pacote 07-08'!$CB:$CB,$A66,'Report Pacote 07-08'!$J:$J,$W66) -> 609 | AB66: =SUMIFS('Report Pacote 07-08'!AM:AM,'Report Pacote 07-08'!$CB:$CB,$A66,'Report Pacote 07-08'!$J:$J,$W66) -> 745 | AC66: =SUMIFS('Report Pacote 07-08'!AN:AN,'Report Pacote 07-08'!$CB:$CB,$A66,'Report Pacote 07-08'!$J:$J,$W66) -> 0 | AD66: =SUMIFS('Report Pacote 07-08'!AO:AO,'Report Pacote 07-08'!$CB:$CB,$A66,'Report Pacote 07-08'!$J:$J,$W66) -> 0 | AE66: =SUMIFS('Report Pacote 07-08'!AP:AP,'Report Pacote 07-08'!$CB:$CB,$A66,'Report Pacote 07-08'!$J:$J,$W66) -> 0 | AF66: =SUMIFS('Report Pacote 07-08'!AQ:AQ,'Report Pacote 07-08'!$CB:$CB,$A66,'Report Pacote 07-08'!$J:$J,$W66) -> 0 | AG66: =SUMIFS('Report Pacote 07-08'!AR:AR,'Report Pacote 07-08'!$CB:$CB,$A66,'Report Pacote 07-08'!$J:$J,$W66) -> 0 | AH66: =SUMIF($AA$7:$AG$7,"<="&$D$4,$AA66:$AG66) -> 1354 | AP66: =SUMIFS('Report Pacote 07-08'!AC:AC,'Report Pacote 07-08'!$CB:$CB,$A66,'Report Pacote 07-08'!$J:$J,$W66) -> 0 | AQ66: =SUMIFS('Report Pacote 07-08'!AD:AD,'Report Pacote 07-08'!$CB:$CB,$A66,'Report Pacote 07-08'!$J:$J,$W66) -> 681
D69: Ponte sobre o Rio Araguaia
A73: Pilares | D73: Pilares | E73: Etapas | G73: P | H73: 8 | I73: =IFERROR((H74/H73),"-") -> 0.875 | K73: P | L73: 8 | M73: =IFERROR((L74/L73),"-") -> 0.875 | O73: P | P73: 7 | Q73: =IFERROR((P74/P73),"-") -> 1 | S73: P | T73: 6 | U73: 1.1666667 | W73: P | X73: =SUMIF($AA$7:$AG$7,"="&$D$4,$AA73:$AG73) -> 0 | Y73: =IFERROR((X74/X73),"-") -> - | AA73: =SUMIFS('Report Pacote 07'!M:M,'Report Pacote 07'!$AY:$AY,$D73,'Report Pacote 07'!$I:$I,'Report Consolidado Semanal'!$W73) -> 0 | AB73: =SUMIFS('Report Pacote 07'!N:N,'Report Pacote 07'!$AY:$AY,$D73,'Report Pacote 07'!$I:$I,'Report Consolidado Semanal'!$W73) -> 0 | AC73: =SUMIFS('Report Pacote 07'!O:O,'Report Pacote 07'!$AY:$AY,$D73,'Report Pacote 07'!$I:$I,'Report Consolidado Semanal'!$W73) -> 4 | AD73: =SUMIFS('Report Pacote 07'!P:P,'Report Pacote 07'!$AY:$AY,$D73,'Report Pacote 07'!$I:$I,'Report Consolidado Semanal'!$W73) -> 0 | AE73: =SUMIFS('Report Pacote 07'!Q:Q,'Report Pacote 07'!$AY:$AY,$D73,'Report Pacote 07'!$I:$I,'Report Consolidado Semanal'!$W73) -> 0 | AF73: =SUMIFS('Report Pacote 07'!R:R,'Report Pacote 07'!$AY:$AY,$D73,'Report Pacote 07'!$I:$I,'Report Consolidado Semanal'!$W73) -> 5 | AG73: =SUMIFS('Report Pacote 07'!S:S,'Report Pacote 07'!$AY:$AY,$D73,'Report Pacote 07'!$I:$I,'Report Consolidado Semanal'!$W73) -> 0 | AH73: =SUMIF($AA$7:$AG$7,"<="&$D$4,$AA73:$AG73) -> 0 | AI73: =IFERROR((AH74/AH73),"-") -> - | AK73: =SUMIFS('Report Pacote 07'!Y:Y,'Report Pacote 07'!$AY:$AY,$D73,'Report Pacote 07'!$I:$I,'Report Consolidado Semanal'!$W73) -> 50 | AL73: =SUMIFS('Report Pacote 07'!Z:Z,'Report Pacote 07'!$AY:$AY,$D73,'Report Pacote 07'!$I:$I,'Report Consolidado Semanal'!$W73) -> 18 | AM73: =SUMIFS('Report Pacote 07'!AA:AA,'Report Pacote 07'!$AY:$AY,$D73,'Report Pacote 07'!$I:$I,'Report Consolidado Semanal'!$W73) -> 13 | AN73: =IFERROR((AM73/AL73),"-") -> 0.72222222 | AP73: =SUMIFS('Report Pacote 07'!AD:AD,'Report Pacote 07'!$AY:$AY,$D73,'Report Pacote 07'!$I:$I,'Report Consolidado Semanal'!$W73) -> 175 | AQ73: =SUMIFS('Report Pacote 07'!AI:AI,'Report Pacote 07'!$AY:$AY,$D73,'Report Pacote 07'!$I:$I,'Report Consolidado Semanal'!$W73) -> 183 | AR73: =IFERROR((AP73/AQ73),"-") -> 0.95628415 | AT73: =SUMIFS('Report Pacote 07'!AL:AL,'Report Pacote 07'!$AY:$AY,$D73,'Report Pacote 07'!$I:$I,'Report Consolidado Semanal'!$W73) -> 249 | AU73: =SUMIFS('Report Pacote 07'!AM:AM,'Report Pacote 07'!$AY:$AY,$D73,'Report Pacote 07'!$I:$I,'Report Consolidado Semanal'!$W73) -> 74 | AW73: =ROUNDUP(SUM(AK73/Quadros!$D$4),0) -> 2 | AX73: =ROUNDUP(SUM(AL73/Quadros!$D$4),0) -> 1 | AY73: =ROUNDUP(IF((AK73-AM73)/(Quadros!$D$4-Quadros!$D$6)<0,"-",(AK73-AM73)/(Quadros!$D$4-Quadros!$D$6)),0) -> 3
A74: Pilares | G74: R | H74: 7 | K74: R | L74: 7 | O74: R | P74: 7 | S74: R | T74: 7 | W74: R | X74: =SUMIF($AA$7:$AG$7,"="&$D$4,$AA74:$AG74) -> 0 | AA74: =SUMIFS('Report Pacote 07'!M:M,'Report Pacote 07'!$AY:$AY,$D73,'Report Pacote 07'!$I:$I,'Report Consolidado Semanal'!$W74) -> 0 | AB74: =SUMIFS('Report Pacote 07'!N:N,'Report Pacote 07'!$AY:$AY,$D73,'Report Pacote 07'!$I:$I,'Report Consolidado Semanal'!$W74) -> 0 | AC74: =SUMIFS('Report Pacote 07'!O:O,'Report Pacote 07'!$AY:$AY,$D73,'Report Pacote 07'!$I:$I,'Report Consolidado Semanal'!$W74) -> 0 | AD74: =SUMIFS('Report Pacote 07'!P:P,'Report Pacote 07'!$AY:$AY,$D73,'Report Pacote 07'!$I:$I,'Report Consolidado Semanal'!$W74) -> 0 | AE74: =SUMIFS('Report Pacote 07'!Q:Q,'Report Pacote 07'!$AY:$AY,$D73,'Report Pacote 07'!$I:$I,'Report Consolidado Semanal'!$W74) -> 0 | AF74: =SUMIFS('Report Pacote 07'!R:R,'Report Pacote 07'!$AY:$AY,$D73,'Report Pacote 07'!$I:$I,'Report Consolidado Semanal'!$W74) -> 0 | AG74: =SUMIFS('Report Pacote 07'!S:S,'Report Pacote 07'!$AY:$AY,$D73,'Report Pacote 07'!$I:$I,'Report Consolidado Semanal'!$W74) -> 0 | AH74: =SUMIF($AA$7:$AG$7,"<="&$D$4,$AA74:$AG74) -> 0
A77: Travessa | D77: Travessa | E77: Etapas | G77: P | H77: 1.5 | I77: =IFERROR((H78/H77),"-") -> 1.6666667 | K77: P | L77: 2 | M77: =IFERROR((L78/L77),"-") -> 0.75 | O77: P | P77: 1.5 | Q77: =IFERROR((P78/P77),"-") -> 1.3333333 | S77: P | T77: 1.5 | U77: 1.3333333 | W77: P | X77: =SUMIF($AA$7:$AG$7,"="&$D$4,$AA77:$AG77) -> 0 | Y77: =IFERROR((X78/X77),"-") -> - | AA77: =SUMIFS('Report Pacote 07'!M:M,'Report Pacote 07'!$AY:$AY,$D77,'Report Pacote 07'!$I:$I,'Report Consolidado Semanal'!$W77) -> 0 | AB77: =SUMIFS('Report Pacote 07'!N:N,'Report Pacote 07'!$AY:$AY,$D77,'Report Pacote 07'!$I:$I,'Report Consolidado Semanal'!$W77) -> 0 | AC77: =SUMIFS('Report Pacote 07'!O:O,'Report Pacote 07'!$AY:$AY,$D77,'Report Pacote 07'!$I:$I,'Report Consolidado Semanal'!$W77) -> 0 | AD77: =SUMIFS('Report Pacote 07'!P:P,'Report Pacote 07'!$AY:$AY,$D77,'Report Pacote 07'!$I:$I,'Report Consolidado Semanal'!$W77) -> 0.5 | AE77: =SUMIFS('Report Pacote 07'!Q:Q,'Report Pacote 07'!$AY:$AY,$D77,'Report Pacote 07'!$I:$I,'Report Consolidado Semanal'!$W77) -> 0 | AF77: =SUMIFS('Report Pacote 07'!R:R,'Report Pacote 07'!$AY:$AY,$D77,'Report Pacote 07'!$I:$I,'Report Consolidado Semanal'!$W77) -> 1 | AG77: =SUMIFS('Report Pacote 07'!S:S,'Report Pacote 07'!$AY:$AY,$D77,'Report Pacote 07'!$I:$I,'Report Consolidado Semanal'!$W77) -> 0 | AH77: =SUMIF($AA$7:$AG$7,"<="&$D$4,$AA77:$AG77) -> 0 | AI77: =IFERROR((AH78/AH77),"-") -> - | AK77: =SUMIFS('Report Pacote 07'!Y:Y,'Report Pacote 07'!$AY:$AY,$D77,'Report Pacote 07'!$I:$I,'Report Consolidado Semanal'!$W77) -> 8 | AL77: =SUMIFS('Report Pacote 07'!Z:Z,'Report Pacote 07'!$AY:$AY,$D77,'Report Pacote 07'!$I:$I,'Report Consolidado Semanal'!$W77) -> 4 | AM77: =SUMIFS('Report Pacote 07'!AA:AA,'Report Pacote 07'!$AY:$AY,$D77,'Report Pacote 07'!$I:$I,'Report Consolidado Semanal'!$W77) -> 4 | AN77: =IFERROR((AM77/AL77),"-") -> 1 | AP77: =SUMIFS('Report Pacote 07'!AD:AD,'Report Pacote 07'!$AY:$AY,$D77,'Report Pacote 07'!$I:$I,'Report Consolidado Semanal'!$W77) -> 20 | AQ77: =SUMIFS('Report Pacote 07'!AI:AI,'Report Pacote 07'!$AY:$AY,$D77,'Report Pacote 07'!$I:$I,'Report Consolidado Semanal'!$W77) -> 38 | AR77: =IFERROR((AP77/AQ77),"-") -> 0.52631579 | AT77: =SUMIFS('Report Pacote 07'!AL:AL,'Report Pacote 07'!$AY:$AY,$D77,'Report Pacote 07'!$I:$I,'Report Consolidado Semanal'!$W77) -> 63 | AU77: =SUMIFS('Report Pacote 07'!AM:AM,'Report Pacote 07'!$AY:$AY,$D77,'Report Pacote 07'!$I:$I,'Report Consolidado Semanal'!$W77) -> 43 | AW77: =ROUNDUP(SUM(AK77/Quadros!$D$4),0) -> 1 | AX77: =ROUNDUP(SUM(AL77/Quadros!$D$4),0) -> 1 | AY77: =ROUNDUP(IF((AK77-AM77)/(Quadros!$D$4-Quadros!$D$6)<0,"-",(AK77-AM77)/(Quadros!$D$4-Quadros!$D$6)),0) -> 1
A78: Travessa | G78: R | H78: 2.5 | K78: R | L78: 1.5 | O78: R | P78: 2 | S78: R | T78: 2 | W78: R | X78: =SUMIF($AA$7:$AG$7,"="&$D$4,$AA78:$AG78) -> 0 | AA78: =SUMIFS('Report Pacote 07'!M:M,'Report Pacote 07'!$AY:$AY,$D77,'Report Pacote 07'!$I:$I,'Report Consolidado Semanal'!$W78) -> 0 | AB78: =SUMIFS('Report Pacote 07'!N:N,'Report Pacote 07'!$AY:$AY,$D77,'Report Pacote 07'!$I:$I,'Report Consolidado Semanal'!$W78) -> 0 | AC78: =SUMIFS('Report Pacote 07'!O:O,'Report Pacote 07'!$AY:$AY,$D77,'Report Pacote 07'!$I:$I,'Report Consolidado Semanal'!$W78) -> 0 | AD78: =SUMIFS('Report Pacote 07'!P:P,'Report Pacote 07'!$AY:$AY,$D77,'Report Pacote 07'!$I:$I,'Report Consolidado Semanal'!$W78) -> 0 | AE78: =SUMIFS('Report Pacote 07'!Q:Q,'Report Pacote 07'!$AY:$AY,$D77,'Report Pacote 07'!$I:$I,'Report Consolidado Semanal'!$W78) -> 0 | AF78: =SUMIFS('Report Pacote 07'!R:R,'Report Pacote 07'!$AY:$AY,$D77,'Report Pacote 07'!$I:$I,'Report Consolidado Semanal'!$W78) -> 0 | AG78: =SUMIFS('Report Pacote 07'!S:S,'Report Pacote 07'!$AY:$AY,$D77,'Report Pacote 07'!$I:$I,'Report Consolidado Semanal'!$W78) -> 0 | AH78: =SUMIF($AA$7:$AG$7,"<="&$D$4,$AA78:$AG78) -> 0
A81: Aduelas | D81: Aduelas | E81: Etapas | G81: P | H81: 4 | I81: =IFERROR((H82/H81),"-") -> 0.5 | K81: P | L81: 0 | M81: =IFERROR((L82/L81),"-") -> - | O81: P | P81: 0 | Q81: =IFERROR((P82/P81),"-") -> - | S81: P | T81: 4 | U81: 0.25 | W81: P | X81: =SUMIF($AA$7:$AG$7,"="&$D$4,$AA81:$AG81) -> 0 | Y81: =IFERROR((X82/X81),"-") -> - | AA81: =SUMIFS('Report Pacote 07'!M:M,'Report Pacote 07'!$AY:$AY,$D81,'Report Pacote 07'!$I:$I,'Report Consolidado Semanal'!$W81) -> 3 | AB81: =SUMIFS('Report Pacote 07'!N:N,'Report Pacote 07'!$AY:$AY,$D81,'Report Pacote 07'!$I:$I,'Report Consolidado Semanal'!$W81) -> 0 | AC81: =SUMIFS('Report Pacote 07'!O:O,'Report Pacote 07'!$AY:$AY,$D81,'Report Pacote 07'!$I:$I,'Report Consolidado Semanal'!$W81) -> 0 | AD81: =SUMIFS('Report Pacote 07'!P:P,'Report Pacote 07'!$AY:$AY,$D81,'Report Pacote 07'!$I:$I,'Report Consolidado Semanal'!$W81) -> 0 | AE81: =SUMIFS('Report Pacote 07'!Q:Q,'Report Pacote 07'!$AY:$AY,$D81,'Report Pacote 07'!$I:$I,'Report Consolidado Semanal'!$W81) -> 0 | AF81: =SUMIFS('Report Pacote 07'!R:R,'Report Pacote 07'!$AY:$AY,$D81,'Report Pacote 07'!$I:$I,'Report Consolidado Semanal'!$W81) -> 1 | AG81: =SUMIFS('Report Pacote 07'!S:S,'Report Pacote 07'!$AY:$AY,$D81,'Report Pacote 07'!$I:$I,'Report Consolidado Semanal'!$W81) -> 0 | AH81: =SUMIF($AA$7:$AG$7,"<="&$D$4,$AA81:$AG81) -> 3 | AI81: =IFERROR((AH82/AH81),"-") -> 1 | AK81: =SUMIFS('Report Pacote 07'!Y:Y,'Report Pacote 07'!$AY:$AY,$D81,'Report Pacote 07'!$I:$I,'Report Consolidado Semanal'!$W81) -> 15 | AL81: =SUMIFS('Report Pacote 07'!Z:Z,'Report Pacote 07'!$AY:$AY,$D81,'Report Pacote 07'!$I:$I,'Report Consolidado Semanal'!$W81) -> 3 | AM81: =SUMIFS('Report Pacote 07'!AA:AA,'Report Pacote 07'!$AY:$AY,$D81,'Report Pacote 07'!$I:$I,'Report Consolidado Semanal'!$W81) -> 5 | AN81: =IFERROR((AM81/AL81),"-") -> 1.6666667 | AP81: =SUMIFS('Report Pacote 07'!AD:AD,'Report Pacote 07'!$AY:$AY,$D81,'Report Pacote 07'!$I:$I,'Report Consolidado Semanal'!$W81) -> 14 | AQ81: =SUMIFS('Report Pacote 07'!AI:AI,'Report Pacote 07'!$AY:$AY,$D81,'Report Pacote 07'!$I:$I,'Report Consolidado Semanal'!$W81) -> 75 | AR81: =IFERROR((AP81/AQ81),"-") -> 0.18666667 | AT81: =SUMIFS('Report Pacote 07'!AL:AL,'Report Pacote 07'!$AY:$AY,$D81,'Report Pacote 07'!$I:$I,'Report Consolidado Semanal'!$W81) -> 135 | AU81: =SUMIFS('Report Pacote 07'!AM:AM,'Report Pacote 07'!$AY:$AY,$D81,'Report Pacote 07'!$I:$I,'Report Consolidado Semanal'!$W81) -> 121 | AW81: =ROUNDUP(SUM(AK81/Quadros!$D$4),0) -> 1 | AX81: =ROUNDUP(SUM(AL81/Quadros!$D$4),0) -> 1 | AY81: =ROUNDUP(IF((AK81-AM81)/(Quadros!$D$4-Quadros!$D$6)<0,"-",(AK81-AM81)/(Quadros!$D$4-Quadros!$D$6)),0) -> 1
A82: Aduelas | G82: R | H82: 2 | K82: R | L82: 2.3333333 | O82: R | P82: 1 | S82: R | T82: 1 | W82: R | X82: =SUMIF($AA$7:$AG$7,"="&$D$4,$AA82:$AG82) -> 3 | AA82: =SUMIFS('Report Pacote 07'!M:M,'Report Pacote 07'!$AY:$AY,$D81,'Report Pacote 07'!$I:$I,'Report Consolidado Semanal'!$W82) -> 0 | AB82: =SUMIFS('Report Pacote 07'!N:N,'Report Pacote 07'!$AY:$AY,$D81,'Report Pacote 07'!$I:$I,'Report Consolidado Semanal'!$W82) -> 3 | AC82: =SUMIFS('Report Pacote 07'!O:O,'Report Pacote 07'!$AY:$AY,$D81,'Report Pacote 07'!$I:$I,'Report Consolidado Semanal'!$W82) -> 0 | AD82: =SUMIFS('Report Pacote 07'!P:P,'Report Pacote 07'!$AY:$AY,$D81,'Report Pacote 07'!$I:$I,'Report Consolidado Semanal'!$W82) -> 0 | AE82: =SUMIFS('Report Pacote 07'!Q:Q,'Report Pacote 07'!$AY:$AY,$D81,'Report Pacote 07'!$I:$I,'Report Consolidado Semanal'!$W82) -> 0 | AF82: =SUMIFS('Report Pacote 07'!R:R,'Report Pacote 07'!$AY:$AY,$D81,'Report Pacote 07'!$I:$I,'Report Consolidado Semanal'!$W82) -> 0 | AG82: =SUMIFS('Report Pacote 07'!S:S,'Report Pacote 07'!$AY:$AY,$D81,'Report Pacote 07'!$I:$I,'Report Consolidado Semanal'!$W82) -> 0 | AH82: =SUMIF($AA$7:$AG$7,"<="&$D$4,$AA82:$AG82) -> 3
A85: Vigas Pré Moldadas | D85: Vigas Pré Moldadas | E85: Und | G85: P | H85: 3 | I85: =IFERROR((H86/H85),"-") -> 0.66666667 | K85: P | L85: 2 | M85: =IFERROR((L86/L85),"-") -> 1 | O85: P | P85: 2 | Q85: =IFERROR((P86/P85),"-") -> 1 | S85: P | T85: 1 | U85: 1 | W85: P | X85: =SUMIF($AA$7:$AG$7,"="&$D$4,$AA85:$AG85) -> 0 | Y85: =IFERROR((X86/X85),"-") -> - | AA85: =SUMIFS('Report Pacote 07'!M:M,'Report Pacote 07'!$AY:$AY,$D85,'Report Pacote 07'!$I:$I,'Report Consolidado Semanal'!$W85) -> 0 | AB85: =SUMIFS('Report Pacote 07'!N:N,'Report Pacote 07'!$AY:$AY,$D85,'Report Pacote 07'!$I:$I,'Report Consolidado Semanal'!$W85) -> 0 | AC85: =SUMIFS('Report Pacote 07'!O:O,'Report Pacote 07'!$AY:$AY,$D85,'Report Pacote 07'!$I:$I,'Report Consolidado Semanal'!$W85) -> 0 | AD85: =SUMIFS('Report Pacote 07'!P:P,'Report Pacote 07'!$AY:$AY,$D85,'Report Pacote 07'!$I:$I,'Report Consolidado Semanal'!$W85) -> 1 | AE85: =SUMIFS('Report Pacote 07'!Q:Q,'Report Pacote 07'!$AY:$AY,$D85,'Report Pacote 07'!$I:$I,'Report Consolidado Semanal'!$W85) -> 0 | AF85: =SUMIFS('Report Pacote 07'!R:R,'Report Pacote 07'!$AY:$AY,$D85,'Report Pacote 07'!$I:$I,'Report Consolidado Semanal'!$W85) -> 1 | AG85: =SUMIFS('Report Pacote 07'!S:S,'Report Pacote 07'!$AY:$AY,$D85,'Report Pacote 07'!$I:$I,'Report Consolidado Semanal'!$W85) -> 0 | AH85: =SUMIF($AA$7:$AG$7,"<="&$D$4,$AA85:$AG85) -> 0 | AI85: =IFERROR((AH86/AH85),"-") -> - | AK85: =SUMIFS('Report Pacote 07'!Y:Y,'Report Pacote 07'!$AY:$AY,$D85,'Report Pacote 07'!$I:$I,'Report Consolidado Semanal'!$W85) -> 8 | AL85: =SUMIFS('Report Pacote 07'!Z:Z,'Report Pacote 07'!$AY:$AY,$D85,'Report Pacote 07'!$I:$I,'Report Consolidado Semanal'!$W85) -> 2 | AM85: =SUMIFS('Report Pacote 07'!AA:AA,'Report Pacote 07'!$AY:$AY,$D85,'Report Pacote 07'!$I:$I,'Report Consolidado Semanal'!$W85) -> 2 | AN85: =IFERROR((AM85/AL85),"-") -> 1 | AP85: =SUMIFS('Report Pacote 07'!AD:AD,'Report Pacote 07'!$AY:$AY,$D85,'Report Pacote 07'!$I:$I,'Report Consolidado Semanal'!$W85) -> 44 | AQ85: =SUMIFS('Report Pacote 07'!AI:AI,'Report Pacote 07'!$AY:$AY,$D85,'Report Pacote 07'!$I:$I,'Report Consolidado Semanal'!$W85) -> 46 | AR85: =IFERROR((AP85/AQ85),"-") -> 0.95652174 | AT85: =SUMIFS('Report Pacote 07'!AL:AL,'Report Pacote 07'!$AY:$AY,$D85,'Report Pacote 07'!$I:$I,'Report Consolidado Semanal'!$W85) -> 66 | AU85: =SUMIFS('Report Pacote 07'!AM:AM,'Report Pacote 07'!$AY:$AY,$D85,'Report Pacote 07'!$I:$I,'Report Consolidado Semanal'!$W85) -> 22 | AW85: =ROUNDUP(SUM(AK85/Quadros!$D$4),0) -> 1 | AX85: =ROUNDUP(SUM(AL85/Quadros!$D$4),0) -> 1 | AY85: =ROUNDUP(IF((AK85-AM85)/(Quadros!$D$4-Quadros!$D$6)<0,"-",(AK85-AM85)/(Quadros!$D$4-Quadros!$D$6)),0) -> 1
A86: Vigas Pré Moldadas | G86: R | H86: 2 | K86: R | L86: 2 | O86: R | P86: 2 | S86: R | T86: 1 | W86: R | X86: =SUMIF($AA$7:$AG$7,"="&$D$4,$AA86:$AG86) -> 0 | AA86: =SUMIFS('Report Pacote 07'!M:M,'Report Pacote 07'!$AY:$AY,$D85,'Report Pacote 07'!$I:$I,'Report Consolidado Semanal'!$W86) -> 0 | AB86: =SUMIFS('Report Pacote 07'!N:N,'Report Pacote 07'!$AY:$AY,$D85,'Report Pacote 07'!$I:$I,'Report Consolidado Semanal'!$W86) -> 0 | AC86: =SUMIFS('Report Pacote 07'!O:O,'Report Pacote 07'!$AY:$AY,$D85,'Report Pacote 07'!$I:$I,'Report Consolidado Semanal'!$W86) -> 0 | AD86: =SUMIFS('Report Pacote 07'!P:P,'Report Pacote 07'!$AY:$AY,$D85,'Report Pacote 07'!$I:$I,'Report Consolidado Semanal'!$W86) -> 0 | AE86: =SUMIFS('Report Pacote 07'!Q:Q,'Report Pacote 07'!$AY:$AY,$D85,'Report Pacote 07'!$I:$I,'Report Consolidado Semanal'!$W86) -> 0 | AF86: =SUMIFS('Report Pacote 07'!R:R,'Report Pacote 07'!$AY:$AY,$D85,'Report Pacote 07'!$I:$I,'Report Consolidado Semanal'!$W86) -> 0 | AG86: =SUMIFS('Report Pacote 07'!S:S,'Report Pacote 07'!$AY:$AY,$D85,'Report Pacote 07'!$I:$I,'Report Consolidado Semanal'!$W86) -> 0 | AH86: =SUMIF($AA$7:$AG$7,"<="&$D$4,$AA86:$AG86) -> 0
A89: Pré moldados | D89: Pré moldados | E89: Und | G89: P | H89: 159 | I89: =IFERROR((H90/H89),"-") -> 1.1006289 | K89: P | L89: 189 | M89: =IFERROR((L90/L89),"-") -> 0.85714286 | O89: P | P89: 161 | Q89: =IFERROR((P90/P89),"-") -> 0.8447205 | S89: P | T89: 189 | U89: 0.7989418 | W89: P | X89: =SUMIF($AA$7:$AG$7,"="&$D$4,$AA89:$AG89) -> 23 | Y89: =IFERROR((X90/X89),"-") -> 1 | AA89: =SUMIFS('Report Pacote 07'!M:M,'Report Pacote 07'!$AY:$AY,$D89,'Report Pacote 07'!$I:$I,'Report Consolidado Semanal'!$W89) -> 40 | AB89: =SUMIFS('Report Pacote 07'!N:N,'Report Pacote 07'!$AY:$AY,$D89,'Report Pacote 07'!$I:$I,'Report Consolidado Semanal'!$W89) -> 23 | AC89: =SUMIFS('Report Pacote 07'!O:O,'Report Pacote 07'!$AY:$AY,$D89,'Report Pacote 07'!$I:$I,'Report Consolidado Semanal'!$W89) -> 40 | AD89: =SUMIFS('Report Pacote 07'!P:P,'Report Pacote 07'!$AY:$AY,$D89,'Report Pacote 07'!$I:$I,'Report Consolidado Semanal'!$W89) -> 23 | AE89: =SUMIFS('Report Pacote 07'!Q:Q,'Report Pacote 07'!$AY:$AY,$D89,'Report Pacote 07'!$I:$I,'Report Consolidado Semanal'!$W89) -> 40 | AF89: =SUMIFS('Report Pacote 07'!R:R,'Report Pacote 07'!$AY:$AY,$D89,'Report Pacote 07'!$I:$I,'Report Consolidado Semanal'!$W89) -> 23 | AG89: =SUMIFS('Report Pacote 07'!S:S,'Report Pacote 07'!$AY:$AY,$D89,'Report Pacote 07'!$I:$I,'Report Consolidado Semanal'!$W89) -> 0 | AH89: =SUMIF($AA$7:$AG$7,"<="&$D$4,$AA89:$AG89) -> 63 | AI89: =IFERROR((AH90/AH89),"-") -> 1 | AK89: =SUMIFS('Report Pacote 07'!Y:Y,'Report Pacote 07'!$AY:$AY,$D89,'Report Pacote 07'!$I:$I,'Report Consolidado Semanal'!$W89) -> 552 | AL89: =SUMIFS('Report Pacote 07'!Z:Z,'Report Pacote 07'!$AY:$AY,$D89,'Report Pacote 07'!$I:$I,'Report Consolidado Semanal'!$W89) -> 276 | AM89: =SUMIFS('Report Pacote 07'!AA:AA,'Report Pacote 07'!$AY:$AY,$D89,'Report Pacote 07'!$I:$I,'Report Consolidado Semanal'!$W89) -> 344 | AN89: =IFERROR((AM89/AL89),"-") -> 1.2463768 | AP89: =SUMIFS('Report Pacote 07'!AD:AD,'Report Pacote 07'!$AY:$AY,$D89,'Report Pacote 07'!$I:$I,'Report Consolidado Semanal'!$W89) -> 1273 | AQ89: =SUMIFS('Report Pacote 07'!AI:AI,'Report Pacote 07'!$AY:$AY,$D89,'Report Pacote 07'!$I:$I,'Report Consolidado Semanal'!$W89) -> 2760 | AR89: =IFERROR((AP89/AQ89),"-") -> 0.46123188 | AT89: =SUMIFS('Report Pacote 07'!AL:AL,'Report Pacote 07'!$AY:$AY,$D89,'Report Pacote 07'!$I:$I,'Report Consolidado Semanal'!$W89) -> 5116 | AU89: =SUMIFS('Report Pacote 07'!AM:AM,'Report Pacote 07'!$AY:$AY,$D89,'Report Pacote 07'!$I:$I,'Report Consolidado Semanal'!$W89) -> 3843 | AW89: =ROUNDUP(SUM(AK89/Quadros!$D$4),0) -> 21 | AX89: =ROUNDUP(SUM(AL89/Quadros!$D$4),0) -> 11 | AY89: =ROUNDUP(IF((AK89-AM89)/(Quadros!$D$4-Quadros!$D$6)<0,"-",(AK89-AM89)/(Quadros!$D$4-Quadros!$D$6)),0) -> 14
A90: Pré moldados | G90: R | H90: 175 | K90: R | L90: 162 | O90: R | P90: 136 | S90: R | T90: 151 | W90: R | X90: =SUMIF($AA$7:$AG$7,"="&$D$4,$AA90:$AG90) -> 23 | AA90: =SUMIFS('Report Pacote 07'!M:M,'Report Pacote 07'!$AY:$AY,$D89,'Report Pacote 07'!$I:$I,'Report Consolidado Semanal'!$W90) -> 40 | AB90: =SUMIFS('Report Pacote 07'!N:N,'Report Pacote 07'!$AY:$AY,$D89,'Report Pacote 07'!$I:$I,'Report Consolidado Semanal'!$W90) -> 23 | AC90: =SUMIFS('Report Pacote 07'!O:O,'Report Pacote 07'!$AY:$AY,$D89,'Report Pacote 07'!$I:$I,'Report Consolidado Semanal'!$W90) -> 0 | AD90: =SUMIFS('Report Pacote 07'!P:P,'Report Pacote 07'!$AY:$AY,$D89,'Report Pacote 07'!$I:$I,'Report Consolidado Semanal'!$W90) -> 0 | AE90: =SUMIFS('Report Pacote 07'!Q:Q,'Report Pacote 07'!$AY:$AY,$D89,'Report Pacote 07'!$I:$I,'Report Consolidado Semanal'!$W90) -> 0 | AF90: =SUMIFS('Report Pacote 07'!R:R,'Report Pacote 07'!$AY:$AY,$D89,'Report Pacote 07'!$I:$I,'Report Consolidado Semanal'!$W90) -> 0 | AG90: =SUMIFS('Report Pacote 07'!S:S,'Report Pacote 07'!$AY:$AY,$D89,'Report Pacote 07'!$I:$I,'Report Consolidado Semanal'!$W90) -> 0 | AH90: =SUMIF($AA$7:$AG$7,"<="&$D$4,$AA90:$AG90) -> 63
D93: DSH / DHP - Drenos Sub-Horizontal e Horizontal Profundo | E93: m | G93: P | I93: =IFERROR((H94/H93),"-") -> - | K93: P | M93: =IFERROR((L94/L93),"-") -> - | O93: P | P93: =P97+P101+P105+P109 -> 0 | Q93: =IFERROR((P94/P93),"-") -> - | S93: P | U93: =IFERROR((T94/T93),"-") -> - | W93: P | X93: =X97+X101+X105+X109 -> 140 | Y93: =IFERROR((X94/X93),"-") -> 2.7857143 | AA93: =AA97+AA101+AA105+AA109 -> 140 | AB93: =AB97+AB101+AB105+AB109 -> 140 | AC93: =AC97+AC101+AC105+AC109 -> 140 | AD93: =AD97+AD101+AD105+AD109 -> 280 | AE93: =AE97+AE101+AE105+AE109 -> 240 | AF93: =AF97+AF101+AF105+AF109 -> 240 | AG93: =AG97+AG101+AG105+AG109 -> 0 | AH93: =SUMIF($AA$7:$AG$7,"<="&$D$4,$AA93:$AG93) -> 280 | AI93: =IFERROR((AH94/AH93),"-") -> 2.4107143 | AK93: =AK97+AK101+AK105+AK109 -> 3359 | AL93: =AL97+AL101+AL105+AL109 -> 1200 | AM93: =AM97+AM101+AM105+AM109 -> 621 | AN93: =IFERROR((AM93/AL93),"-") -> 0.5175 | AP93: =AP97+AP101+AP105+AP109 -> 9400.2 | AQ93: =AQ97+AQ101+AQ105+AQ109 -> 10388.25 | AR93: =IFERROR((AP93/AQ93),"-") -> 0.90488773 | AT93: =AT97+AT101+AT105+AT109 -> 38071 | AU93: =AU97+AU101+AU105+AU109 -> 28670.8 | AW93: =AW97+AW101+AW105+AW109 -> 124.40741 | AX93: =AX97+AX101+AX105+AX109 -> 51.75 | AY93: =IF((AK93-AM93)/(Quadros!$D$4-Quadros!$D$6)<0,"-",(AK93-AM93)/(Quadros!$D$4-Quadros!$D$6)) -> 182.53333
G94: R | K94: R | O94: R | P94: =P98+P102+P106+P110 -> 0 | S94: R | W94: R | X94: =X98+X102+X106+X110 -> 390 | AA94: =AA98+AA102+AA106+AA110 -> 285 | AB94: =AB98+AB102+AB106+AB110 -> 390 | AC94: =AC98+AC102+AC106+AC110 -> 0 | AD94: =AD98+AD102+AD106+AD110 -> 0 | AE94: =AE98+AE102+AE106+AE110 -> 0 | AF94: =AF98+AF102+AF106+AF110 -> 0 | AG94: =AG98+AG102+AG106+AG110 -> 0 | AH94: =SUMIF($AA$7:$AG$7,"<="&$D$4,$AA94:$AG94) -> 675
A97: Pacote 04 - Segmento 2.2B- Km 104+500 a Km 116+400 | D97: Pacote 04 - km 104+500 a 131+260 | E97: m | G97: P | I97: =IFERROR((H98/H97),"-") -> - | K97: P | M97: =IFERROR((L98/L97),"-") -> - | O97: P | Q97: =IFERROR((P98/P97),"-") -> - | S97: P | U97: =IFERROR((T98/T97),"-") -> - | W97: P | X97: =SUMIF($AA$7:$AG$7,"="&$D$4,$AA97:$AG97) -> 140 | Y97: =IFERROR((X98/X97),"-") -> 2.7857143 | AA97: =SUMIFS('Report Pacote 0405'!P:P,'Report Pacote 0405'!$AV:$AV,$D$93,'Report Pacote 0405'!$AW:$AW,$A$97,'Report Pacote 0405'!$H:$H,$W97)+SUMIFS('Report Pacote 0405'!P:P,'Report Pacote 0405'!$AV:$AV,$D$93,'Report Pacote 0405'!$AW:$AW,$A$98,'Report Pacote 0405'!$H:$H,$W97) -> 140 | AB97: =SUMIFS('Report Pacote 0405'!Q:Q,'Report Pacote 0405'!$AV:$AV,$D$93,'Report Pacote 0405'!$AW:$AW,$A$97,'Report Pacote 0405'!$H:$H,$W97)+SUMIFS('Report Pacote 0405'!Q:Q,'Report Pacote 0405'!$AV:$AV,$D$93,'Report Pacote 0405'!$AW:$AW,$A$98,'Report Pacote 0405'!$H:$H,$W97) -> 140 | AC97: =SUMIFS('Report Pacote 0405'!R:R,'Report Pacote 0405'!$AV:$AV,$D$93,'Report Pacote 0405'!$AW:$AW,$A$97,'Report Pacote 0405'!$H:$H,$W97)+SUMIFS('Report Pacote 0405'!R:R,'Report Pacote 0405'!$AV:$AV,$D$93,'Report Pacote 0405'!$AW:$AW,$A$98,'Report Pacote 0405'!$H:$H,$W97) -> 140 | AD97: =SUMIFS('Report Pacote 0405'!S:S,'Report Pacote 0405'!$AV:$AV,$D$93,'Report Pacote 0405'!$AW:$AW,$A$97,'Report Pacote 0405'!$H:$H,$W97)+SUMIFS('Report Pacote 0405'!S:S,'Report Pacote 0405'!$AV:$AV,$D$93,'Report Pacote 0405'!$AW:$AW,$A$98,'Report Pacote 0405'!$H:$H,$W97) -> 280 | AE97: =SUMIFS('Report Pacote 0405'!T:T,'Report Pacote 0405'!$AV:$AV,$D$93,'Report Pacote 0405'!$AW:$AW,$A$97,'Report Pacote 0405'!$H:$H,$W97)+SUMIFS('Report Pacote 0405'!T:T,'Report Pacote 0405'!$AV:$AV,$D$93,'Report Pacote 0405'!$AW:$AW,$A$98,'Report Pacote 0405'!$H:$H,$W97) -> 240 | AF97: =SUMIFS('Report Pacote 0405'!U:U,'Report Pacote 0405'!$AV:$AV,$D$93,'Report Pacote 0405'!$AW:$AW,$A$97,'Report Pacote 0405'!$H:$H,$W97)+SUMIFS('Report Pacote 0405'!U:U,'Report Pacote 0405'!$AV:$AV,$D$93,'Report Pacote 0405'!$AW:$AW,$A$98,'Report Pacote 0405'!$H:$H,$W97) -> 240 | AG97: =SUMIFS('Report Pacote 0405'!V:V,'Report Pacote 0405'!$AV:$AV,$D$93,'Report Pacote 0405'!$AW:$AW,$A$97,'Report Pacote 0405'!$H:$H,$W97)+SUMIFS('Report Pacote 0405'!V:V,'Report Pacote 0405'!$AV:$AV,$D$93,'Report Pacote 0405'!$AW:$AW,$A$98,'Report Pacote 0405'!$H:$H,$W97) -> 0 | AH97: =SUMIF($AA$7:$AG$7,"<="&$D$4,$AA97:$AG97) -> 280 | AI97: =IFERROR((AH98/AH97),"-") -> 2.4107143 | AK97: =SUMIFS('Report Pacote 0405'!AA:AA,'Report Pacote 0405'!$AV:$AV,$D$93,'Report Pacote 0405'!$AW:$AW,$A$97,'Report Pacote 0405'!$H:$H,$W97)+SUMIFS('Report Pacote 0405'!AA:AA,'Report Pacote 0405'!$AV:$AV,$D$93,'Report Pacote 0405'!$AW:$AW,$A$98,'Report Pacote 0405'!$H:$H,$W97) -> 3359 | AL97: =SUMIFS('Report Pacote 0405'!AB:AB,'Report Pacote 0405'!$AV:$AV,$D$93,'Report Pacote 0405'!$AW:$AW,$A$97,'Report Pacote 0405'!$H:$H,$W97)+SUMIFS('Report Pacote 0405'!AB:AB,'Report Pacote 0405'!$AV:$AV,$D$93,'Report Pacote 0405'!$AW:$AW,$A$98,'Report Pacote 0405'!$H:$H,$W97) -> 1200 | AM97: =SUMIFS('Report Pacote 0405'!AC:AC,'Report Pacote 0405'!$AV:$AV,$D$93,'Report Pacote 0405'!$AW:$AW,$A$97,'Report Pacote 0405'!$H:$H,$W97)+SUMIFS('Report Pacote 0405'!AC:AC,'Report Pacote 0405'!$AV:$AV,$D$93,'Report Pacote 0405'!$AW:$AW,$A$98,'Report Pacote 0405'!$H:$H,$W97) -> 621 | AN97: =IFERROR((AM97/AL97),"-") -> 0.5175 | AP97: =SUMIFS('Report Pacote 0405'!AK:AK,'Report Pacote 0405'!$AV:$AV,$D$93,'Report Pacote 0405'!$AW:$AW,$A$98,'Report Pacote 0405'!$H:$H,$W97)+SUMIFS('Report Pacote 0405'!AK:AK,'Report Pacote 0405'!$AV:$AV,$D$93,'Report Pacote 0405'!$AW:$AW,$A$97,'Report Pacote 0405'!$H:$H,$W97) -> 5680.98 | AQ97: =SUMIFS('Report Pacote 0405'!AL:AL,'Report Pacote 0405'!$AV:$AV,$D$93,'Report Pacote 0405'!$AW:$AW,$A$97,'Report Pacote 0405'!$H:$H,$W97)+SUMIFS('Report Pacote 0405'!AL:AL,'Report Pacote 0405'!$AV:$AV,$D$93,'Report Pacote 0405'!$AW:$AW,$A$98,'Report Pacote 0405'!$H:$H,$W97) -> 6119.25 | AR97: =IFERROR((AP97/AQ97),"-") -> 0.92837848 | AT97: =SUMIFS('Report Pacote 0405'!AO:AO,'Report Pacote 0405'!$AV:$AV,$D$93,'Report Pacote 0405'!$AW:$AW,$A$97,'Report Pacote 0405'!$H:$H,$W97)+SUMIFS('Report Pacote 0405'!AO:AO,'Report Pacote 0405'!$AV:$AV,$D$93,'Report Pacote 0405'!$AW:$AW,$A$98,'Report Pacote 0405'!$H:$H,$W97) -> 24428 | AU97: =SUMIFS('Report Pacote 0405'!AP:AP,'Report Pacote 0405'!$AV:$AV,$D$93,'Report Pacote 0405'!$AW:$AW,$A$97,'Report Pacote 0405'!$H:$H,$W97)+SUMIFS('Report Pacote 0405'!AP:AP,'Report Pacote 0405'!$AV:$AV,$D$93,'Report Pacote 0405'!$AW:$AW,$A$98,'Report Pacote 0405'!$H:$H,$W97) -> 18747.02 | AW97: =AK97/Quadros!$D$4 -> 124.40741 | AX97: =AM97/Quadros!$D$6 -> 51.75 | AY97: =IF((AK97-AM97)/(Quadros!$D$4-Quadros!$D$6)<0,"-",(AK97-AM97)/(Quadros!$D$4-Quadros!$D$6)) -> 182.53333
A98: Pacote 04 - Segmento 2.3 - Km 116+517 a 131+241 | G98: R | K98: R | O98: R | S98: R | W98: R | X98: =SUMIF($AA$7:$AG$7,"="&$D$4,$AA98:$AG98) -> 390 | AA98: =SUMIFS('Report Pacote 0405'!P:P,'Report Pacote 0405'!$AV:$AV,$D$93,'Report Pacote 0405'!$AW:$AW,$A$97,'Report Pacote 0405'!$H:$H,$W98)+SUMIFS('Report Pacote 0405'!P:P,'Report Pacote 0405'!$AV:$AV,$D$93,'Report Pacote 0405'!$AW:$AW,$A$98,'Report Pacote 0405'!$H:$H,$W98) -> 285 | AB98: =SUMIFS('Report Pacote 0405'!Q:Q,'Report Pacote 0405'!$AV:$AV,$D$93,'Report Pacote 0405'!$AW:$AW,$A$97,'Report Pacote 0405'!$H:$H,$W98)+SUMIFS('Report Pacote 0405'!Q:Q,'Report Pacote 0405'!$AV:$AV,$D$93,'Report Pacote 0405'!$AW:$AW,$A$98,'Report Pacote 0405'!$H:$H,$W98) -> 390 | AC98: =SUMIFS('Report Pacote 0405'!R:R,'Report Pacote 0405'!$AV:$AV,$D$93,'Report Pacote 0405'!$AW:$AW,$A$97,'Report Pacote 0405'!$H:$H,$W98)+SUMIFS('Report Pacote 0405'!R:R,'Report Pacote 0405'!$AV:$AV,$D$93,'Report Pacote 0405'!$AW:$AW,$A$98,'Report Pacote 0405'!$H:$H,$W98) -> 0 | AD98: =SUMIFS('Report Pacote 0405'!S:S,'Report Pacote 0405'!$AV:$AV,$D$93,'Report Pacote 0405'!$AW:$AW,$A$97,'Report Pacote 0405'!$H:$H,$W98)+SUMIFS('Report Pacote 0405'!S:S,'Report Pacote 0405'!$AV:$AV,$D$93,'Report Pacote 0405'!$AW:$AW,$A$98,'Report Pacote 0405'!$H:$H,$W98) -> 0 | AE98: =SUMIFS('Report Pacote 0405'!T:T,'Report Pacote 0405'!$AV:$AV,$D$93,'Report Pacote 0405'!$AW:$AW,$A$97,'Report Pacote 0405'!$H:$H,$W98)+SUMIFS('Report Pacote 0405'!T:T,'Report Pacote 0405'!$AV:$AV,$D$93,'Report Pacote 0405'!$AW:$AW,$A$98,'Report Pacote 0405'!$H:$H,$W98) -> 0 | AF98: =SUMIFS('Report Pacote 0405'!U:U,'Report Pacote 0405'!$AV:$AV,$D$93,'Report Pacote 0405'!$AW:$AW,$A$97,'Report Pacote 0405'!$H:$H,$W98)+SUMIFS('Report Pacote 0405'!U:U,'Report Pacote 0405'!$AV:$AV,$D$93,'Report Pacote 0405'!$AW:$AW,$A$98,'Report Pacote 0405'!$H:$H,$W98) -> 0 | AG98: =SUMIFS('Report Pacote 0405'!V:V,'Report Pacote 0405'!$AV:$AV,$D$93,'Report Pacote 0405'!$AW:$AW,$A$97,'Report Pacote 0405'!$H:$H,$W98)+SUMIFS('Report Pacote 0405'!V:V,'Report Pacote 0405'!$AV:$AV,$D$93,'Report Pacote 0405'!$AW:$AW,$A$98,'Report Pacote 0405'!$H:$H,$W98) -> 0 | AH98: =SUMIF($AA$7:$AG$7,"<="&$D$4,$AA98:$AG98) -> 675
A101: Pacote 05 - Segmento 2.4 - Km 131+260 a Km 138+000 | D101: Pacote 05 - km 131+260 a 167+300 | E101: m | G101: P | I101: =IFERROR((H102/H101),"-") -> - | K101: P | M101: =IFERROR((L102/L101),"-") -> - | O101: P | Q101: =IFERROR((P102/P101),"-") -> - | S101: P | U101: =IFERROR((T102/T101),"-") -> - | W101: P | X101: =SUMIF($AA$7:$AG$7,"="&$D$4,$AA101:$AG101) -> 0 | Y101: =IFERROR((X102/X101),"-") -> - | AA101: =SUMIFS('Report Pacote 0405'!P:P,'Report Pacote 0405'!$AV:$AV,$D$93,'Report Pacote 0405'!$AW:$AW,$A$101,'Report Pacote 0405'!$H:$H,$W101)+SUMIFS('Report Pacote 0405'!P:P,'Report Pacote 0405'!$AV:$AV,$D$93,'Report Pacote 0405'!$AW:$AW,$A$102,'Report Pacote 0405'!$H:$H,$W101)+SUMIFS('Report Pacote 0405'!P:P,'Report Pacote 0405'!$AV:$AV,$D$93,'Report Pacote 0405'!$AW:$AW,$A$103,'Report Pacote 0405'!$H:$H,$W101) -> 0 | AB101: =SUMIFS('Report Pacote 0405'!Q:Q,'Report Pacote 0405'!$AV:$AV,$D$93,'Report Pacote 0405'!$AW:$AW,$A$101,'Report Pacote 0405'!$H:$H,$W101)+SUMIFS('Report Pacote 0405'!Q:Q,'Report Pacote 0405'!$AV:$AV,$D$93,'Report Pacote 0405'!$AW:$AW,$A$102,'Report Pacote 0405'!$H:$H,$W101)+SUMIFS('Report Pacote 0405'!Q:Q,'Report Pacote 0405'!$AV:$AV,$D$93,'Report Pacote 0405'!$AW:$AW,$A$103,'Report Pacote 0405'!$H:$H,$W101) -> 0 | AC101: =SUMIFS('Report Pacote 0405'!R:R,'Report Pacote 0405'!$AV:$AV,$D$93,'Report Pacote 0405'!$AW:$AW,$A$101,'Report Pacote 0405'!$H:$H,$W101)+SUMIFS('Report Pacote 0405'!R:R,'Report Pacote 0405'!$AV:$AV,$D$93,'Report Pacote 0405'!$AW:$AW,$A$102,'Report Pacote 0405'!$H:$H,$W101)+SUMIFS('Report Pacote 0405'!R:R,'Report Pacote 0405'!$AV:$AV,$D$93,'Report Pacote 0405'!$AW:$AW,$A$103,'Report Pacote 0405'!$H:$H,$W101) -> 0 | AD101: =SUMIFS('Report Pacote 0405'!S:S,'Report Pacote 0405'!$AV:$AV,$D$93,'Report Pacote 0405'!$AW:$AW,$A$101,'Report Pacote 0405'!$H:$H,$W101)+SUMIFS('Report Pacote 0405'!S:S,'Report Pacote 0405'!$AV:$AV,$D$93,'Report Pacote 0405'!$AW:$AW,$A$102,'Report Pacote 0405'!$H:$H,$W101)+SUMIFS('Report Pacote 0405'!S:S,'Report Pacote 0405'!$AV:$AV,$D$93,'Report Pacote 0405'!$AW:$AW,$A$103,'Report Pacote 0405'!$H:$H,$W101) -> 0 | AE101: =SUMIFS('Report Pacote 0405'!T:T,'Report Pacote 0405'!$AV:$AV,$D$93,'Report Pacote 0405'!$AW:$AW,$A$101,'Report Pacote 0405'!$H:$H,$W101)+SUMIFS('Report Pacote 0405'!T:T,'Report Pacote 0405'!$AV:$AV,$D$93,'Report Pacote 0405'!$AW:$AW,$A$102,'Report Pacote 0405'!$H:$H,$W101)+SUMIFS('Report Pacote 0405'!T:T,'Report Pacote 0405'!$AV:$AV,$D$93,'Report Pacote 0405'!$AW:$AW,$A$103,'Report Pacote 0405'!$H:$H,$W101) -> 0 | AF101: =SUMIFS('Report Pacote 0405'!U:U,'Report Pacote 0405'!$AV:$AV,$D$93,'Report Pacote 0405'!$AW:$AW,$A$101,'Report Pacote 0405'!$H:$H,$W101)+SUMIFS('Report Pacote 0405'!U:U,'Report Pacote 0405'!$AV:$AV,$D$93,'Report Pacote 0405'!$AW:$AW,$A$102,'Report Pacote 0405'!$H:$H,$W101)+SUMIFS('Report Pacote 0405'!U:U,'Report Pacote 0405'!$AV:$AV,$D$93,'Report Pacote 0405'!$AW:$AW,$A$103,'Report Pacote 0405'!$H:$H,$W101) -> 0 | AG101: =SUMIFS('Report Pacote 0405'!V:V,'Report Pacote 0405'!$AV:$AV,$D$93,'Report Pacote 0405'!$AW:$AW,$A$101,'Report Pacote 0405'!$H:$H,$W101)+SUMIFS('Report Pacote 0405'!V:V,'Report Pacote 0405'!$AV:$AV,$D$93,'Report Pacote 0405'!$AW:$AW,$A$102,'Report Pacote 0405'!$H:$H,$W101)+SUMIFS('Report Pacote 0405'!V:V,'Report Pacote 0405'!$AV:$AV,$D$93,'Report Pacote 0405'!$AW:$AW,$A$103,'Report Pacote 0405'!$H:$H,$W101) -> 0 | AH101: =SUMIFS('Report Pacote 0405'!W:W,'Report Pacote 0405'!$AV:$AV,$D$93,'Report Pacote 0405'!$AW:$AW,$A$101,'Report Pacote 0405'!$H:$H,$W101)+SUMIFS('Report Pacote 0405'!W:W,'Report Pacote 0405'!$AV:$AV,$D$93,'Report Pacote 0405'!$AW:$AW,$A$102,'Report Pacote 0405'!$H:$H,$W101)+SUMIFS('Report Pacote 0405'!W:W,'Report Pacote 0405'!$AV:$AV,$D$93,'Report Pacote 0405'!$AW:$AW,$A$103,'Report Pacote 0405'!$H:$H,$W101) -> 0 | AI101: =IFERROR((AH102/AH101),"-") -> - | AK101: =SUMIFS('Report Pacote 0405'!AA:AA,'Report Pacote 0405'!$AV:$AV,$D$93,'Report Pacote 0405'!$AW:$AW,$A$102,'Report Pacote 0405'!$H:$H,$W101)+SUMIFS('Report Pacote 0405'!AA:AA,'Report Pacote 0405'!$AV:$AV,$D$93,'Report Pacote 0405'!$AW:$AW,$A$101,'Report Pacote 0405'!$H:$H,$W101)+SUMIFS('Report Pacote 0405'!AA:AA,'Report Pacote 0405'!$AV:$AV,$D$93,'Report Pacote 0405'!$AW:$AW,$A$103,'Report Pacote 0405'!$H:$H,$W101) -> 0 | AL101: =SUMIFS('Report Pacote 0405'!AB:AB,'Report Pacote 0405'!$AV:$AV,$D$93,'Report Pacote 0405'!$AW:$AW,$A$102,'Report Pacote 0405'!$H:$H,$W101)+SUMIFS('Report Pacote 0405'!AB:AB,'Report Pacote 0405'!$AV:$AV,$D$93,'Report Pacote 0405'!$AW:$AW,$A$101,'Report Pacote 0405'!$H:$H,$W101)+SUMIFS('Report Pacote 0405'!AB:AB,'Report Pacote 0405'!$AV:$AV,$D$93,'Report Pacote 0405'!$AW:$AW,$A$103,'Report Pacote 0405'!$H:$H,$W101) -> 0 | AM101: =SUMIFS('Report Pacote 0405'!AC:AC,'Report Pacote 0405'!$AV:$AV,$D$93,'Report Pacote 0405'!$AW:$AW,$A$102,'Report Pacote 0405'!$H:$H,$W101)+SUMIFS('Report Pacote 0405'!AC:AC,'Report Pacote 0405'!$AV:$AV,$D$93,'Report Pacote 0405'!$AW:$AW,$A$101,'Report Pacote 0405'!$H:$H,$W101)+SUMIFS('Report Pacote 0405'!AC:AC,'Report Pacote 0405'!$AV:$AV,$D$93,'Report Pacote 0405'!$AW:$AW,$A$103,'Report Pacote 0405'!$H:$H,$W101) -> 0 | AN101: =IFERROR((AM101/AL101),"-") -> - | AP101: =SUMIFS('Report Pacote 0405'!AK:AK,'Report Pacote 0405'!$AV:$AV,$D$93,'Report Pacote 0405'!$AW:$AW,$A$102,'Report Pacote 0405'!$H:$H,$W101)+SUMIFS('Report Pacote 0405'!AK:AK,'Report Pacote 0405'!$AV:$AV,$D$93,'Report Pacote 0405'!$AW:$AW,$A$101,'Report Pacote 0405'!$H:$H,$W101)+SUMIFS('Report Pacote 0405'!AJ:AJ,'Report Pacote 0405'!$AV:$AV,$D$93,'Report Pacote 0405'!$AW:$AW,$A$103,'Report Pacote 0405'!$H:$H,$W101) -> 0 | AQ101: =SUMIFS('Report Pacote 0405'!AL:AL,'Report Pacote 0405'!$AV:$AV,$D$93,'Report Pacote 0405'!$AW:$AW,$A$102,'Report Pacote 0405'!$H:$H,$W101)+SUMIFS('Report Pacote 0405'!AL:AL,'Report Pacote 0405'!$AV:$AV,$D$93,'Report Pacote 0405'!$AW:$AW,$A$101,'Report Pacote 0405'!$H:$H,$W101)+SUMIFS('Report Pacote 0405'!AK:AK,'Report Pacote 0405'!$AV:$AV,$D$93,'Report Pacote 0405'!$AW:$AW,$A$103,'Report Pacote 0405'!$H:$H,$W101) -> 0 | AR101: =IFERROR((AP101/AQ101),"-") -> - | AT101: =SUMIFS('Report Pacote 0405'!AO:AO,'Report Pacote 0405'!$AV:$AV,$D$93,'Report Pacote 0405'!$AW:$AW,$A$102,'Report Pacote 0405'!$H:$H,$W101)+SUMIFS('Report Pacote 0405'!AO:AO,'Report Pacote 0405'!$AV:$AV,$D$93,'Report Pacote 0405'!$AW:$AW,$A$101,'Report Pacote 0405'!$H:$H,$W101)+SUMIFS('Report Pacote 0405'!AN:AN,'Report Pacote 0405'!$AV:$AV,$D$93,'Report Pacote 0405'!$AW:$AW,$A$103,'Report Pacote 0405'!$H:$H,$W101) -> 0 | AU101: =SUMIFS('Report Pacote 0405'!AP:AP,'Report Pacote 0405'!$AV:$AV,$D$93,'Report Pacote 0405'!$AW:$AW,$A$102,'Report Pacote 0405'!$H:$H,$W101)+SUMIFS('Report Pacote 0405'!AP:AP,'Report Pacote 0405'!$AV:$AV,$D$93,'Report Pacote 0405'!$AW:$AW,$A$101,'Report Pacote 0405'!$H:$H,$W101)+SUMIFS('Report Pacote 0405'!AO:AO,'Report Pacote 0405'!$AV:$AV,$D$93,'Report Pacote 0405'!$AW:$AW,$A$103,'Report Pacote 0405'!$H:$H,$W101) -> 0 | AW101: =AK101/Quadros!$D$4 -> 0 | AX101: =AM101/Quadros!$D$6 -> 0 | AY101: =IF((AK101-AM101)/(Quadros!$D$4-Quadros!$D$6)<0,"-",(AK101-AM101)/(Quadros!$D$4-Quadros!$D$6)) -> 0
A102: Pacote 05 - Segmento 2.5 - 138+160 a 153+420 | G102: R | K102: R | O102: R | S102: R | W102: R | X102: =SUMIF($AA$7:$AG$7,"="&$D$4,$AA102:$AG102) -> 0 | AA102: =SUMIFS('Report Pacote 0405'!P:P,'Report Pacote 0405'!$AV:$AV,$D$93,'Report Pacote 0405'!$AW:$AW,$A$101,'Report Pacote 0405'!$H:$H,$W102)+SUMIFS('Report Pacote 0405'!P:P,'Report Pacote 0405'!$AV:$AV,$D$93,'Report Pacote 0405'!$AW:$AW,$A$102,'Report Pacote 0405'!$H:$H,$W102)+SUMIFS('Report Pacote 0405'!P:P,'Report Pacote 0405'!$AV:$AV,$D$93,'Report Pacote 0405'!$AW:$AW,$A$103,'Report Pacote 0405'!$H:$H,$W102) -> 0 | AB102: =SUMIFS('Report Pacote 0405'!Q:Q,'Report Pacote 0405'!$AV:$AV,$D$93,'Report Pacote 0405'!$AW:$AW,$A$101,'Report Pacote 0405'!$H:$H,$W102)+SUMIFS('Report Pacote 0405'!Q:Q,'Report Pacote 0405'!$AV:$AV,$D$93,'Report Pacote 0405'!$AW:$AW,$A$102,'Report Pacote 0405'!$H:$H,$W102)+SUMIFS('Report Pacote 0405'!Q:Q,'Report Pacote 0405'!$AV:$AV,$D$93,'Report Pacote 0405'!$AW:$AW,$A$103,'Report Pacote 0405'!$H:$H,$W102) -> 0 | AC102: =SUMIFS('Report Pacote 0405'!R:R,'Report Pacote 0405'!$AV:$AV,$D$93,'Report Pacote 0405'!$AW:$AW,$A$101,'Report Pacote 0405'!$H:$H,$W102)+SUMIFS('Report Pacote 0405'!R:R,'Report Pacote 0405'!$AV:$AV,$D$93,'Report Pacote 0405'!$AW:$AW,$A$102,'Report Pacote 0405'!$H:$H,$W102)+SUMIFS('Report Pacote 0405'!R:R,'Report Pacote 0405'!$AV:$AV,$D$93,'Report Pacote 0405'!$AW:$AW,$A$103,'Report Pacote 0405'!$H:$H,$W102) -> 0 | AD102: =SUMIFS('Report Pacote 0405'!S:S,'Report Pacote 0405'!$AV:$AV,$D$93,'Report Pacote 0405'!$AW:$AW,$A$101,'Report Pacote 0405'!$H:$H,$W102)+SUMIFS('Report Pacote 0405'!S:S,'Report Pacote 0405'!$AV:$AV,$D$93,'Report Pacote 0405'!$AW:$AW,$A$102,'Report Pacote 0405'!$H:$H,$W102)+SUMIFS('Report Pacote 0405'!S:S,'Report Pacote 0405'!$AV:$AV,$D$93,'Report Pacote 0405'!$AW:$AW,$A$103,'Report Pacote 0405'!$H:$H,$W102) -> 0 | AE102: =SUMIFS('Report Pacote 0405'!T:T,'Report Pacote 0405'!$AV:$AV,$D$93,'Report Pacote 0405'!$AW:$AW,$A$101,'Report Pacote 0405'!$H:$H,$W102)+SUMIFS('Report Pacote 0405'!T:T,'Report Pacote 0405'!$AV:$AV,$D$93,'Report Pacote 0405'!$AW:$AW,$A$102,'Report Pacote 0405'!$H:$H,$W102)+SUMIFS('Report Pacote 0405'!T:T,'Report Pacote 0405'!$AV:$AV,$D$93,'Report Pacote 0405'!$AW:$AW,$A$103,'Report Pacote 0405'!$H:$H,$W102) -> 0 | AF102: =SUMIFS('Report Pacote 0405'!U:U,'Report Pacote 0405'!$AV:$AV,$D$93,'Report Pacote 0405'!$AW:$AW,$A$101,'Report Pacote 0405'!$H:$H,$W102)+SUMIFS('Report Pacote 0405'!U:U,'Report Pacote 0405'!$AV:$AV,$D$93,'Report Pacote 0405'!$AW:$AW,$A$102,'Report Pacote 0405'!$H:$H,$W102)+SUMIFS('Report Pacote 0405'!U:U,'Report Pacote 0405'!$AV:$AV,$D$93,'Report Pacote 0405'!$AW:$AW,$A$103,'Report Pacote 0405'!$H:$H,$W102) -> 0 | AG102: =SUMIFS('Report Pacote 0405'!V:V,'Report Pacote 0405'!$AV:$AV,$D$93,'Report Pacote 0405'!$AW:$AW,$A$101,'Report Pacote 0405'!$H:$H,$W102)+SUMIFS('Report Pacote 0405'!V:V,'Report Pacote 0405'!$AV:$AV,$D$93,'Report Pacote 0405'!$AW:$AW,$A$102,'Report Pacote 0405'!$H:$H,$W102)+SUMIFS('Report Pacote 0405'!V:V,'Report Pacote 0405'!$AV:$AV,$D$93,'Report Pacote 0405'!$AW:$AW,$A$103,'Report Pacote 0405'!$H:$H,$W102) -> 0 | AH102: =SUMIFS('Report Pacote 0405'!W:W,'Report Pacote 0405'!$AV:$AV,$D$93,'Report Pacote 0405'!$AW:$AW,$A$101,'Report Pacote 0405'!$H:$H,$W102)+SUMIFS('Report Pacote 0405'!W:W,'Report Pacote 0405'!$AV:$AV,$D$93,'Report Pacote 0405'!$AW:$AW,$A$102,'Report Pacote 0405'!$H:$H,$W102)+SUMIFS('Report Pacote 0405'!W:W,'Report Pacote 0405'!$AV:$AV,$D$93,'Report Pacote 0405'!$AW:$AW,$A$103,'Report Pacote 0405'!$H:$H,$W102) -> 0
A103: Pacote 05 - Segmento 3.1 - 153+000 a 167+400
A105: Pacote 05 - Segmento 3.1 - 153+000 a 167+400 | D105: Pacote 06 - km 167+300 0 a 225+000 | E105: m | G105: P | I105: =IFERROR((H106/H105),"-") -> - | K105: P | M105: =IFERROR((L106/L105),"-") -> - | O105: P | Q105: =IFERROR((P106/P105),"-") -> - | S105: P | U105: =IFERROR((T106/T105),"-") -> - | W105: P | X105: =SUMIF($AA$7:$AG$7,"="&$D$4,$AA105:$AG105) -> 0 | Y105: =IFERROR((X106/X105),"-") -> - | AA105: =SUMIFS('Report Pacote 06'!V:V,'Report Pacote 06'!$CH:$CH,$D$93,'Report Pacote 06'!$G:$G,'Report Consolidado Semanal'!$W105) -> 0 | AB105: =SUMIFS('Report Pacote 06'!W:W,'Report Pacote 06'!$CH:$CH,$D$93,'Report Pacote 06'!$G:$G,'Report Consolidado Semanal'!$W105) -> 0 | AC105: =SUMIFS('Report Pacote 06'!X:X,'Report Pacote 06'!$CH:$CH,$D$93,'Report Pacote 06'!$G:$G,'Report Consolidado Semanal'!$W105) -> 0 | AD105: =SUMIFS('Report Pacote 06'!Y:Y,'Report Pacote 06'!$CH:$CH,$D$93,'Report Pacote 06'!$G:$G,'Report Consolidado Semanal'!$W105) -> 0 | AE105: =SUMIFS('Report Pacote 06'!Z:Z,'Report Pacote 06'!$CH:$CH,$D$93,'Report Pacote 06'!$G:$G,'Report Consolidado Semanal'!$W105) -> 0 | AF105: =SUMIFS('Report Pacote 06'!AA:AA,'Report Pacote 06'!$CH:$CH,$D$93,'Report Pacote 06'!$G:$G,'Report Consolidado Semanal'!$W105) -> 0 | AG105: =SUMIFS('Report Pacote 06'!AB:AB,'Report Pacote 06'!$CH:$CH,$D$93,'Report Pacote 06'!$G:$G,'Report Consolidado Semanal'!$W105) -> 0 | AH105: =SUMIF($AA$7:$AG$7,"<="&$D$4,$AA105:$AG105) -> 0 | AI105: =IFERROR((AH106/AH105),"-") -> - | AK105: =SUMIFS('Report Pacote 06'!BN:BN,'Report Pacote 06'!$CH:$CH,$D$93,'Report Pacote 06'!$G:$G,'Report Consolidado Semanal'!$W105) -> 0 | AL105: =SUMIFS('Report Pacote 06'!BO:BO,'Report Pacote 06'!$CH:$CH,$D$93,'Report Pacote 06'!$G:$G,'Report Consolidado Semanal'!$W105) -> 0 | AM105: =SUMIFS('Report Pacote 06'!BP:BP,'Report Pacote 06'!$CH:$CH,$D$93,'Report Pacote 06'!$G:$G,'Report Consolidado Semanal'!$W105) -> 0 | AN105: =IFERROR((AM105/AL105),"-") -> - | AP105: =SUMIFS('Report Pacote 06'!BU:BU,'Report Pacote 06'!$CH:$CH,'Report Consolidado Semanal'!$D$93,'Report Pacote 06'!$G:$G,'Report Consolidado Semanal'!$W105) -> 648 | AQ105: =SUMIFS('Report Pacote 06'!BX:BX,'Report Pacote 06'!$CH:$CH,'Report Consolidado Semanal'!$D$93,'Report Pacote 06'!$G:$G,'Report Consolidado Semanal'!$W105) -> 648 | AR105: =IFERROR((AP105/AQ105),"-") -> 1 | AT105: =SUMIFS('Report Pacote 06'!CA:CA,'Report Pacote 06'!$CH:$CH,$D$93,'Report Pacote 06'!$G:$G,'Report Consolidado Semanal'!$W105) -> 3084 | AU105: =SUMIFS('Report Pacote 06'!CB:CB,'Report Pacote 06'!$CH:$CH,$D$93,'Report Pacote 06'!$G:$G,'Report Consolidado Semanal'!$W105) -> 2436 | AW105: =AK105/Quadros!$D$4 -> 0 | AX105: =AM105/Quadros!$D$6 -> 0 | AY105: =IF((AK105-AM105)/(Quadros!$D$4-Quadros!$D$6)<0,"-",(AK105-AM105)/(Quadros!$D$4-Quadros!$D$6)) -> 0
G106: R | K106: R | O106: R | S106: R | W106: R | X106: =SUMIF($AA$7:$AG$7,"="&$D$4,$AA106:$AG106) -> 0 | AA106: =SUMIFS('Report Pacote 06'!V:V,'Report Pacote 06'!$CH:$CH,$D$93,'Report Pacote 06'!$G:$G,'Report Consolidado Semanal'!$W106) -> 0 | AB106: =SUMIFS('Report Pacote 06'!W:W,'Report Pacote 06'!$CH:$CH,$D$93,'Report Pacote 06'!$G:$G,'Report Consolidado Semanal'!$W106) -> 0 | AC106: =SUMIFS('Report Pacote 06'!X:X,'Report Pacote 06'!$CH:$CH,$D$93,'Report Pacote 06'!$G:$G,'Report Consolidado Semanal'!$W106) -> 0 | AD106: =SUMIFS('Report Pacote 06'!Y:Y,'Report Pacote 06'!$CH:$CH,$D$93,'Report Pacote 06'!$G:$G,'Report Consolidado Semanal'!$W106) -> 0 | AE106: =SUMIFS('Report Pacote 06'!Z:Z,'Report Pacote 06'!$CH:$CH,$D$93,'Report Pacote 06'!$G:$G,'Report Consolidado Semanal'!$W106) -> 0 | AF106: =SUMIFS('Report Pacote 06'!AA:AA,'Report Pacote 06'!$CH:$CH,$D$93,'Report Pacote 06'!$G:$G,'Report Consolidado Semanal'!$W106) -> 0 | AG106: =SUMIFS('Report Pacote 06'!AB:AB,'Report Pacote 06'!$CH:$CH,$D$93,'Report Pacote 06'!$G:$G,'Report Consolidado Semanal'!$W106) -> 0 | AH106: =SUMIF($AA$7:$AG$7,"<="&$D$4,$AA106:$AG106) -> 0
D109: Pacote 07/08 - km 227+200 a 292+260 | E109: m | G109: P | I109: =IFERROR((H110/H109),"-") -> - | K109: P | M109: =IFERROR((L110/L109),"-") -> - | O109: P | Q109: =IFERROR((P110/P109),"-") -> - | S109: P | U109: =IFERROR((T110/T109),"-") -> - | W109: P | X109: =SUMIF($AA$7:$AG$7,"="&$D$4,$AA109:$AG109) -> 0 | Y109: =IFERROR((X110/X109),"-") -> - | AA109: =SUMIFS('Report Pacote 07-08'!AD:AD,'Report Pacote 07-08'!$CB:$CB,$D93,'Report Pacote 07-08'!$J:$J,$W109) -> 0 | AB109: =SUMIFS('Report Pacote 07-08'!AE:AE,'Report Pacote 07-08'!$CB:$CB,$D93,'Report Pacote 07-08'!$J:$J,$W109) -> 0 | AC109: =SUMIFS('Report Pacote 07-08'!AF:AF,'Report Pacote 07-08'!$CB:$CB,$D93,'Report Pacote 07-08'!$J:$J,$W109) -> 0 | AD109: =SUMIFS('Report Pacote 07-08'!AG:AG,'Report Pacote 07-08'!$CB:$CB,$D93,'Report Pacote 07-08'!$J:$J,$W109) -> 0 | AE109: =SUMIFS('Report Pacote 07-08'!AH:AH,'Report Pacote 07-08'!$CB:$CB,$D93,'Report Pacote 07-08'!$J:$J,$W109) -> 0 | AF109: =SUMIFS('Report Pacote 07-08'!AI:AI,'Report Pacote 07-08'!$CB:$CB,$D93,'Report Pacote 07-08'!$J:$J,$W109) -> 0 | AG109: =SUMIFS('Report Pacote 07-08'!AJ:AJ,'Report Pacote 07-08'!$CB:$CB,$D93,'Report Pacote 07-08'!$J:$J,$W109) -> 0 | AH109: =SUMIF($AA$7:$AG$7,"<="&$D$4,$AA109:$AG109) -> 0 | AI109: =IFERROR((AH110/AH109),"-") -> - | AK109: =SUMIFS('Report Pacote 07-08'!BM:BM,'Report Pacote 07-08'!$CB:$CB,$D93,'Report Pacote 07-08'!$J:$J,$W109) -> 0 | AL109: =SUMIFS('Report Pacote 07-08'!BN:BN,'Report Pacote 07-08'!$CB:$CB,$D93,'Report Pacote 07-08'!$J:$J,$W109) -> 0 | AM109: =SUMIFS('Report Pacote 07-08'!BO:BO,'Report Pacote 07-08'!$CB:$CB,$D93,'Report Pacote 07-08'!$J:$J,$W109) -> 0 | AN109: =IFERROR((AM109/AL109),"-") -> - | AP109: 3071.22 | AQ109: 3621 | AR109: =IFERROR((AP109/AQ109),"-") -> 0.84816901 | AT109: 10559 | AU109: =AT109-AP109 -> 7487.78 | AW109: =AK109/Quadros!$D$4 -> 0 | AX109: =AM109/Quadros!$D$6 -> 0 | AY109: =IF((AK109-AM109)/(Quadros!$D$4-Quadros!$D$6)<0,"-",(AK109-AM109)/(Quadros!$D$4-Quadros!$D$6)) -> 0
G110: R | K110: R | O110: R | S110: R | W110: R | X110: =SUMIF($AA$7:$AG$7,"="&$D$4,$AA110:$AG110) -> 0 | AA110: =SUMIFS('Report Pacote 07-08'!AD:AD,'Report Pacote 07-08'!$CB:$CB,$D94,'Report Pacote 07-08'!$J:$J,$W110) -> 0 | AB110: =SUMIFS('Report Pacote 07-08'!AE:AE,'Report Pacote 07-08'!$CB:$CB,$D94,'Report Pacote 07-08'!$J:$J,$W110) -> 0 | AC110: =SUMIFS('Report Pacote 07-08'!AF:AF,'Report Pacote 07-08'!$CB:$CB,$D94,'Report Pacote 07-08'!$J:$J,$W110) -> 0 | AD110: =SUMIFS('Report Pacote 07-08'!AG:AG,'Report Pacote 07-08'!$CB:$CB,$D94,'Report Pacote 07-08'!$J:$J,$W110) -> 0 | AE110: =SUMIFS('Report Pacote 07-08'!AH:AH,'Report Pacote 07-08'!$CB:$CB,$D94,'Report Pacote 07-08'!$J:$J,$W110) -> 0 | AF110: =SUMIFS('Report Pacote 07-08'!AI:AI,'Report Pacote 07-08'!$CB:$CB,$D94,'Report Pacote 07-08'!$J:$J,$W110) -> 0 | AG110: =SUMIFS('Report Pacote 07-08'!AJ:AJ,'Report Pacote 07-08'!$CB:$CB,$D94,'Report Pacote 07-08'!$J:$J,$W110) -> 0 | AH110: =SUMIF($AA$7:$AG$7,"<="&$D$4,$AA110:$AG110) -> 0 | AK110: =SUMIFS('Report Pacote 07-08'!X:X,'Report Pacote 07-08'!$CB:$CB,$A110,'Report Pacote 07-08'!$J:$J,$W110) -> 0 | AL110: =SUMIFS('Report Pacote 07-08'!Y:Y,'Report Pacote 07-08'!$CB:$CB,$A110,'Report Pacote 07-08'!$J:$J,$W110) -> 0 | AM110: =SUMIFS('Report Pacote 07-08'!Z:Z,'Report Pacote 07-08'!$CB:$CB,$A110,'Report Pacote 07-08'!$J:$J,$W110) -> 0

Sheet Gráficos
G2: 1 | H2: 2 | I2: 3 | J2: 4 | K2: 5 | L2: 6 | T2: 1 | U2: 2 | V2: 3 | W2: 4 | X2: 5 | Y2: 6
F3: ORIGEM | G3: seg | H3: ter | I3: qua | J3: qui | K3: sex | L3: sáb | N3: SEMANA | P3: PLANEJADO MÊS | Q3: PLANEJADO ATÉ A DATA | R3: REAL MÊS | T3: seg | U3: ter | V3: qua | W3: qui | X3: sex | Y3: sáb | AA3: SEMANA | AC3: PLANEJADO MÊS | AD3: PLANEJADO ATÉ A DATA | AE3: REAL MÊS | AJ3: Ponte sobre o Rio Araguaia | AN3: seg | AO3: ter | AP3: qua | AQ3: qui | AR3: sex | AS3: sáb
D5: PCTE 4/5 | F5: M | G5: =Quadros!J6/1000 -> 59.916438 | H5: =G5 -> 59.916438 | I5: =H5 -> 59.916438 | J5: =I5 -> 59.916438 | K5: =J5 -> 59.916438 | L5: =K5 -> 59.916438 | N5: =SUM(G5:L5) -> 359.49863 | O5: =N5 -> 359.49863 | P5: =SUM('Report Consolidado Semanal'!AK13:AK14,'Report Consolidado Semanal'!AK17:AK18,'Report Consolidado Semanal'!AK33:AK34,'Report Consolidado Semanal'!AK37:AK38)/1000 -> 1617.7438 | Q5: =SUM('Report Consolidado Semanal'!AL13:AL14,'Report Consolidado Semanal'!AL17:AL18,'Report Consolidado Semanal'!AL33:AL34,'Report Consolidado Semanal'!AL37:AL38)/1000 -> 821.15657 | R5: =SUM('Report Consolidado Semanal'!AM13:AM14,'Report Consolidado Semanal'!AM17:AM18,'Report Consolidado Semanal'!AM33:AM34,'Report Consolidado Semanal'!AM37:AM38)/1000 -> 628.89172 | T5: =Quadros!U6 -> 928.8837 | U5: =T5 -> 928.8837 | V5: =U5 -> 928.8837 | W5: =V5 -> 928.8837 | X5: =W5 -> 928.8837 | Y5: =X5 -> 928.8837 | AA5: =SUM(T5:Y5) -> 5573.3022 | AC5: {=SUM('Report Consolidado Semanal'!AK53:AK54+'Report Consolidado Semanal'!AK57:AK58)} -> 25079.86 | AD5: {=SUM('Report Consolidado Semanal'!AL53:AL54+'Report Consolidado Semanal'!AL57:AL58)} -> 13028.12 | AE5: {=SUM('Report Consolidado Semanal'!AM53:AM54+'Report Consolidado Semanal'!AM57:AM58)} -> 7323.2 | AJ5: Pilares | AL5: Meta | AN5: =Quadros!AE6 -> 2 | AO5: =AN5 -> 2 | AP5: =AO5 -> 2 | AQ5: =AP5 -> 2 | AR5: =AQ5 -> 2 | AS5: =AR5 -> 2
D7: =D5 -> PCTE 4/5 | F7: P | G7: =SUM('Report Consolidado Semanal'!AA13,'Report Consolidado Semanal'!AA17,'Report Consolidado Semanal'!AA33,'Report Consolidado Semanal'!AA37)/1000 -> 57.316 | H7: =SUM('Report Consolidado Semanal'!AB13,'Report Consolidado Semanal'!AB17,'Report Consolidado Semanal'!AB33,'Report Consolidado Semanal'!AB37)/1000 -> 57.316 | I7: =SUM('Report Consolidado Semanal'!AC13,'Report Consolidado Semanal'!AC17,'Report Consolidado Semanal'!AC33,'Report Consolidado Semanal'!AC37)/1000 -> 57.316 | J7: =SUM('Report Consolidado Semanal'!AD13,'Report Consolidado Semanal'!AD17,'Report Consolidado Semanal'!AD33,'Report Consolidado Semanal'!AD37)/1000 -> 57.246 | K7: =SUM('Report Consolidado Semanal'!AE13,'Report Consolidado Semanal'!AE17,'Report Consolidado Semanal'!AE33,'Report Consolidado Semanal'!AE37)/1000 -> 50.536 | L7: =SUM('Report Consolidado Semanal'!AF13,'Report Consolidado Semanal'!AF17,'Report Consolidado Semanal'!AF33,'Report Consolidado Semanal'!AF37)/1000 -> 50.536 | N7: =SUM('Report Consolidado Semanal'!AH13,'Report Consolidado Semanal'!AH17,'Report Consolidado Semanal'!AH33,'Report Consolidado Semanal'!AH37)/1000 -> 114.632 | T7: =SUM('Report Consolidado Semanal'!AA53,'Report Consolidado Semanal'!AA57) -> 854 | U7: =SUM('Report Consolidado Semanal'!AB53,'Report Consolidado Semanal'!AB57) -> 819 | V7: =SUM('Report Consolidado Semanal'!AC53,'Report Consolidado Semanal'!AC57) -> 830 | W7: =SUM('Report Consolidado Semanal'!AD53,'Report Consolidado Semanal'!AD57) -> 830 | X7: =SUM('Report Consolidado Semanal'!AE53,'Report Consolidado Semanal'!AE57) -> 740 | Y7: =SUM('Report Consolidado Semanal'!AF53,'Report Consolidado Semanal'!AF57) -> 740 | AA7: =SUM('Report Consolidado Semanal'!AH53,'Report Consolidado Semanal'!AH57) -> 1673 | AL7: Previsto | AN7: ='Report Consolidado Semanal'!AA73 -> 0 | AO7: ='Report Consolidado Semanal'!AB73 -> 0 | AP7: ='Report Consolidado Semanal'!AC73 -> 4 | AQ7: ='Report Consolidado Semanal'!AD73 -> 0 | AR7: ='Report Consolidado Semanal'!AE73 -> 0 | AS7: ='Report Consolidado Semanal'!AF73 -> 5
D9: =D7 -> PCTE 4/5 | F9: R | G9: =SUM('Report Consolidado Semanal'!AA14,'Report Consolidado Semanal'!AA18,'Report Consolidado Semanal'!AA34,'Report Consolidado Semanal'!AA38)/1000 -> 57.0734 | H9: =SUM('Report Consolidado Semanal'!AB14,'Report Consolidado Semanal'!AB18,'Report Consolidado Semanal'!AB34,'Report Consolidado Semanal'!AB38)/1000 -> 56.07148 | I9: =SUM('Report Consolidado Semanal'!AC14,'Report Consolidado Semanal'!AC18,'Report Consolidado Semanal'!AC34,'Report Consolidado Semanal'!AC38)/1000 -> 0 | J9: =SUM('Report Consolidado Semanal'!AD14,'Report Consolidado Semanal'!AD18,'Report Consolidado Semanal'!AD34,'Report Consolidado Semanal'!AD38)/1000 -> 0 | K9: =SUM('Report Consolidado Semanal'!AE14,'Report Consolidado Semanal'!AE18,'Report Consolidado Semanal'!AE34,'Report Consolidado Semanal'!AE38)/1000 -> 0 | L9: =SUM('Report Consolidado Semanal'!AF14,'Report Consolidado Semanal'!AF18,'Report Consolidado Semanal'!AF34,'Report Consolidado Semanal'!AF38)/1000 -> 0 | N9: =SUM('Report Consolidado Semanal'!AH14,'Report Consolidado Semanal'!AH18,'Report Consolidado Semanal'!AH34,'Report Consolidado Semanal'!AH38)/1000 -> 113.14488 | T9: =SUM('Report Consolidado Semanal'!AA54,'Report Consolidado Semanal'!AA58) -> 759 | U9: =SUM('Report Consolidado Semanal'!AB54,'Report Consolidado Semanal'!AB58) -> 712.5 | V9: =SUM('Report Consolidado Semanal'!AC54,'Report Consolidado Semanal'!AC58) -> 0 | W9: =SUM('Report Consolidado Semanal'!AD54,'Report Consolidado Semanal'!AD58) -> 0 | X9: =SUM('Report Consolidado Semanal'!AE54,'Report Consolidado Semanal'!AE58) -> 0 | Y9: =SUM('Report Consolidado Semanal'!AF54,'Report Consolidado Semanal'!AF58) -> 0 | AA9: =SUM('Report Consolidado Semanal'!AH54,'Report Consolidado Semanal'!AH58) -> 1471.5 | AL9: Realizado | AN9: ='Report Consolidado Semanal'!AA74 -> 0 | AO9: ='Report Consolidado Semanal'!AB74 -> 0 | AP9: ='Report Consolidado Semanal'!AC74 -> 0 | AQ9: ='Report Consolidado Semanal'!AD74 -> 0 | AR9: ='Report Consolidado Semanal'!AE74 -> 0 | AS9: ='Report Consolidado Semanal'!AF74 -> 0
D11: PCTE 06 | F11: M | G11: =Quadros!K6/1000 -> 39.091084 | H11: =G11 -> 39.091084 | I11: =H11 -> 39.091084 | J11: =I11 -> 39.091084 | K11: =J11 -> 39.091084 | L11: =K11 -> 39.091084 | N11: =SUM(G11:L11) -> 234.54651 | P11: =SUM('Report Consolidado Semanal'!AK21:AK22,'Report Consolidado Semanal'!AK41:AK42)/1000 -> 1055.4593 | Q11: =SUM('Report Consolidado Semanal'!AL21:AL22,'Report Consolidado Semanal'!AL41:AL42)/1000 -> 469.09301 | R11: =SUM('Report Consolidado Semanal'!AM21:AM22,'Report Consolidado Semanal'!AM41:AM42)/1000 -> 399.7211 | T11: =Quadros!V6 -> 511.09111 | U11: =T11 -> 511.09111 | V11: =U11 -> 511.09111 | W11: =V11 -> 511.09111 | X11: =W11 -> 511.09111 | Y11: =X11 -> 511.09111 | AA11: =SUM(T11:Y11) -> 3066.5467 | AC11: =SUM('Report Consolidado Semanal'!AK61:AK62) -> 13799.46 | AD11: =SUM('Report Consolidado Semanal'!AL61:AL62) -> 6133.0933 | AE11: =SUM('Report Consolidado Semanal'!AM61:AM62) -> 2915 | AJ11: Travessas | AL11: Meta | AN11: =Quadros!AF6 -> 1 | AO11: =AN11 -> 1 | AP11: =AO11 -> 1 | AQ11: =AP11 -> 1 | AR11: =AQ11 -> 1 | AS11: =AR11 -> 1
D13: PCTE 06 | F13: P | G13: =SUM('Report Consolidado Semanal'!AA21,'Report Consolidado Semanal'!AA41)/1000 -> 47.649398 | H13: =SUM('Report Consolidado Semanal'!AB21,'Report Consolidado Semanal'!AB41)/1000 -> 47.649398 | I13: =SUM('Report Consolidado Semanal'!AC21,'Report Consolidado Semanal'!AC41)/1000 -> 47.649398 | J13: =SUM('Report Consolidado Semanal'!AD21,'Report Consolidado Semanal'!AD41)/1000 -> 47.649398 | K13: =SUM('Report Consolidado Semanal'!AE21,'Report Consolidado Semanal'!AE41)/1000 -> 47.649398 | L13: =SUM('Report Consolidado Semanal'!AF21,'Report Consolidado Semanal'!AF41)/1000 -> 47.149398 | N13: =SUM('Report Consolidado Semanal'!AH21,'Report Consolidado Semanal'!AH41)/1000 -> 95.298797 | T13: =SUM('Report Consolidado Semanal'!AA61) -> 100 | U13: =SUM('Report Consolidado Semanal'!AB61) -> 250 | V13: =SUM('Report Consolidado Semanal'!AC61) -> 350 | W13: =SUM('Report Consolidado Semanal'!AD61) -> 350 | X13: =SUM('Report Consolidado Semanal'!AE61) -> 350 | Y13: =SUM('Report Consolidado Semanal'!AF61) -> 350 | AA13: =SUM('Report Consolidado Semanal'!AH61) -> 350 | AJ13: Peso | AL13: Previsto | AN13: ='Report Consolidado Semanal'!AA77 -> 0 | AO13: ='Report Consolidado Semanal'!AB77 -> 0 | AP13: ='Report Consolidado Semanal'!AC77 -> 0 | AQ13: ='Report Consolidado Semanal'!AD77 -> 0.5 | AR13: ='Report Consolidado Semanal'!AE77 -> 0 | AS13: ='Report Consolidado Semanal'!AF77 -> 1
D15: PCTE 06 | F15: R | G15: =SUM('Report Consolidado Semanal'!AA22,'Report Consolidado Semanal'!AA42)/1000 -> 36.23926 | H15: =SUM('Report Consolidado Semanal'!AB22,'Report Consolidado Semanal'!AB42)/1000 -> 35.89605 | I15: =SUM('Report Consolidado Semanal'!AC22,'Report Consolidado Semanal'!AC42)/1000 -> 0 | J15: =SUM('Report Consolidado Semanal'!AD22,'Report Consolidado Semanal'!AD42)/1000 -> 0 | K15: =SUM('Report Consolidado Semanal'!AE22,'Report Consolidado Semanal'!AE42)/1000 -> 0 | L15: =SUM('Report Consolidado Semanal'!AF22,'Report Consolidado Semanal'!AF42)/1000 -> 0 | N15: =SUM('Report Consolidado Semanal'!AH22,'Report Consolidado Semanal'!AH42)/1000 -> 72.13531 | T15: =SUM('Report Consolidado Semanal'!AA62) -> 150 | U15: =SUM('Report Consolidado Semanal'!AB62) -> 326 | V15: =SUM('Report Consolidado Semanal'!AC62) -> 0 | W15: =SUM('Report Consolidado Semanal'!AD62) -> 0 | X15: =SUM('Report Consolidado Semanal'!AE62) -> 0 | Y15: =SUM('Report Consolidado Semanal'!AF62) -> 0 | AA15: =SUM('Report Consolidado Semanal'!AH62) -> 476 | AJ15: =B172 -> 0.031426 | AL15: Realizado | AN15: ='Report Consolidado Semanal'!AA78 -> 0 | AO15: ='Report Consolidado Semanal'!AB78 -> 0 | AP15: ='Report Consolidado Semanal'!AC78 -> 0 | AQ15: ='Report Consolidado Semanal'!AD78 -> 0 | AR15: ='Report Consolidado Semanal'!AE78 -> 0 | AS15: ='Report Consolidado Semanal'!AF78 -> 0
D17: PCTE 7/8 | F17: M | G17: =Quadros!L6/1000 -> 14.06966 | H17: =G17 -> 14.06966 | I17: =H17 -> 14.06966 | J17: =I17 -> 14.06966 | K17: =J17 -> 14.06966 | L17: =K17 -> 14.06966 | N17: =SUM(G17:L17) -> 84.41796 | P17: =SUM('Report Consolidado Semanal'!AK25:AK26,'Report Consolidado Semanal'!AK45:AK46)/1000 -> 379.88082 | Q17: =SUM('Report Consolidado Semanal'!AL25:AL26,'Report Consolidado Semanal'!AL45:AL46)/1000 -> 192.89011 | R17: =SUM('Report Consolidado Semanal'!AM25:AM26,'Report Consolidado Semanal'!AM45:AM46)/1000 -> 221.20588 | T17: =Quadros!W6 -> 500.81343 | U17: =T17 -> 500.81343 | V17: =U17 -> 500.81343 | W17: =V17 -> 500.81343 | X17: =W17 -> 500.81343 | Y17: =X17 -> 500.81343 | AA17: =SUM(T17:Y17) -> 3004.8806 | AC17: =SUM('Report Consolidado Semanal'!AK65:AK66) -> 13521.962 | AD17: =SUM('Report Consolidado Semanal'!AL65:AL66) -> 6959.2802 | AE17: =SUM('Report Consolidado Semanal'!AM65:AM66) -> 7173 | AJ17: Aduelas | AL17: Meta | AN17: =Quadros!AG6 -> 1 | AO17: =AN17 -> 1 | AP17: =AO17 -> 1 | AQ17: =AP17 -> 1 | AR17: =AQ17 -> 1 | AS17: =AR17 -> 1
D19: PCTE 7/8 | F19: P | G19: =SUM('Report Consolidado Semanal'!AA25,'Report Consolidado Semanal'!AA45)/1000 -> 10.111496 | H19: =SUM('Report Consolidado Semanal'!AB25,'Report Consolidado Semanal'!AB45)/1000 -> 10.111496 | I19: =SUM('Report Consolidado Semanal'!AC25,'Report Consolidado Semanal'!AC45)/1000 -> 10.111496 | J19: =SUM('Report Consolidado Semanal'!AD25,'Report Consolidado Semanal'!AD45)/1000 -> 10.111496 | K19: =SUM('Report Consolidado Semanal'!AE25,'Report Consolidado Semanal'!AE45)/1000 -> 10.111496 | L19: =SUM('Report Consolidado Semanal'!AF25,'Report Consolidado Semanal'!AF45)/1000 -> 10.111496 | N19: =SUM('Report Consolidado Semanal'!AH25,'Report Consolidado Semanal'!AH45)/1000 -> 20.222992 | T19: =SUM('Report Consolidado Semanal'!AA65) -> 452.6726 | U19: =SUM('Report Consolidado Semanal'!AB65) -> 452.6726 | V19: =SUM('Report Consolidado Semanal'!AC65) -> 452.6726 | W19: =SUM('Report Consolidado Semanal'!AD65) -> 452.6726 | X19: =SUM('Report Consolidado Semanal'!AE65) -> 452.6726 | Y19: =SUM('Report Consolidado Semanal'!AF65) -> 452.6726 | AA19: =SUM('Report Consolidado Semanal'!AH65) -> 905.3452 | AJ19: Peso | AL19: Previsto | AN19: ='Report Consolidado Semanal'!AA81 -> 3 | AO19: ='Report Consolidado Semanal'!AB81 -> 0 | AP19: ='Report Consolidado Semanal'!AC81 -> 0 | AQ19: ='Report Consolidado Semanal'!AD81 -> 0 | AR19: ='Report Consolidado Semanal'!AE81 -> 0 | AS19: ='Report Consolidado Semanal'!AF81 -> 1
D21: PCTE 7/8 | F21: R | G21: =SUM('Report Consolidado Semanal'!AA26,'Report Consolidado Semanal'!AA46)/1000 -> 14.580076 | H21: =SUM('Report Consolidado Semanal'!AB26,'Report Consolidado Semanal'!AB46)/1000 -> 14.792387 | I21: =SUM('Report Consolidado Semanal'!AC26,'Report Consolidado Semanal'!AC46)/1000 -> 0 | J21: =SUM('Report Consolidado Semanal'!AD26,'Report Consolidado Semanal'!AD46)/1000 -> 0 | K21: =SUM('Report Consolidado Semanal'!AE26,'Report Consolidado Semanal'!AE46)/1000 -> 0 | L21: =SUM('Report Consolidado Semanal'!AF26,'Report Consolidado Semanal'!AF46)/1000 -> 0 | N21: =SUM('Report Consolidado Semanal'!AH26,'Report Consolidado Semanal'!AH46)/1000 -> 29.372463 | T21: =SUM('Report Consolidado Semanal'!AA66) -> 609 | U21: =SUM('Report Consolidado Semanal'!AB66) -> 745 | V21: =SUM('Report Consolidado Semanal'!AC66) -> 0 | W21: =SUM('Report Consolidado Semanal'!AD66) -> 0 | X21: =SUM('Report Consolidado Semanal'!AE66) -> 0 | Y21: =SUM('Report Consolidado Semanal'!AF66) -> 0 | AA21: =SUM('Report Consolidado Semanal'!AH66) -> 1354 | AJ21: =B174 -> 0.344021 | AL21: Realizado | AN21: ='Report Consolidado Semanal'!AA82 -> 0 | AO21: ='Report Consolidado Semanal'!AB82 -> 3 | AP21: ='Report Consolidado Semanal'!AC82 -> 0 | AQ21: ='Report Consolidado Semanal'!AD82 -> 0 | AR21: ='Report Consolidado Semanal'!AE82 -> 0 | AS21: ='Report Consolidado Semanal'!AF82 -> 0
AJ23: Vigas Pré Moldadas | AL23: Meta | AN23: =Quadros!AH6 -> 1 | AO23: =AN23 -> 1 | AP23: =AO23 -> 1 | AQ23: =AP23 -> 1 | AR23: =AQ23 -> 1 | AS23: =AR23 -> 1
D24: Terraplanagem - Corte + Aterro - (x1000.m³) | R24: ='Report Consolidado Semanal'!$Y$7 -> 46217 | T24: Drenagem Superficial (m) | AG24: ='Report Consolidado Semanal'!$Y$7 -> 46217 | AL24: Previsto | AN24: ='Report Consolidado Semanal'!AA85 -> 0 | AO24: ='Report Consolidado Semanal'!AB85 -> 0 | AP24: ='Report Consolidado Semanal'!AC85 -> 0 | AQ24: ='Report Consolidado Semanal'!AD85 -> 1 | AR24: ='Report Consolidado Semanal'!AE85 -> 0 | AS24: ='Report Consolidado Semanal'!AF85 -> 1
AL25: Realizado | AN25: ='Report Consolidado Semanal'!AA86 -> 0 | AO25: ='Report Consolidado Semanal'!AB86 -> 0 | AP25: ='Report Consolidado Semanal'!AC86 -> 0 | AQ25: ='Report Consolidado Semanal'!AD86 -> 0 | AR25: ='Report Consolidado Semanal'!AE86 -> 0 | AS25: ='Report Consolidado Semanal'!AF86 -> 0
AJ27: Pré moldados | AL27: Meta | AN27: =Quadros!AI6 -> 21 | AO27: =AN27 -> 21 | AP27: =AO27 -> 21 | AQ27: =AP27 -> 21 | AR27: =AQ27 -> 21 | AS27: =AR27 -> 21
AL28: Previsto | AN28: ='Report Consolidado Semanal'!AA89 -> 40 | AO28: ='Report Consolidado Semanal'!AB89 -> 23 | AP28: ='Report Consolidado Semanal'!AC89 -> 40 | AQ28: ='Report Consolidado Semanal'!AD89 -> 23 | AR28: ='Report Consolidado Semanal'!AE89 -> 40 | AS28: ='Report Consolidado Semanal'!AF89 -> 23
AL29: Realizado | AN29: ='Report Consolidado Semanal'!AA90 -> 40 | AO29: ='Report Consolidado Semanal'!AB90 -> 23 | AP29: ='Report Consolidado Semanal'!AC90 -> 0 | AQ29: ='Report Consolidado Semanal'!AD90 -> 0 | AR29: ='Report Consolidado Semanal'!AE90 -> 0 | AS29: ='Report Consolidado Semanal'!AF90 -> 0
AJ31: Real acumulado dia | AN31: =SUMIF($AL$5:AL29,$AL$9,AN5:AN29) -> 40 | AO31: =SUMIF($AL$5:AM29,$AL$9,AO5:AO29) -> 26 | AP31: =SUMIF($AL$5:AL29,$AL$9,AP5:AP29) -> 0 | AQ31: =SUMIF($AL$5:AL29,$AL$9,AQ5:AQ29) -> 0 | AR31: =SUMIF($AL$5:AL29,$AL$9,AR5:AR29) -> 0 | AS31: =SUMIF($AL$5:AL29,$AL$9,AS5:AS29) -> 0
AJ32: Meta acumulado dia | AN32: =SUMIF($AL$5:AL30,$AL$5,AN5:AN30) -> 26 | AO32: =SUMIF($AL$5:AL30,$AL$5,AO5:AO30) -> 26 | AP32: =SUMIF($AL$5:AL29,$AL$5,AP5:AP30) -> 26 | AQ32: =SUMIF($AL$5:AL29,$AL$5,AQ5:AQ29) -> 26 | AR32: =SUMIF($AL$5:AL29,$AL$5,AR5:AR29) -> 26 | AS32: =SUMIF($AL$5:AL29,$AL$5,AS5:AS29) -> 26
AJ33: Aderência meta | AN33: =AN31/AN32 -> 1.5384615 | AO33: =AO31/AO32 -> 1 | AP33: =AP31/AP32 -> 0 | AQ33: =AQ31/AQ32 -> 0 | AR33: =AR31/AR32 -> 0 | AS33: =AS31/AS32 -> 0
P55: Terraplanagem - Corte + Aterro - (x1000.m³) | U55: ='Report Consolidado Semanal'!$Y$7 -> 46217
D56: =D24 -> Terraplanagem - Corte + Aterro - (x1000.m³) | F56: Quant. total | G56: Saldo | H56: Quant. Total % | I56: Saldo Total %
D59: PCTE 4/5 | F59: =SUM('Report Consolidado Semanal'!AT13:AT14,'Report Consolidado Semanal'!AT17:AT18,'Report Consolidado Semanal'!AT33:AT34,'Report Consolidado Semanal'!AT37:AT38) -> 9496785.4 | G59: =SUM('Report Consolidado Semanal'!AU13:AU14,'Report Consolidado Semanal'!AU17:AU18,'Report Consolidado Semanal'!AU33:AU34,'Report Consolidado Semanal'!AU37:AU38) -> 3574575.8 | H59: =(F59)/(F59+G59) -> 0.72653378 | I59: =(G59)/(F59+G59) -> 0.27346622
D61: PCTE 06 | F61: =SUM('Report Consolidado Semanal'!AT21:AT22) -> 6620711 | G61: =SUM('Report Consolidado Semanal'!AU21:AU22) -> 1473376.6 | H61: =(F61)/(F61+G61) -> 0.81796878 | I61: =(G61)/(F61+G61) -> 0.18203122
D63: PCTE 7/8 | F63: =SUM('Report Consolidado Semanal'!AT25:AT26) -> 2502064 | G63: =SUM('Report Consolidado Semanal'!AU25:AU26) -> 363883.14 | H63: =(F63)/(F63+G63) -> 0.87303215 | I63: =(G63)/(F63+G63) -> 0.12696785
P66: Drenagem Superficial (m) | T66: ='Report Consolidado Semanal'!$Y$7 -> 46217
D68: =T24 -> Drenagem Superficial (m) | F68: Quant. total | G68: Saldo | H68: Quant. Total % | I68: Saldo Total %
D71: Pacote 4/5 | F71: {=SUM('Report Consolidado Semanal'!AT53:AT54+'Report Consolidado Semanal'!AT57:AT58)} -> 201994.21 | G71: {=SUM('Report Consolidado Semanal'!AU53:AU54+'Report Consolidado Semanal'!AU57:AU58)} -> 180591.36 | H71: =(F71)/(F71+G71) -> 0.52797133 | I71: =(G71)/(F71+G71) -> 0.47202867
D73: Pacote 06 | F73: =SUM('Report Consolidado Semanal'!AT61:AT62) -> 127599 | G73: =SUM('Report Consolidado Semanal'!AU61:AU62) -> 69776.62 | H73: =(F73)/(F73+G73) -> 0.64647802 | I73: =(G73)/(F73+G73) -> 0.35352198
D75: Pacote 7/8 | F75: =SUM('Report Consolidado Semanal'!AT65:AT66) -> 98366.94 | G75: =SUM('Report Consolidado Semanal'!AU65:AU66) -> 38993.66 | H75: =(F75)/(F75+G75) -> 0.71612194 | I75: =(G75)/(F75+G75) -> 0.28387806
D83: =TEXT("Dias reais |","@") & " " & TEXT(Quadros!D6,"0") -> Dias reais | 12
B86: Produção total - Terraplangem (S-1 a S-4) | F86: =Quadros!H23 -> 06 a 12/07 | G86: =Quadros!H20 -> 29 a 05/07 | H86: =Quadros!H17 -> 22 a 28/06 | I86: =Quadros!H14 -> 15 a 21/06
F87: S-1 | G87: S-2 | H87: S-3 | I87: S-4
B89: Pacote 4/5 | D89: Previsto | F89: =Quadros!J23 -> 314155 | G89: =Quadros!J20 -> 273432 | H89: =Quadros!J17 -> 351609 | I89: =Quadros!J14 -> 264932
D90: Realizado | F90: =Quadros!J24 -> 298057.56 | G90: =Quadros!J21 -> 316315.8 | H90: =Quadros!J18 -> 358541.84 | I90: =Quadros!J15 -> 246473.84
B92: Pacote 06 | D92: Previsto | F92: =Quadros!K23 -> 288876.39 | G92: =Quadros!K20 -> 254894.08 | H92: =Quadros!K17 -> 304655.64 | I92: =Quadros!K14 -> 289786.47
D93: Realizado | F93: =Quadros!K24 -> 203067.09 | G93: =Quadros!K21 -> 203679.14 | H93: =Quadros!K18 -> 217779.78 | I93: =Quadros!K15 -> 209442.61
B95: Pacote 7/8 | D95: Previsto | F95: =Quadros!L23 -> 75931.156 | G95: =Quadros!L20 -> 96735.957 | H95: =Quadros!L17 -> 98406 | I95: =Quadros!L14 -> 76279.804
D96: Realizado | F96: =Quadros!L24 -> 92685.568 | G96: =Quadros!L21 -> 100493.51 | H96: =Quadros!L18 -> 110515.22 | I96: =Quadros!L15 -> 110095.34
B104: Produção total - Drenagem Superficial (S-1 a S-4) | F104: =F86 -> 06 a 12/07 | G104: =G86 -> 29 a 05/07 | H104: =H86 -> 22 a 28/06 | I104: =I86 -> 15 a 21/06
F105: S-1 | G105: S-2 | H105: S-3 | I105: S-4
B107: Pacote 4/5 | D107: Previsto | F107: =Quadros!U23 -> 5455 | G107: =Quadros!U20 -> 5400 | H107: =Quadros!U17 -> 5200 | I107: =Quadros!U14 -> 4824
D108: Realizado | F108: =Quadros!U24 -> 3800.2 | G108: =Quadros!U21 -> 2747 | H108: =Quadros!U18 -> 4007 | I108: =Quadros!U15 -> 3061
B110: Pacote 06 | D110: Previsto | F110: =Quadros!V23 -> 2300 | G110: =Quadros!V20 -> 2340 | H110: =Quadros!V17 -> 3380 | I110: =Quadros!V14 -> 3250
D111: Realizado | F111: =Quadros!V24 -> 1460 | G111: =Quadros!V21 -> 2009 | H111: =Quadros!V18 -> 2008 | I111: =Quadros!V15 -> 1784
B113: Pacote 7/8 | D113: Previsto | F113: =Quadros!W23 -> 3267.956 | G113: =Quadros!W20 -> 2785.979 | H113: =Quadros!W17 -> 2400 | I113: =Quadros!W14 -> 1170.17
D114: Realizado | F114: =Quadros!W24 -> 3783 | G114: =Quadros!W21 -> 2036 | H114: =Quadros!W18 -> 2381 | I114: =Quadros!W15 -> 1699
B137: Ponte sobre o Rio Araguaia | F137: =F86 -> 06 a 12/07 | G137: =G86 -> 29 a 05/07 | H137: =H86 -> 22 a 28/06 | I137: =I86 -> 15 a 21/06
F138: =F87 -> S-1 | G138: =G87 -> S-2 | H138: =H87 -> S-3 | I138: =I87 -> S-4
B140: Pilares | D140: Previsto | F140: ='Report Consolidado Semanal'!T73 -> 6 | G140: ='Report Consolidado Semanal'!P73 -> 7 | H140: ='Report Consolidado Semanal'!L73 -> 8 | I140: ='Report Consolidado Semanal'!H73 -> 8
D141: Realizado | F141: ='Report Consolidado Semanal'!T74 -> 7 | G141: ='Report Consolidado Semanal'!P74 -> 7 | H141: ='Report Consolidado Semanal'!L74 -> 7 | I141: ='Report Consolidado Semanal'!H74 -> 7
B143: Travessa | D143: Previsto | F143: ='Report Consolidado Semanal'!T77 -> 1.5 | G143: ='Report Consolidado Semanal'!P77 -> 1.5 | H143: ='Report Consolidado Semanal'!L77 -> 2 | I143: ='Report Consolidado Semanal'!H77 -> 1.5
D144: Realizado | F144: ='Report Consolidado Semanal'!T78 -> 2 | G144: ='Report Consolidado Semanal'!P78 -> 2 | H144: ='Report Consolidado Semanal'!L78 -> 1.5 | I144: ='Report Consolidado Semanal'!H78 -> 2.5
B146: Aduelas | D146: Previsto | F146: ='Report Consolidado Semanal'!T81 -> 4 | G146: ='Report Consolidado Semanal'!P81 -> 0 | H146: ='Report Consolidado Semanal'!L81 -> 0 | I146: ='Report Consolidado Semanal'!H81 -> 4
D147: Realizado | F147: ='Report Consolidado Semanal'!T82 -> 1 | G147: ='Report Consolidado Semanal'!P82 -> 1 | H147: ='Report Consolidado Semanal'!L82 -> 2.3333333 | I147: ='Report Consolidado Semanal'!H82 -> 2
B149: Vigas Pré Moldadas | D149: Previsto | F149: ='Report Consolidado Semanal'!T85 -> 1 | G149: ='Report Consolidado Semanal'!P85 -> 2 | H149: ='Report Consolidado Semanal'!L85 -> 2 | I149: ='Report Consolidado Semanal'!H85 -> 3
D150: Realizado | F150: ='Report Consolidado Semanal'!T86 -> 1 | G150: ='Report Consolidado Semanal'!P86 -> 2 | H150: ='Report Consolidado Semanal'!L86 -> 2 | I150: ='Report Consolidado Semanal'!H86 -> 2
B152: Pré moldados | D152: Previsto | F152: ='Report Consolidado Semanal'!T89 -> 189 | G152: ='Report Consolidado Semanal'!P89 -> 161 | H152: ='Report Consolidado Semanal'!L89 -> 189 | I152: ='Report Consolidado Semanal'!H89 -> 159
D153: Realizado | F153: ='Report Consolidado Semanal'!T90 -> 151 | G153: ='Report Consolidado Semanal'!P90 -> 136 | H153: ='Report Consolidado Semanal'!L90 -> 162 | I153: ='Report Consolidado Semanal'!H90 -> 175
D156: Aderência | F156: =(F153/F152) -> 0.7989418 | G156: =(G153/G152) -> 0.8447205 | H156: =(H153/H152) -> 0.85714286 | I156: =(I153/I152) -> 1.1006289
B166: Peso | D166: Atividade | F166: {='Report Consolidado Semanal'!AT6:AT7} -> QUANT. TOTAL | G166: Previsto | H166: Executado | I166: {='Report Consolidado Semanal'!AU6:AU7} -> SALDO | J166: %Previsto | K166: % Executado | L166: % Contribuição Prevista | N166: % Contribuição executada
F167: 0 | I167: 0
B168: 0.078533 | D168: Blocos | F168: 67 | G168: 67 | H168: 67 | I168: 67 | J168: =G168/F168 -> 1 | K168: =H168/F168 -> 1 | L168: =J168*B168 -> 0.078533 | N168: =K168*B168 -> 0.078533
B170: 0.115671 | D170: Pilares | F170: {='Report Consolidado Semanal'!AT73:AT74} -> 249 | G170: {='Report Consolidado Semanal'!AQ73:AQ74} -> 183 | H170: =F170-I170 -> 175 | I170: {='Report Consolidado Semanal'!AU73:AU74} -> 74 | J170: =G170/F170 -> 0.73493976 | K170: =H170/F170 -> 0.70281124 | L170: =J170*B170 -> 0.085011217 | N170: =K170*B170 -> 0.08129488
F171: 0 | G171: 0 | I171: 0
B172: 0.031426 | D172: Travessa | F172: {='Report Consolidado Semanal'!AT77:AT78} -> 63 | G172: {='Report Consolidado Semanal'!AQ77:AQ78} -> 38 | H172: =F172-I172 -> 20 | I172: {='Report Consolidado Semanal'!AU77:AU78} -> 43 | J172: =G172/F172 -> 0.6031746 | K172: =H172/F172 -> 0.31746032 | L172: =J172*B172 -> 0.018955365 | N172: =K172*B172 -> 0.0099765079
F173: 0 | G173: 0 | H173: =F173-I173 -> 0 | I173: 0
B174: 0.344021 | D174: Aduelas | F174: {='Report Consolidado Semanal'!AT81:AT82} -> 135 | G174: {='Report Consolidado Semanal'!AQ81:AQ82} -> 75 | H174: =F174-I174 -> 14 | I174: {='Report Consolidado Semanal'!AU81:AU82} -> 121 | J174: =G174/F174 -> 0.55555556 | K174: 0.2636 | L174: =J174*B174 -> 0.19112278 | N174: =K174*B174 -> 0.090683936
F175: 0 | G175: 0 | H175: =F175-I175 -> 0 | I175: 0
B176: 0.1358902 | D176: Vigas Pré-Moldadas | F176: {='Report Consolidado Semanal'!AT85:AT86} -> 66 | G176: {='Report Consolidado Semanal'!AQ85:AQ86} -> 46 | H176: =F176-I176 -> 44 | I176: {='Report Consolidado Semanal'!AU85:AU86} -> 22 | J176: =G176/F176 -> 0.6969697 | K176: =H176/F176 -> 0.66666667 | L176: =J176*B176 -> 0.094711352 | N176: =K176*B176 -> 0.090593467
F177: 0 | G177: 0 | H177: =F177-I177 -> 0 | I177: 0
B178: 0.081573 | D178: Pré-moldados | F178: {='Report Consolidado Semanal'!AT89:AT90} -> 5116 | G178: {='Report Consolidado Semanal'!AQ89:AQ90} -> 2760 | H178: =F178-I178 -> 1273 | I178: {='Report Consolidado Semanal'!AU89:AU90} -> 3843 | J178: =G178/F178 -> 0.53948397 | K178: 0.3323 | L178: =J178*B178 -> 0.044007326 | N178: =K178*B178 -> 0.027106708
F179: 0 | G179: 0 | I179: 0
B180: 0.002611 | D180: Encontros | F180: 8 | G180: 2 | H180: 2 | I180: =G180-H180 -> 0 | J180: =G180/F180 -> 0.25 | K180: =H180/F180 -> 0.25 | L180: =J180*B180 -> 0.00065275 | N180: =K180*B180 -> 0.00065275
B182: 0.011659 | D182: Instalação de Aparelho de Apoio | F182: 156 | G182: 0 | H182: 0 | I182: =G182-H182 -> 0 | J182: =G182/F182 -> 0 | K182: =H182/F182 -> 0 | L182: =J182*B182 -> 0 | N182: =K182*B182 -> 0
B184: 0.1094998 | D184: Execução de Vigas Longarinas | F184: 66 | G184: 0 | H184: 0 | I184: =G184-H184 -> 0 | J184: =G184/F184 -> 0 | K184: =H184/F184 -> 0 | L184: =J184*B184 -> 0 | N184: =K184*B184 -> 0
B186: 0.004277 | D186: Execução de Vigas Transversinas | F186: 68 | G186: 0 | H186: 0 | I186: =G186-H186 -> 0 | J186: =G186/F186 -> 0 | K186: =H186/F186 -> 0 | L186: =J186*B186 -> 0 | N186: =K186*B186 -> 0
B188: 0.048218 | D188: Lançamento de pré-moldados | F188: 5116 | G188: 0 | H188: 0 | I188: =G188-H188 -> 0 | J188: =G188/F188 -> 0 | K188: =H188/F188 -> 0 | L188: =J188*B188 -> 0 | N188: =K188*B188 -> 0
B190: 0.006767 | D190: Lajes in-loco | F190: 68 | G190: 0 | H190: 0 | I190: =G190-H190 -> 0 | J190: =G190/F190 -> 0 | K190: =H190/F190 -> 0 | L190: =J190*B190 -> 0 | N190: =K190*B190 -> 0
B192: 0.029854 | D192: Instalação de Guarda-Corpo | F192: 36 | G192: 0 | H192: 0 | I192: =G192-H192 -> 0 | J192: =G192/F192 -> 0 | K192: =H192/F192 -> 0 | L192: =J192*B192 -> 0 | N192: =K192*B192 -> 0
B194: =SUM(B168:B192) -> 1 | D194: TOTAL | F194: =SUM(F168:F192) -> 11214 | G194: =SUM(G168:G192) -> 3171 | H194: =SUM(H168:H192) -> 1595 | I194: =SUM(I168:I192) -> 4170 | J194: =G194/F194 -> 0.28277154 | K194: =H194/F194 -> 0.14223292 | L194: =SUM(L168:L192) -> 0.51299379 | N194: =SUM(N168:N192) -> 0.37884125

Sheet Quadros
A1: 46234
A2: {=DAY(EOMONTH(A1,0))-SUMPRODUCT(--(WEEKDAY(DATE(YEAR(A1),MONTH(A1),ROW(INDIRECT("1:"&DAY(EOMONTH(A1,0))))),1)=1))} -> 27
F3: Historico das Últimas semanas de Produção | Q3: Historico das Últimas semanas de Produção | AA3: Historico das Últimas semanas de Produção | AK3: Historico das Últimas semanas de Produção
C4: Dias mês | D4: =A2 -> 27 | F4: Terraplanagem (C+A) Média m³/d | H4: Dias | J4: PCTE 4/5 | K4: PCTE 06 | L4: PCTE 7/8 | N4: REG 02 | Q4: Drenag Superficial Média m/d | S4: Dias | U4: PCTE 4/5 | V4: PCTE 06 | W4: PCTE 7/8 | Y4: REG 02 | AA4: Ponte do Araguaia Média m/d | AC4: Dias | AE4: Pilares | AF4: Travessas | AG4: Aduelas | AH4: Vigas Pré Moldadas | AI4: Pré moldados | AK4: DSH / DHP Média m/d | AM4: Dias | AO4: PCTE 4/5 | AP4: PCTE 06 | AQ4: PCTE 7/8 | AS4: REG 02
C6: Dias reais | D6: =ROUND(DAY('Report Consolidado Semanal'!D4)*(6/7),0) -> 12 | F6: Média PLANEJADA MÊS | H6: =Quadros!$D$4 -> 27 | J6: =SUM('Report Consolidado Semanal'!AW13:AW18)+SUM('Report Consolidado Semanal'!AW33:AW38) -> 59916.438 | K6: =SUM('Report Consolidado Semanal'!AW21+'Report Consolidado Semanal'!AW41) -> 39091.084 | L6: ='Report Consolidado Semanal'!AW25+'Report Consolidado Semanal'!AW45 -> 14069.66 | N6: =SUM(J6:M6) -> 113077.18 | Q6: Média Planejada MÊS | S6: =Quadros!$D$4 -> 27 | U6: =SUM('Report Consolidado Semanal'!AW53:AW58) -> 928.8837 | V6: ='Report Consolidado Semanal'!AW61 -> 511.09111 | W6: ='Report Consolidado Semanal'!AW65 -> 500.81343 | Y6: =SUM(U6:X6) -> 1940.7882 | AA6: Média Planejada MÊS | AC6: =Quadros!$D$4 -> 27 | AE6: =SUM('Report Consolidado Semanal'!AW73:AW74) -> 2 | AF6: =SUM('Report Consolidado Semanal'!AW77:AW78) -> 1 | AG6: =SUM('Report Consolidado Semanal'!AW81:AW82) -> 1 | AH6: =SUM('Report Consolidado Semanal'!AW85:AW86) -> 1 | AI6: =SUM('Report Consolidado Semanal'!AW89:AW90) -> 21 | AK6: Média Planejada MÊS | AM6: =Quadros!$D$4 -> 27
C8: Semana | D8: =COUNTIF('Report Consolidado Semanal'!AA10:AF10,">"&0) -> 2 | F8: Média ACUMUL MÊS | H8: =$D$6 -> 12 | J8: =SUM('Report Consolidado Semanal'!AX13:AX18)+SUM('Report Consolidado Semanal'!AX33:AX38) -> 52407.643 | K8: ='Report Consolidado Semanal'!AX21+'Report Consolidado Semanal'!AX41 -> 33310.091 | L8: ='Report Consolidado Semanal'!AX25+'Report Consolidado Semanal'!AX45 -> 18433.823 | N8: =SUM(J8:M8) -> 104151.56 | Q8: Média Acumulada MÊS | S8: =$D$6 -> 12 | U8: =SUM('Report Consolidado Semanal'!AX53:AX58) -> 610.26667 | V8: ='Report Consolidado Semanal'!AX61 -> 242.91667 | W8: ='Report Consolidado Semanal'!AX65 -> 597.75 | Y8: =SUM(U8:X8) -> 1450.9333 | AA8: Média Acumulada MÊS | AC8: =$D$6 -> 12 | AE8: =SUM('Report Consolidado Semanal'!AX73:AX74) -> 1 | AF8: =SUM('Report Consolidado Semanal'!AX77:AX78) -> 1 | AG8: =SUM('Report Consolidado Semanal'!AX81:AX82) -> 1 | AH8: =SUM('Report Consolidado Semanal'!AX85:AX86) -> 1 | AI8: =SUM('Report Consolidado Semanal'!AX89:AX90) -> 11 | AK8: Média Acumulada MÊS | AM8: =$D$6 -> 12
F10: Média ACUMUL SEMANA | H10: =$D$8 -> 2 | J10: =('Report Consolidado Semanal'!AH14+'Report Consolidado Semanal'!AH18+'Report Consolidado Semanal'!AH34+'Report Consolidado Semanal'!AH38)/Quadros!$D$8 -> 56572.44 | K10: =('Report Consolidado Semanal'!AH22+'Report Consolidado Semanal'!AH42)/Quadros!$D$8 -> 36067.655 | L10: =('Report Consolidado Semanal'!AH26+'Report Consolidado Semanal'!AH46)/Quadros!$D$8 -> 14686.231 | N10: =SUM(J10:M10) -> 107326.33 | Q10: Média Acumulada SEMANA | S10: =$D$8 -> 2 | U10: =('Report Consolidado Semanal'!AH54+'Report Consolidado Semanal'!AH58)/Quadros!$D$8 -> 735.75 | V10: ='Report Consolidado Semanal'!AH62/Quadros!$D$8 -> 238 | W10: ='Report Consolidado Semanal'!AH66/Quadros!$D$8 -> 677 | Y10: =SUM(U10:X10) -> 1650.75 | AA10: Média Acumulada SEMANA | AC10: =$D$8 -> 2 | AE10: =ROUNDUP(SUM('Report Consolidado Semanal'!AH74/$D$8),0) -> 0 | AF10: =ROUNDUP(SUM('Report Consolidado Semanal'!AH78/$D$8),0) -> 0 | AG10: =SUM('Report Consolidado Semanal'!AY81:AY82) -> 1 | AH10: =SUM('Report Consolidado Semanal'!AY85:AY86) -> 1 | AI10: =SUM('Report Consolidado Semanal'!AY89:AY90) -> 14 | AK10: Média Acumulada SEMANA | AM10: =$D$8 -> 2
F12: Historico das Últimas semanas de Produção | Q12: Historico das Últimas semanas de Produção
F14: Produção total S-4 | H14: =RIGHT('Report Consolidado Semanal'!G4,10) -> 15 a 21/06 | J14: =SUM('Report Consolidado Semanal'!H13,'Report Consolidado Semanal'!H17,'Report Consolidado Semanal'!H33,'Report Consolidado Semanal'!H37) -> 264932 | K14: =SUM('Report Consolidado Semanal'!H21,'Report Consolidado Semanal'!H41) -> 289786.47 | L14: =SUM('Report Consolidado Semanal'!H25,'Report Consolidado Semanal'!H45) -> 76279.804 | N14: =SUM(J14:M14) -> 630998.27 | Q14: Produção total S-4 | S14: =H14 -> 15 a 21/06 | U14: =SUM('Report Consolidado Semanal'!H53,'Report Consolidado Semanal'!H57) -> 4824 | V14: ='Report Consolidado Semanal'!H61 -> 3250 | W14: =SUM('Report Consolidado Semanal'!H65) -> 1170.17 | Y14: =SUM('Report Consolidado Semanal'!J65) -> 0
J15: =SUM('Report Consolidado Semanal'!H14,'Report Consolidado Semanal'!H18,'Report Consolidado Semanal'!H34,'Report Consolidado Semanal'!H38) -> 246473.84 | K15: =SUM('Report Consolidado Semanal'!H22,'Report Consolidado Semanal'!H42) -> 209442.61 | L15: =SUM('Report Consolidado Semanal'!H26,'Report Consolidado Semanal'!H46) -> 110095.34 | N15: =SUM(J15:M15) -> 566011.79 | U15: =SUM('Report Consolidado Semanal'!H54,'Report Consolidado Semanal'!H58) -> 3061 | V15: ='Report Consolidado Semanal'!H62 -> 1784 | W15: =SUM('Report Consolidado Semanal'!H66) -> 1699 | Y15: =SUM(U15:W15) -> 6544
F17: Produção total S-3 | H17: =RIGHT('Report Consolidado Semanal'!K4,10) -> 22 a 28/06 | J17: =SUM('Report Consolidado Semanal'!L13,'Report Consolidado Semanal'!L17,'Report Consolidado Semanal'!L33,'Report Consolidado Semanal'!L37) -> 351609 | K17: =SUM('Report Consolidado Semanal'!L21,'Report Consolidado Semanal'!L41) -> 304655.64 | L17: =SUM('Report Consolidado Semanal'!L25,'Report Consolidado Semanal'!L45) -> 98406 | N17: =SUM(J17:M17) -> 754670.64 | Q17: Produção total S-3 | S17: =H17 -> 22 a 28/06 | U17: =SUM('Report Consolidado Semanal'!L53,'Report Consolidado Semanal'!L57) -> 5200 | V17: ='Report Consolidado Semanal'!L61 -> 3380 | W17: =SUM('Report Consolidado Semanal'!L65) -> 2400 | Y17: =SUM('Report Consolidado Semanal'!N65) -> 0
J18: =SUM('Report Consolidado Semanal'!L14,'Report Consolidado Semanal'!L18,'Report Consolidado Semanal'!L34,'Report Consolidado Semanal'!L38) -> 358541.84 | K18: =SUM('Report Consolidado Semanal'!L22,'Report Consolidado Semanal'!L42) -> 217779.78 | L18: =SUM('Report Consolidado Semanal'!L26,'Report Consolidado Semanal'!L46) -> 110515.22 | N18: =SUM(J18:M18) -> 686836.84 | U18: =SUM('Report Consolidado Semanal'!L54,'Report Consolidado Semanal'!L58) -> 4007 | V18: ='Report Consolidado Semanal'!L62 -> 2008 | W18: =SUM('Report Consolidado Semanal'!L66) -> 2381 | Y18: =SUM(U18:W18) -> 8396
F20: Produção total S-2 | H20: =RIGHT('Report Consolidado Semanal'!O4,10) -> 29 a 05/07 | J20: =SUM('Report Consolidado Semanal'!P13,'Report Consolidado Semanal'!P17,'Report Consolidado Semanal'!P33,'Report Consolidado Semanal'!P37) -> 273432 | K20: =SUM('Report Consolidado Semanal'!P21,'Report Consolidado Semanal'!P41) -> 254894.08 | L20: =SUM('Report Consolidado Semanal'!P25,'Report Consolidado Semanal'!P45) -> 96735.957 | N20: =SUM(J20:M20) -> 625062.03 | Q20: Produção total S-2 | S20: =H20 -> 29 a 05/07 | U20: =SUM('Report Consolidado Semanal'!P53,'Report Consolidado Semanal'!P57) -> 5400 | V20: ='Report Consolidado Semanal'!P61 -> 2340 | W20: =SUM('Report Consolidado Semanal'!P65) -> 2785.979 | Y20: =SUM('Report Consolidado Semanal'!R65) -> 0
J21: =SUM('Report Consolidado Semanal'!P14,'Report Consolidado Semanal'!P18,'Report Consolidado Semanal'!P34,'Report Consolidado Semanal'!P38) -> 316315.8 | K21: =SUM('Report Consolidado Semanal'!P22,'Report Consolidado Semanal'!P42) -> 203679.14 | L21: =SUM('Report Consolidado Semanal'!P26,'Report Consolidado Semanal'!P46) -> 100493.51 | N21: =SUM(J21:M21) -> 620488.44 | U21: =SUM('Report Consolidado Semanal'!P54,'Report Consolidado Semanal'!P58) -> 2747 | V21: ='Report Consolidado Semanal'!P62 -> 2009 | W21: =SUM('Report Consolidado Semanal'!P66) -> 2036 | Y21: =SUM(U21:W21) -> 6792
F23: Produção total S-1 | H23: =RIGHT('Report Consolidado Semanal'!$S$4,10) -> 06 a 12/07 | J23: =SUM('Report Consolidado Semanal'!T13,'Report Consolidado Semanal'!T17,'Report Consolidado Semanal'!T33,'Report Consolidado Semanal'!T37) -> 314155 | K23: =SUM('Report Consolidado Semanal'!T21,'Report Consolidado Semanal'!T41) -> 288876.39 | L23: =SUM('Report Consolidado Semanal'!T25,'Report Consolidado Semanal'!T45) -> 75931.156 | N23: =SUM(J23:M23) -> 678962.55 | Q23: Produção total S-1 | S23: =H23 -> 06 a 12/07 | U23: =SUM('Report Consolidado Semanal'!T53,'Report Consolidado Semanal'!T57) -> 5455 | V23: ='Report Consolidado Semanal'!T61 -> 2300 | W23: =SUM('Report Consolidado Semanal'!T65) -> 3267.956 | Y23: =SUM('Report Consolidado Semanal'!V65) -> 0
J24: =SUM('Report Consolidado Semanal'!T14,'Report Consolidado Semanal'!T18,'Report Consolidado Semanal'!T34,'Report Consolidado Semanal'!T38) -> 298057.56 | K24: =SUM('Report Consolidado Semanal'!T22,'Report Consolidado Semanal'!T42) -> 203067.09 | L24: =SUM('Report Consolidado Semanal'!T26,'Report Consolidado Semanal'!T46) -> 92685.568 | N24: =SUM(J24:M24) -> 593810.22 | U24: =SUM('Report Consolidado Semanal'!T54,'Report Consolidado Semanal'!T58) -> 3800.2 | V24: ='Report Consolidado Semanal'!T62 -> 1460 | W24: =SUM('Report Consolidado Semanal'!T66) -> 3783 | Y24: =SUM(U24:W24) -> 9043.2
C26: dias mês | D26: =30-4 -> 26 | F26: Terraplanagem (C+A) Média m³/d | H26: Dias | J26: PCTE 4/5 | K26: PCTE 06 | L26: PCTE 7/8 | N26: REG 02 | Q26: Drenag Superficial Média m/d | S26: Dias | U26: PCTE 4/5 | V26: PCTE 06 | W26: PCTE 7/8 | Y26: REG 02
F28: Produtiv. Escavação m³/escavad/dia | H28: =D6 -> 12 | J28: =('Report Consolidado Semanal'!AM13+'Report Consolidado Semanal'!AM17)/J29/Quadros!$D$6 -> 565.98765 | K28: ='Report Consolidado Semanal'!AM21/K29/Quadros!$D$6 -> 900.31746 | L28: ='Report Consolidado Semanal'!AM25/L29/Quadros!$D$6 -> 579.68778 | N28: =SUM(J28:M28) -> 2045.9929 | Q28: Produtuv Drenagem m/homem/dia | S28: =H28 -> 12 | U28: =U31/U29/Quadros!$D$6 -> 2.9481481 | V28: =V31/V29/Quadros!$D$6 -> 4.6714744 | W28: =('Report Consolidado Semanal'!AM65)/W29/Quadros!$D$6 -> 11.955 | Y28: =SUM(U28:W28) -> 19.574623
F29: Quant. Escavadeiras: | J29: 54 | K29: 21 | L29: 18 | N29: =SUM(J29:L29) -> 93 | Q29: Efetivo mobilizado para drenagem | U29: 207 | V29: 52 | W29: 50 | Y29: =SUM(U29:W29) -> 309
F31: Produtiv. Aterro m³/rolo/dia | H31: =H28 -> 12 | J31: =('Report Consolidado Semanal'!AM33+'Report Consolidado Semanal'!AM37)/J32/Quadros!$D$6 -> 364.07183 | K31: ='Report Consolidado Semanal'!AM41/K32/Quadros!$D$6 -> 1028.8161 | L31: ='Report Consolidado Semanal'!AM45/L32/Quadros!$D$6 -> 499.96519 | N31: =SUM(J31:M31) -> 1892.8531 | Q31: Produção mês | U31: ='Report Consolidado Semanal'!AM53+'Report Consolidado Semanal'!AM57 -> 7323.2 | V31: ='Report Consolidado Semanal'!AM61 -> 2915 | W31: ='Report Consolidado Semanal'!AM65 -> 7173 | Y31: =SUM(U31:W31) -> 17411.2
F32: Quant. Rolo Compactadores: | J32: 60 | K32: 14 | L32: 16 | N32: =SUM(J32:M32) -> 90
F34: Avanço de Produção Terraplanagem | H34: Dias | J34: PCTE 4/5 | K34: PCTE 06 | L34: PCTE 7/8 | N34: REG 02 | Q34: Avanço de Produção Drenagem Superficilal | S34: Dias | U34: PCTE 4/5 | V34: PCTE 06 | W34: PCTE 7/8 | Y34: REG 02 | AA34: Avanço de Produção Ponte do Araguaia | AC34: Dias | AE34: Pilares | AF34: Travessas | AG34: Aduelas | AH34: Vigas Pré Moldadas | AI34: Pré moldados
F36: Meta mês | H36: =H6 -> 27 | J36: =SUM('Report Consolidado Semanal'!AK13:AK14,'Report Consolidado Semanal'!AK17:AK18,'Report Consolidado Semanal'!AK33:AK34,'Report Consolidado Semanal'!AK37:AK38) -> 1617743.8 | K36: =SUM('Report Consolidado Semanal'!AK21:AK22,'Report Consolidado Semanal'!AK41:AK42) -> 1055459.3 | L36: =SUM('Report Consolidado Semanal'!AK25:AK26,'Report Consolidado Semanal'!AK45:AK46) -> 379880.82 | N36: =SUM(J36:M36) -> 3053083.9 | Q36: Meta mês | S36: =H36 -> 27 | U36: =SUM('Report Consolidado Semanal'!AK53:AK58) -> 25079.86 | V36: =SUM('Report Consolidado Semanal'!AK61:AK62) -> 13799.46 | W36: =SUM('Report Consolidado Semanal'!AK65:AK66) -> 13521.962 | Y36: =SUM(U36:X36) -> 52401.283 | AA36: Meta mês | AC36: =Quadros!$D$4 -> 27 | AE36: =SUM('Report Consolidado Semanal'!AK73:AK74) -> 50 | AF36: =SUM('Report Consolidado Semanal'!AK77:AK78) -> 8 | AG36: =SUM('Report Consolidado Semanal'!AK81:AK82) -> 15 | AH36: =SUM('Report Consolidado Semanal'!AK85:AK86) -> 8 | AI36: =SUM('Report Consolidado Semanal'!AK89:AK90) -> 552
F38: Acumulado | H38: =H8 -> 12 | J38: =SUM('Report Consolidado Semanal'!AM13:AM14,'Report Consolidado Semanal'!AM17:AM18,'Report Consolidado Semanal'!AM33:AM34,'Report Consolidado Semanal'!AM37:AM38) -> 628891.72 | K38: =SUM('Report Consolidado Semanal'!AM41:AM42,'Report Consolidado Semanal'!AM21:AM22) -> 399721.1 | L38: =SUM('Report Consolidado Semanal'!AM25:AM26,'Report Consolidado Semanal'!AM45:AM46) -> 221205.88 | N38: =SUM(J38:M38) -> 1249818.7 | Q38: Acumulado | S38: =H38 -> 12 | U38: =SUM('Report Consolidado Semanal'!AM53:AM58) -> 7323.2 | V38: =SUM('Report Consolidado Semanal'!AM61:AM62) -> 2915 | W38: =SUM('Report Consolidado Semanal'!AM65:AM66) -> 7173 | Y38: =SUM(U38:X38) -> 17411.2 | AA38: Acumulado | AC38: =$D$6 -> 12 | AE38: =SUM('Report Consolidado Semanal'!AM73:AM74) -> 13 | AF38: =SUM('Report Consolidado Semanal'!AM77:AM78) -> 4 | AG38: =SUM('Report Consolidado Semanal'!AM81:AM82) -> 5 | AH38: =SUM('Report Consolidado Semanal'!AM85:AM86) -> 2 | AI38: =SUM('Report Consolidado Semanal'!AM89:AM90) -> 344
F40: Avanço | H40: =H38/H36 -> 0.44444444 | J40: =J38/J36 -> 0.38874617 | K40: =K38/K36 -> 0.37871769 | L40: =L38/L36 -> 0.58230335 | N40: =N38/N36 -> 0.40936271 | Q40: Avanço | S40: =S38/S36 -> 0.44444444 | U40: =U38/U36 -> 0.29199525 | V40: =V38/V36 -> 0.21124015 | W40: =W38/W36 -> 0.53047034 | Y40: =Y38/Y36 -> 0.33226668 | AA40: Avanço | AC40: =AC38/AC36 -> 0.44444444 | AE40: =AE38/AE36 -> 0.26 | AF40: =AF38/AF36 -> 0.5 | AG40: =AG38/AG36 -> 0.33333333 | AH40: =AH38/AH36 -> 0.25 | AI40: =AI38/AI36 -> 0.62318841

Sheet Report Pacote 0405
I1: 46209 | AC1: 46204 | AH1: 46187
I2: 46215 | AC2: =N8 -> 46217 | AF2: 46112 | AH2: 46203
S3: REPORT DIÁRIO
R4: =282+452 -> 734 | AV4: Aterro e compactação
E5: PACOTES 04 E 05 | I5: SEMANA | J5: 27 | M5: SEMANA | N5: 28 | P5: ACOMPANHAMENTO SEMANAL | AA5: ACOMPANHAMENTO MENSAL (Cronograma Corrente*) | AF5: ACUMULADO | AO5: ESCOPO | AV5: Drenagem Superficial
F6: 132 | J6: 132 | N6: , | AA6: 46081 | AB6: 46081
E7: ATIVIDADE | F7: UM | H7: PRODUÇÃO S-1 | J7: ADERÊNCIA S-1 | L7: PRODUÇÃO DO DIA | N7: =TEXT(N8,"dDD") -> ter | P7: =TEXT(P8,"dDD") -> seg | Q7: =TEXT(Q8,"dDD") -> ter | R7: =TEXT(R8,"dDD") -> qua | S7: =TEXT(S8,"dDD") -> qui | T7: =TEXT(T8,"dDD") -> sex | U7: =TEXT(U8,"dDD") -> sáb | V7: =TEXT(V8,"dDD") -> dom | X7: ="TOTAL SEMANA (até "&TEXT(N8,"DD/MM")&")" -> TOTAL SEMANA (até 14/07) | Y7: ADERÊNCIA | AA7: META MÊS | AB7: ="PLANEJADO ATÉ A DATA " & TEXT(AC2,"DD/MM") -> PLANEJADO ATÉ A DATA 14/07 | AC7: ="REAL MÊS ("&TEXT(AC1,"DD/MM")&" até "&TEXT(AC2,"DD/MM")&")" -> REAL MÊS (01/07 até 14/07) | AD7: ADERÊNCIA | AF7: PROD. ACUM. BM 12 MARÇO | AG7: BM 13 ABRIL (11/04) | AH7: ="PROD. "&TEXT(AH1,"DD/MM")&" a "&TEXT(AH2,"DD/MM") -> PROD. 14/06 a 30/06 | AI7: BM 14 MAIO (11/05) | AJ7: BM 15 JUNHO (13/06 | AK7: REAL ACUMULADO | AL7: PREVISTO ACUMUL. BL01 | AM7: ADERÊNCIA | AO7: QUANT. TOTAL | AP7: SALDO | AV7: Escavação 3ª categor
A8: Exibir S/N | B8: ID exclusiva | C8: ID CRON. | D8: COD. ATIVO - PROD | N8: =Q8 -> 46217 | P8: 46216 | Q8: =P8+1 -> 46217 | R8: =Q8+1 -> 46218 | S8: =R8+1 -> 46219 | T8: =S8+1 -> 46220 | U8: =T8+1 -> 46221 | V8: =U8+1 -> 46222
AV9: =IF(AX9="Y",LEFT(E9,20),IF(AX9="x",E9,AV8)) -> 0 | AW9: =IF(E9<>"",E9,AW8) -> 0
A10: 0 | E10: Escavação 1ª e 2ª categoria | F10: m³ | H10: P | I10: =I14+I102+I176+I232+I310 -> 181120 | J10: =IFERROR((I11/I10),"-") -> 0.97232774 | L10: P | M10: =M14+M102+M176+M232+M310 -> 33880 | N10: =IFERROR((M11/M10),"-") -> 0.93772137 | P10: =P14+P102+P176+P232+P310 -> 33880 | Q10: =Q14+Q102+Q176+Q232+Q310 -> 33880 | R10: =R14+R102+R176+R232+R310 -> 33880 | S10: =S14+S102+S176+S232+S310 -> 33810 | T10: =T14+T102+T176+T232+T310 -> 30040 | U10: =U14+U102+U176+U232+U310 -> 30040 | V10: =V14+V102+V176+V232+V310 -> 0 | X10: =SUMIFS(P10:V10,$P$8:$V$8,">="&$P$8,$P$8:$V$8,"<="&$N$8) -> 67760 | Y10: =IFERROR((X11/X10),"-") -> 0.95764463 | AA10: =AA14+AA102+AA176+AA232+AA310 -> 945763.13 | AB10: =AB14+AB102+AB176+AB232+AB310 -> 534971.68 | AC10: =AC14+AC102+AC176+AC232+AC310 -> 366760 | AD10: =IFERROR((AC10/AB10),"-") -> 0.685569 | AF10: 3339564 | AG10: =AG14+AG102+AG176+AG232+AG310 -> 114046.33 | AH10: =AH14+AH102+AH176+AH232+AH310 -> 373170 | AI10: =AI14+AI102+AI176+AI232+AI310 -> 235766.45 | AJ10: =AJ14+AJ102+AJ176+AJ232+AJ310 -> 486855.91 | AK10: =AK14+AK102+AK176+AK232+AK310 -> 4852235.4 | AL10: =AL14+AL102+AL176+AL232+AL310 -> 5127980.5 | AM10: =IFERROR((AK10/AL10),"-") -> 0.94622734 | AO10: =AO14+AO102+AO176+AO232+AO310 -> 7062974.4 | AP10: =AP14+AP102+AP176+AP232+AP310 -> 2210739 | AV10: =IF(AX10="Y",LEFT(E10,20),IF(AX10="x",E10,AV9)) -> Escavação 1ª e 2ª categoria | AW10: =IF(E10<>"",E10,AW9) -> Escavação 1ª e 2ª categoria | AX10: x
A11: 0 | H11: R | I11: =I15+I103+I177+I233+I311 -> 176108 | L11: R | M11: =M15+M103+M177+M233+M311 -> 31770 | P11: =P15+P103+P177+P233+P311 -> 33120 | Q11: =Q15+Q103+Q177+Q233+Q311 -> 31770 | R11: =R15+R103+R177+R233+R311 -> 0 | S11: =S15+S103+S177+S233+S311 -> 0 | T11: =T15+T103+T177+T233+T311 -> 0 | U11: =U15+U103+U177+U233+U311 -> 0 | V11: =V15+V103+V177+V233+V311 -> 0 | X11: =SUMIFS(P11:V11,$P$8:$V$8,">="&$P$8,$P$8:$V$8,"<="&$N$8) -> 64890 | AV11: =IF(AX11="Y",LEFT(E11,20),IF(AX11="x",E11,AV10)) -> Escavação 1ª e 2ª categoria | AW11: =IF(E11<>"",E11,AW10) -> Escavação 1ª e 2ª categoria
A12: 0 | AV12: =IF(AX12="Y",LEFT(E12,20),IF(AX12="x",E12,AV11)) -> Escavação 1ª e 2ª categoria | AW12: =IF(E12<>"",E12,AW11) -> Escavação 1ª e 2ª categoria
A13: 0 | AV13: =IF(AX13="Y",LEFT(E13,20),IF(AX13="x",E13,AV12)) -> Escavação 1ª e 2ª categoria | AW13: =IF(E13<>"",E13,AW12) -> Escavação 1ª e 2ª categoria
A14: 0 | E14: Pacote 04 - Segmento 2.2B- Km 104+500 a Km 116+400 | F14: m³ | H14: P | I14: =SUMIF($L18:$L93,$L14,I18:I93) -> 15200 | J14: =IFERROR((I15/I14),"-") -> 0.38618421 | L14: P | M14: =SUMIF($L18:$L99,$L14,M18:M99) -> 1400 | N14: =IFERROR((M15/M14),"-") -> 1.0428571 | P14: =SUMIF($L18:$L99,$L14,P16:P99) -> 1400 | Q14: =SUMIF($L18:$L99,$L14,Q18:Q99) -> 1400 | R14: =SUMIF($L18:$L99,$L14,R18:R99) -> 1400 | S14: =SUMIF($L18:$L99,$L14,S18:S99) -> 630 | T14: =SUMIF($L18:$L99,$L14,T18:T99) -> 540 | U14: =SUMIF($L18:$L99,$L14,U18:U99) -> 540 | V14: =SUMIF($L18:$L99,$L14,V18:V99) -> 0 | X14: =SUMIF($L18:$L99,$L14,X18:X99) -> 2800 | Y14: =IFERROR((X15/X14),"-") -> 0.70714286 | AA14: =SUM(AA16:AA99) -> 154237.84 | AB14: =SUM(AB16:AB99) -> 145279.6 | AC14: =SUM(AC16:AC99) -> 15130 | AD14: =IFERROR((AC14/AB14),"-") -> 0.10414401 | AF14: =SUM(AF16:AF99) -> 541447.25 | AG14: =SUM(AG16:AG99) -> 16875.654 | AH14: =SUM(AH16:AH99) -> 23400 | AI14: =SUM(AI16:AI99) -> 45100.632 | AJ14: =SUM(AJ16:AJ99) -> 18521.959 | AK14: =SUM(AK16:AK99) -> 660475.49 | AL14: =SUM(AL16:AL99) -> 600955.05 | AM14: =IFERROR((AK14/AL14),"-") -> 1.0990431 | AO14: =SUM(AO16:AO99) -> 787353.2 | AP14: =SUM(AP16:AP99) -> 126877.71 | AV14: =IF(AX14="Y",LEFT(E14,20),IF(AX14="x",E14,AV13)) -> Escavação 1ª e 2ª categoria | AW14: =IF(E14<>"",E14,AW13) -> Pacote 04 - Segmento 2.2B- Km 104+500 a Km 116+400
A15: 0 | H15: R | I15: =SUMIF($L18:$L93,$L15,I18:I93) -> 5870 | L15: R | M15: =SUMIF($L18:$L99,$L15,M18:M99) -> 1460 | P15: =SUMIF($L18:$L99,$L15,P18:P99) -> 520 | Q15: =SUMIF($L18:$L99,$L15,Q18:Q99) -> 1460 | R15: =SUMIF($L18:$L99,$L15,R18:R99) -> 0 | S15: =SUMIF($L18:$L99,$L15,S18:S99) -> 0 | T15: =SUMIF($L18:$L99,$L15,T18:T99) -> 0 | U15: =SUMIF($L18:$L99,$L15,U18:U99) -> 0 | V15: =SUMIF($L18:$L99,$L15,V18:V99) -> 0 | X15: =SUMIF($L18:$L99,$L15,X18:X99) -> 1980 | AV15: =IF(AX15="Y",LEFT(E15,20),IF(AX15="x",E15,AV14)) -> Escavação 1ª e 2ª categoria | AW15: =IF(E15<>"",E15,AW14) -> Pacote 04 - Segmento 2.2B- Km 104+500 a Km 116+400
A16: =IF(SUM(P16:V17)>0,"S","N") -> N | B16: 1057291 | C16: 2.1.4.1.1.6.1 | D16: 2.2-C06 | E16: Seg. 2.2-C06 - Acabamentos em talude do Corte | F16: m³ | H16: P | I16: 0 | J16: =IFERROR((I17/I16),"-") -> - | L16: P | M16: =_xlfn.XLOOKUP($N$8,$P$8:$V$8,$P16:$V16) -> 0 | N16: =IFERROR((M17/M16),"-") -> - | P16: 0 | Q16: 0 | R16: 0 | S16: 0 | T16: 0 | U16: 0 | V16: 0 | X16: =SUMIFS(P16:V16,$P$8:$V$8,">="&$N$8,$P$8:$V$8,"<="&$N$8) -> 0 | Y16: =IFERROR((X17/X16),"-") -> - | AA16: 0 | AB16: 0 | AC16: 0 | AD16: =IFERROR((AC16/AB16),"-") -> - | AF16: 3744.925 | AG16: 0 | AH16: 0 | AK16: =AF16+AG16+AH16+AI16+AJ16+AC16 -> 3744.925 | AL16: 273.78 | AM16: =IFERROR((AK16/AL16),"-") -> 13.678592 | AO16: 273.78 | AP16: =AO16-AK16 -> -3471.145 | AV16: =IF(AX16="Y",LEFT(E16,20),IF(AX16="x",E16,AV15)) -> Escavação 1ª e 2ª categoria | AW16: =IF(E16<>"",E16,AW15) -> Seg. 2.2-C06 - Acabamentos em talude do Corte
A17: =A16 -> N | D17: 2.2-C06 | H17: R | I17: 0 | L17: R | M17: =_xlfn.XLOOKUP($N$8,$P$8:$V$8,$P17:$V17) -> 0 | P17: 0 | Q17: 0 | R17: 0 | S17: 0 | T17: 0 | U17: 0 | V17: 0 | X17: =SUMIFS(P17:V17,$P$8:$V$8,">="&$P$8,$P$8:$V$8,"<="&$N$8) -> 0 | AV17: =IF(AX17="Y",LEFT(E17,20),IF(AX17="x",E17,AV16)) -> Escavação 1ª e 2ª categoria | AW17: =IF(E17<>"",E17,AW16) -> Seg. 2.2-C06 - Acabamentos em talude do Corte
A18: =IF(SUM(P18:V19)>0,"S","N") -> N | B18: 1059583 | C18: 2.1.4.1.1.2.1 | D18: 2.2-C02 | E18: Seg. 2.2-C02 - Escavação, carga e transporte de material 1ª/2ª categoria | F18: m³ | H18: P | I18: 0 | J18: =IFERROR((I19/I18),"-") -> - | L18: P | M18: =_xlfn.XLOOKUP($N$8,$P$8:$V$8,$P18:$V18) -> 0 | N18: =IFERROR((M19/M18),"-") -> - | P18: 0 | Q18: 0 | R18: 0 | S18: 0 | T18: 0 | U18: 0 | V18: 0 | X18: =SUMIFS(P18:V18,$P$8:$V$8,">="&$N$8,$P$8:$V$8,"<="&$N$8) -> 0 | Y18: =IFERROR((X19/X18),"-") -> - | AA18: 44.05 | AB18: 40.56 | AC18: 0 | AD18: =IFERROR((AC18/AB18),"-") -> 0 | AF18: 3744.925 | AG18: 0 | AH18: 0 | AK18: =AF18+AG18+AH18+AI18+AJ18+AC18 -> 3744.925 | AL18: 4401.51 | AM18: =IFERROR((AK18/AL18),"-") -> 0.85082733 | AO18: 4432.1 | AP18: =AO18-AK18 -> 687.175 | AV18: =IF(AX18="Y",LEFT(E18,20),IF(AX18="x",E18,AV17)) -> Escavação 1ª e 2ª categoria | AW18: =IF(E18<>"",E18,AW17) -> Seg. 2.2-C02 - Escavação, carga e transporte de material 1ª/2ª categoria
A19: =A18 -> N | D19: 2.2-C02 | H19: R | I19: 0 | L19: R | M19: =_xlfn.XLOOKUP($N$8,$P$8:$V$8,$P19:$V19) -> 0 | P19: 0 | Q19: 0 | R19: 0 | S19: 0 | T19: 0 | U19: 0 | V19: 0 | X19: =SUMIFS(P19:V19,$P$8:$V$8,">="&$P$8,$P$8:$V$8,"<="&$N$8) -> 0 | AV19: =IF(AX19="Y",LEFT(E19,20),IF(AX19="x",E19,AV18)) -> Escavação 1ª e 2ª categoria | AW19: =IF(E19<>"",E19,AW18) -> Seg. 2.2-C02 - Escavação, carga e transporte de material 1ª/2ª categoria
A20: =IF(SUM(P20:V21)>0,"S","N") -> N | B20: 1059584 | C20: 2.1.4.1.1.3.1 | D20: 2.2-C03 | E20: Seg. 2.2-C03 - Escavação, carga e transporte de material 1ª/2ª categoria | F20: m³ | H20: P | I20: 0 | J20: =IFERROR((I21/I20),"-") -> - | L20: P | M20: =_xlfn.XLOOKUP($N$8,$P$8:$V$8,$P20:$V20) -> 0 | N20: =IFERROR((M21/M20),"-") -> - | P20: 0 | Q20: 0 | R20: 0 | S20: 0 | T20: 0 | U20: 0 | V20: 0 | X20: =SUMIFS(P20:V20,$P$8:$V$8,">="&$P$8,$P$8:$V$8,"<="&$N$8) -> 0 | Y20: =IFERROR((X21/X20),"-") -> - | AA20: 0 | AB20: 0 | AC20: 0 | AD20: =IFERROR((AC20/AB20),"-") -> - | AF20: 702.418 | AG20: 0 | AH20: 0 | AK20: =AF20+AG20+AH20+AI20+AJ20+AC20 -> 702.418 | AL20: 1 | AM20: =IFERROR((AK20/AL20),"-") -> 702.418 | AO20: 4433.58 | AP20: =AO20-AK20 -> 3731.162 | AV20: =IF(AX20="Y",LEFT(E20,20),IF(AX20="x",E20,AV19)) -> Escavação 1ª e 2ª categoria | AW20: =IF(E20<>"",E20,AW19) -> Seg. 2.2-C03 - Escavação, carga e transporte de material 1ª/2ª categoria
A21: =A20 -> N | D21: 2.2-C03 | H21: R | I21: 0 | L21: R | M21: =_xlfn.XLOOKUP($N$8,$P$8:$V$8,$P21:$V21) -> 0 | P21: 0 | Q21: 0 | R21: 0 | S21: 0 | T21: 0 | U21: 0 | V21: 0 | X21: =SUMIFS(P21:V21,$P$8:$V$8,">="&$P$8,$P$8:$V$8,"<="&$N$8) -> 0 | AV21: =IF(AX21="Y",LEFT(E21,20),IF(AX21="x",E21,AV20)) -> Escavação 1ª e 2ª categoria | AW21: =IF(E21<>"",E21,AW20) -> Seg. 2.2-C03 - Escavação, carga e transporte de material 1ª/2ª categoria
A22: =IF(SUM(P22:V23)>0,"S","N") -> S | B22: 1059585 | C22: 2.1.4.1.1.4.1.1 | D22: 2.2-C04 | E22: Seg. 2.2-C04-B01 - Escavação, carga e transporte de material 1ª/2ª categoria | F22: m³ | H22: P | I22: 8000 | J22: =IFERROR((I23/I22),"-") -> 0.05 | L22: P | M22: =_xlfn.XLOOKUP($N$8,$P$8:$V$8,$P22:$V22) -> 1400 | N22: =IFERROR((M23/M22),"-") -> 0 | P22: 1400 | Q22: 1400 | R22: 1400 | S22: 0 | T22: 0 | U22: 0 | V22: 0 | X22: =SUMIFS(P22:V22,$P$8:$V$8,">="&$P$8,$P$8:$V$8,"<="&$N$8) -> 2800 | Y22: =IFERROR((X23/X22),"-") -> 0 | AA22: 14444.39 | AB22: 14444.39 | AC22: 400 | AD22: =IFERROR((AC22/AB22),"-") -> 0.027692412 | AF22: 86033.56 | AG22: 0 | AH22: 660 | AI22: 6809.587 | AJ22: 3086.242 | AK22: =AF22+AG22+AH22+AI22+AJ22+AC22 -> 96989.389 | AL22: 3656.3 | AM22: =IFERROR((AK22/AL22),"-") -> 26.52665 | AO22: 139090.46 | AP22: =AO22-AK22 -> 42101.071 | AV22: =IF(AX22="Y",LEFT(E22,20),IF(AX22="x",E22,AV21)) -> Escavação 1ª e 2ª categoria | AW22: =IF(E22<>"",E22,AW21) -> Seg. 2.2-C04-B01 - Escavação, carga e transporte de material 1ª/2ª categoria
A23: =A22 -> S | C23: 2.1.4.1.1.4.3.2 | D23: 2.2-C04 | H23: R | I23: 400 | L23: R | M23: =_xlfn.XLOOKUP($N$8,$P$8:$V$8,$P23:$V23) -> 0 | P23: 0 | Q23: 0 | R23: 0 | S23: 0 | T23: 0 | U23: 0 | V23: 0 | X23: =SUMIFS(P23:V23,$P$8:$V$8,">="&$P$8,$P$8:$V$8,"<="&$N$8) -> 0 | AV23: =IF(AX23="Y",LEFT(E23,20),IF(AX23="x",E23,AV22)) -> Escavação 1ª e 2ª categoria | AW23: =IF(E23<>"",E23,AW22) -> Seg. 2.2-C04-B01 - Escavação, carga e transporte de material 1ª/2ª categoria
A24: =IF(SUM(P24:V25)>0,"S","N") -> N | B24: 1059594 | C24: 2.1.4.1.1.5.1 | D24: 2.2-C05 | E24: Seg. 2.2-C05 - Escavação, carga e transporte de material 1ª/2ª categoria | F24: m³ | H24: P | I24: 0 | J24: =IFERROR((I25/I24),"-") -> - | L24: P | M24: =_xlfn.XLOOKUP($N$8,$P$8:$V$8,$P24:$V24) -> 0 | N24: =IFERROR((M25/M24),"-") -> - | P24: 0 | Q24: 0 | R24: 0 | S24: 0 | T24: 0 | U24: 0 | V24: 0 | X24: =SUMIFS(P24:V24,$P$8:$V$8,">="&$P$8,$P$8:$V$8,"<="&$N$8) -> 0 | Y24: =IFERROR((X25/X24),"-") -> - | AA24: 184.28 | AB24: 0 | AC24: 0 | AD24: =IFERROR((AC24/AB24),"-") -> - | AF24: 7528.338 | AG24: 0 | AH24: 200 | AK24: =AF24+AG24+AH24+AI24+AJ24+AC24 -> 7728.338 | AL24: 7728.12 | AM24: =IFERROR((AK24/AL24),"-") -> 1.0000282 | AO24: 7912.26 | AP24: =AO24-AK24 -> 183.922 | AV24: =IF(AX24="Y",LEFT(E24,20),IF(AX24="x",E24,AV23)) -> Escavação 1ª e 2ª categoria | AW24: =IF(E24<>"",E24,AW23) -> Seg. 2.2-C05 - Escavação, carga e transporte de material 1ª/2ª categoria
A25: =A24 -> N | D25: 2.2-C05 | H25: R | I25: 0 | L25: R | M25: =_xlfn.XLOOKUP($N$8,$P$8:$V$8,$P25:$V25) -> 0 | P25: 0 | Q25: 0 | R25: 0 | S25: 0 | T25: 0 | U25: 0 | V25: 0 | X25: =SUMIFS(P25:V25,$P$8:$V$8,">="&$P$8,$P$8:$V$8,"<="&$N$8) -> 0 | AV25: =IF(AX25="Y",LEFT(E25,20),IF(AX25="x",E25,AV24)) -> Escavação 1ª e 2ª categoria | AW25: =IF(E25<>"",E25,AW24) -> Seg. 2.2-C05 - Escavação, carga e transporte de material 1ª/2ª categoria
A26: =IF(SUM(P26:V27)>0,"S","N") -> N | B26: 1059595 | C26: 2.1.4.1.1.7.1 | D26: 2.2-C07 | E26: Seg. 2.2-C07 - Escavação, carga e transporte de material 1ª/2ª categoria | F26: m³ | H26: P | I26: 0 | J26: =IFERROR((I27/I26),"-") -> - | L26: P | M26: =_xlfn.XLOOKUP($N$8,$P$8:$V$8,$P26:$V26) -> 0 | N26: =IFERROR((M27/M26),"-") -> - | P26: 0 | Q26: 0 | R26: 0 | S26: 0 | T26: 0 | U26: 0 | V26: 0 | X26: =SUMIFS(P26:V26,$P$8:$V$8,">="&$P$8,$P$8:$V$8,"<="&$N$8) -> 0 | Y26: =IFERROR((X27/X26),"-") -> - | AA26: 8909.03 | AB26: 8909.04 | AC26: 500 | AD26: =IFERROR((AC26/AB26),"-") -> 0.05612277 | AF26: 80715.737 | AG26: 282.037 | AH26: 1580 | AI26: 495.136 | AK26: =AF26+AG26+AH26+AI26+AJ26+AC26 -> 83572.91 | AL26: 92278.99 | AM26: =IFERROR((AK26/AL26),"-") -> 0.9056548 | AO26: 92279.04 | AP26: =AO26-AK26 -> 8706.13 | AV26: =IF(AX26="Y",LEFT(E26,20),IF(AX26="x",E26,AV25)) -> Escavação 1ª e 2ª categoria | AW26: =IF(E26<>"",E26,AW25) -> Seg. 2.2-C07 - Escavação, carga e transporte de material 1ª/2ª categoria
A27: =A26 -> N | D27: 2.2-C07 | H27: R | I27: 230 | L27: R | M27: =_xlfn.XLOOKUP($N$8,$P$8:$V$8,$P27:$V27) -> 0 | P27: 0 | Q27: 0 | R27: 0 | S27: 0 | T27: 0 | U27: 0 | V27: 0 | X27: =SUMIFS(P27:V27,$P$8:$V$8,">="&$P$8,$P$8:$V$8,"<="&$N$8) -> 0 | AV27: =IF(AX27="Y",LEFT(E27,20),IF(AX27="x",E27,AV26)) -> Escavação 1ª e 2ª categoria | AW27: =IF(E27<>"",E27,AW26) -> Seg. 2.2-C07 - Escavação, carga e transporte de material 1ª/2ª categoria
A28: =IF(SUM(P28:V29)>0,"S","N") -> N | B28: 1059596 | C28: 2.1.4.1.1.8.1 | D28: 2.2-C08 | E28: Seg. 2.2-C08 - Escavação, carga e transporte de material 1ª/2ª categoria | F28: m³ | H28: P | I28: 0 | J28: =IFERROR((I29/I28),"-") -> - | L28: P | M28: =_xlfn.XLOOKUP($N$8,$P$8:$V$8,$P28:$V28) -> 0 | N28: =IFERROR((M29/M28),"-") -> - | P28: 0 | Q28: 0 | R28: 0 | S28: 0 | T28: 0 | U28: 0 | V28: 0 | X28: =SUMIFS(P28:V28,$P$8:$V$8,">="&$P$8,$P$8:$V$8,"<="&$N$8) -> 0 | Y28: =IFERROR((X29/X28),"-") -> - | AA28: 0 | AB28: 0 | AC28: 0 | AD28: =IFERROR((AC28/AB28),"-") -> - | AF28: 347.995 | AG28: 0 | AH28: 0 | AK28: =AF28+AG28+AH28+AI28+AJ28+AC28 -> 347.995 | AL28: 904.37 | AM28: =IFERROR((AK28/AL28),"-") -> 0.38479273 | AO28: 904.37 | AP28: =AO28-AK28 -> 556.375 | AV28: =IF(AX28="Y",LEFT(E28,20),IF(AX28="x",E28,AV27)) -> Escavação 1ª e 2ª categoria | AW28: =IF(E28<>"",E28,AW27) -> Seg. 2.2-C08 - Escavação, carga e transporte de material 1ª/2ª categoria
A29: =A28 -> N | D29: 2.2-C08 | H29: R | I29: 0 | L29: R | M29: =_xlfn.XLOOKUP($N$8,$P$8:$V$8,$P29:$V29) -> 0 | P29: 0 | Q29: 0 | R29: 0 | S29: 0 | T29: 0 | U29: 0 | V29: 0 | X29: =SUMIFS(P29:V29,$P$8:$V$8,">="&$P$8,$P$8:$V$8,"<="&$N$8) -> 0 | AV29: =IF(AX29="Y",LEFT(E29,20),IF(AX29="x",E29,AV28)) -> Escavação 1ª e 2ª categoria | AW29: =IF(E29<>"",E29,AW28) -> Seg. 2.2-C08 - Escavação, carga e transporte de material 1ª/2ª categoria
A30: =IF(SUM(P30:V31)>0,"S","N") -> N | B30: 1059597 | C30: 2.1.4.1.1.9.1 | D30: 2.2-C09 | E30: Seg. 2.2-C09 - Escavação, carga e transporte de material 1ª/2ª categoria | F30: m³ | H30: P | I30: 0 | J30: =IFERROR((I31/I30),"-") -> - | L30: P | M30: =_xlfn.XLOOKUP($N$8,$P$8:$V$8,$P30:$V30) -> 0 | N30: =IFERROR((M31/M30),"-") -> - | P30: 0 | Q30: 0 | R30: 0 | S30: 0 | T30: 0 | U30: 0 | V30: 0 | X30: =SUMIFS(P30:V30,$P$8:$V$8,">="&$P$8,$P$8:$V$8,"<="&$N$8) -> 0 | Y30: =IFERROR((X31/X30),"-") -> - | AA30: 4565.78 | AB30: 4565.78 | AC30: 90 | AD30: =IFERROR((AC30/AB30),"-") -> 0.019711856 | AF30: 18490.549 | AG30: 0 | AH30: 150 | AK30: =AF30+AG30+AH30+AI30+AJ30+AC30 -> 18730.549 | AL30: 23556.83 | AM30: =IFERROR((AK30/AL30),"-") -> 0.7951218 | AO30: 23556.78 | AP30: =AO30-AK30 -> 4826.231 | AV30: =IF(AX30="Y",LEFT(E30,20),IF(AX30="x",E30,AV29)) -> Escavação 1ª e 2ª categoria | AW30: =IF(E30<>"",E30,AW29) -> Seg. 2.2-C09 - Escavação, carga e transporte de material 1ª/2ª categoria
A31: =A30 -> N | D31: 2.2-C09 | H31: R | I31: 90 | L31: R | M31: =_xlfn.XLOOKUP($N$8,$P$8:$V$8,$P31:$V31) -> 0 | P31: 0 | Q31: 0 | R31: 0 | S31: 0 | T31: 0 | U31: 0 | V31: 0 | X31: =SUMIFS(P31:V31,$P$8:$V$8,">="&$P$8,$P$8:$V$8,"<="&$N$8) -> 0 | AV31: =IF(AX31="Y",LEFT(E31,20),IF(AX31="x",E31,AV30)) -> Escavação 1ª e 2ª categoria | AW31: =IF(E31<>"",E31,AW30) -> Seg. 2.2-C09 - Escavação, carga e transporte de material 1ª/2ª categoria
A32: =IF(SUM(P32:V33)>0,"S","N") -> N | B32: 1059598 | C32: 2.1.4.1.1.10.1 | D32: 2.2-C10 | E32: Seg. 2.2-C10 - Escavação, carga e transporte de material 1ª categoria | F32: m³ | H32: P | I32: 0 | J32: =IFERROR((I33/I32),"-") -> - | L32: P | M32: =_xlfn.XLOOKUP($N$8,$P$8:$V$8,$P32:$V32) -> 0 | N32: =IFERROR((M33/M32),"-") -> - | P32: 0 | Q32: 0 | R32: 0 | S32: 0 | T32: 0 | U32: 0 | V32: 0 | X32: =SUMIFS(P32:V32,$P$8:$V$8,">="&$P$8,$P$8:$V$8,"<="&$N$8) -> 0 | Y32: =IFERROR((X33/X32),"-") -> - | AA32: 1961.96 | AB32: 1961.96 | AC32: 0 | AD32: =IFERROR((AC32/AB32),"-") -> 0 | AF32: 1169.756 | AG32: 0 | AH32: 0 | AK32: =AF32+AG32+AH32+AI32+AJ32+AC32 -> 1169.756 | AL32: 3131.96 | AM32: =IFERROR((AK32/AL32),"-") -> 0.37349008 | AO32: 3131.96 | AP32: =AO32-AK32 -> 1962.204 | AV32: =IF(AX32="Y",LEFT(E32,20),IF(AX32="x",E32,AV31)) -> Escavação 1ª e 2ª categoria | AW32: =IF(E32<>"",E32,AW31) -> Seg. 2.2-C10 - Escavação, carga e transporte de material 1ª categoria
A33: =A32 -> N | D33: 2.2-C10 | H33: R | I33: 0 | L33: R | M33: =_xlfn.XLOOKUP($N$8,$P$8:$V$8,$P33:$V33) -> 0 | P33: 0 | Q33: 0 | R33: 0 | S33: 0 | T33: 0 | U33: 0 | V33: 0 | X33: =SUMIFS(P33:V33,$P$8:$V$8,">="&$P$8,$P$8:$V$8,"<="&$N$8) -> 0 | AV33: =IF(AX33="Y",LEFT(E33,20),IF(AX33="x",E33,AV32)) -> Escavação 1ª e 2ª categoria | AW33: =IF(E33<>"",E33,AW32) -> Seg. 2.2-C10 - Escavação, carga e transporte de material 1ª categoria
A34: =IF(SUM(P34:V35)>0,"S","N") -> N | B34: 1059599 | C34: 2.1.4.1.1.11.1 | D34: 2.2-C11 | E34: Seg. 2.2-C11 - Escavação, carga e transporte de material 1ª categoria | F34: m³ | H34: P | I34: 0 | J34: =IFERROR((I35/I34),"-") -> - | L34: P | M34: =_xlfn.XLOOKUP($N$8,$P$8:$V$8,$P34:$V34) -> 0 | N34: =IFERROR((M35/M34),"-") -> - | P34: 0 | Q34: 0 | R34: 0 | S34: 0 | T34: 0 | U34: 0 | V34: 0 | X34: =SUMIFS(P34:V34,$P$8:$V$8,">="&$P$8,$P$8:$V$8,"<="&$N$8) -> 0 | Y34: =IFERROR((X35/X34),"-") -> - | AA34: 0 | AB34: 0 | AC34: 0 | AD34: =IFERROR((AC34/AB34),"-") -> - | AF34: 2979.06 | AG34: 0 | AH34: 0 | AK34: =AF34+AG34+AH34+AI34+AJ34+AC34 -> 2979.06 | AL34: 11344.5 | AM34: =IFERROR((AK34/AL34),"-") -> 0.2625995 | AO34: 11344.5 | AP34: =AO34-AK34 -> 8365.44 | AV34: =IF(AX34="Y",LEFT(E34,20),IF(AX34="x",E34,AV33)) -> Escavação 1ª e 2ª categoria | AW34: =IF(E34<>"",E34,AW33) -> Seg. 2.2-C11 - Escavação, carga e transporte de material 1ª categoria
A35: =A34 -> N | D35: 2.2-C11 | H35: R | I35: 0 | L35: R | M35: =_xlfn.XLOOKUP($N$8,$P$8:$V$8,$P35:$V35) -> 0 | P35: 0 | Q35: 0 | R35: 0 | S35: 0 | T35: 0 | U35: 0 | V35: 0 | X35: =SUMIFS(P35:V35,$P$8:$V$8,">="&$P$8,$P$8:$V$8,"<="&$N$8) -> 0 | AV35: =IF(AX35="Y",LEFT(E35,20),IF(AX35="x",E35,AV34)) -> Escavação 1ª e 2ª categoria | AW35: =IF(E35<>"",E35,AW34) -> Seg. 2.2-C11 - Escavação, carga e transporte de material 1ª categoria
A36: =IF(SUM(P36:V37)>0,"S","N") -> N | B36: 1059600 | C36: 2.1.4.1.1.13.1 | D36: 2.2-C12 | E36: Seg. 2.2-C12 - Escavação, carga e transporte de material 1ª/2ª categoria | F36: m³ | H36: P | I36: 0 | J36: =IFERROR((I37/I36),"-") -> - | L36: P | M36: =_xlfn.XLOOKUP($N$8,$P$8:$V$8,$P36:$V36) -> 0 | N36: =IFERROR((M37/M36),"-") -> - | P36: 0 | Q36: 0 | R36: 0 | S36: 0 | T36: 0 | U36: 0 | V36: 0 | X36: =SUMIFS(P36:V36,$P$8:$V$8,">="&$P$8,$P$8:$V$8,"<="&$N$8) -> 0 | Y36: =IFERROR((X37/X36),"-") -> - | AA36: 36291.14 | AB36: 36291.15 | AC36: 0 | AD36: =IFERROR((AC36/AB36),"-") -> 0 | AF36: 37971.863 | AG36: 0 | AH36: 0 | AK36: =AF36+AG36+AH36+AI36+AJ36+AC36 -> 37971.863 | AL36: 37623.07 | AM36: =IFERROR((AK36/AL36),"-") -> 1.0092707 | AO36: 37623 | AP36: =AO36-AK36 -> -348.863 | AV36: =IF(AX36="Y",LEFT(E36,20),IF(AX36="x",E36,AV35)) -> Escavação 1ª e 2ª categoria | AW36: =IF(E36<>"",E36,AW35) -> Seg. 2.2-C12 - Escavação, carga e transporte de material 1ª/2ª categoria
A37: =A36 -> N | D37: 2.2-C12 | H37: R | I37: 0 | L37: R | M37: =_xlfn.XLOOKUP($N$8,$P$8:$V$8,$P37:$V37) -> 0 | P37: 0 | Q37: 0 | R37: 0 | S37: 0 | T37: 0 | U37: 0 | V37: 0 | X37: =SUMIFS(P37:V37,$P$8:$V$8,">="&$P$8,$P$8:$V$8,"<="&$N$8) -> 0 | AV37: =IF(AX37="Y",LEFT(E37,20),IF(AX37="x",E37,AV36)) -> Escavação 1ª e 2ª categoria | AW37: =IF(E37<>"",E37,AW36) -> Seg. 2.2-C12 - Escavação, carga e transporte de material 1ª/2ª categoria
A38: =IF(SUM(P38:V39)>0,"S","N") -> S | B38: 1059601 | C38: 2.1.4.1.1.14.4 | D38: 2.2-C13 | E38: Seg. 2.2-C13 - Escavação, carga e transporte de material 1ª/2ª categoria | F38: m³ | H38: P | I38: 0 | J38: =IFERROR((I39/I38),"-") -> - | L38: P | M38: =_xlfn.XLOOKUP($N$8,$P$8:$V$8,$P38:$V38) -> 0 | N38: =IFERROR((M39/M38),"-") -> - | P38: 0 | Q38: 0 | R38: 0 | S38: 0 | T38: 0 | U38: 0 | V38: 0 | X38: =SUMIFS(P38:V38,$P$8:$V$8,">="&$P$8,$P$8:$V$8,"<="&$N$8) -> 0 | Y38: =IFERROR((X39/X38),"-") -> - | AA38: 0 | AB38: 0 | AC38: 800 | AD38: =IFERROR((AC38/AB38),"-") -> - | AF38: 36064.872 | AG38: 5981.819 | AH38: 4200 | AI38: 13782.547 | AJ38: 3162.518 | AK38: =AF38+AG38+AH38+AI38+AJ38+AC38 -> 63991.756 | AL38: 60301.87 | AM38: =IFERROR((AK38/AL38),"-") -> 1.0611902 | AO38: 61428.32 | AP38: =AO38-AK38 -> -2563.436 | AV38: =IF(AX38="Y",LEFT(E38,20),IF(AX38="x",E38,AV37)) -> Escavação 1ª e 2ª categoria | AW38: =IF(E38<>"",E38,AW37) -> Seg. 2.2-C13 - Escavação, carga e transporte de material 1ª/2ª categoria
A39: =A38 -> S | D39: 2.2-C13 | H39: R | I39: 0 | L39: R | M39: =_xlfn.XLOOKUP($N$8,$P$8:$V$8,$P39:$V39) -> 800 | P39: 0 | Q39: 800 | R39: 0 | S39: 0 | T39: 0 | U39: 0 | V39: 0 | X39: =SUMIFS(P39:V39,$P$8:$V$8,">="&$P$8,$P$8:$V$8,"<="&$N$8) -> 800 | AV39: =IF(AX39="Y",LEFT(E39,20),IF(AX39="x",E39,AV38)) -> Escavação 1ª e 2ª categoria | AW39: =IF(E39<>"",E39,AW38) -> Seg. 2.2-C13 - Escavação, carga e transporte de material 1ª/2ª categoria
A40: =IF(SUM(P40:V41)>0,"S","N") -> N | B40: 1059603 | C40: 2.1.4.1.1.15.1 | D40: 2.2-C14 | E40: Seg. 2.2-C14 - Acabamentos em talude do Corte - Seg.2.2B C 14 | F40: m³ | H40: P | I40: 0 | J40: =IFERROR((I41/I40),"-") -> - | L40: P | M40: =_xlfn.XLOOKUP($N$8,$P$8:$V$8,$P40:$V40) -> 0 | N40: =IFERROR((M41/M40),"-") -> - | P40: 0 | Q40: 0 | R40: 0 | S40: 0 | T40: 0 | U40: 0 | V40: 0 | X40: =SUMIFS(P40:V40,$P$8:$V$8,">="&$P$8,$P$8:$V$8,"<="&$N$8) -> 0 | Y40: =IFERROR((X41/X40),"-") -> - | AA40: 0 | AB40: 0 | AC40: 0 | AD40: =IFERROR((AC40/AB40),"-") -> - | AF40: 0 | AG40: 0 | AH40: 0 | AK40: =AF40+AG40+AH40+AI40+AJ40+AC40 -> 0 | AL40: 239.46 | AM40: =IFERROR((AK40/AL40),"-") -> 0 | AO40: 239.46 | AP40: =AO40-AK40 -> 239.46 | AV40: =IF(AX40="Y",LEFT(E40,20),IF(AX40="x",E40,AV39)) -> Escavação 1ª e 2ª categoria | AW40: =IF(E40<>"",E40,AW39) -> Seg. 2.2-C14 - Acabamentos em talude do Corte - Seg.2.2B C 14
A41: =A40 -> N | D41: 2.2-C14 | H41: R | I41: 0 | L41: R | M41: =_xlfn.XLOOKUP($N$8,$P$8:$V$8,$P41:$V41) -> 0 | P41: 0 | Q41: 0 | R41: 0 | S41: 0 | T41: 0 | U41: 0 | V41: 0 | X41: =SUMIFS(P41:V41,$P$8:$V$8,">="&$P$8,$P$8:$V$8,"<="&$N$8) -> 0 | AV41: =IF(AX41="Y",LEFT(E41,20),IF(AX41="x",E41,AV40)) -> Escavação 1ª e 2ª categoria | AW41: =IF(E41<>"",E41,AW40) -> Seg. 2.2-C14 - Acabamentos em talude do Corte - Seg.2.2B C 14
A42: =IF(SUM(P42:V43)>0,"S","N") -> N | B42: 1059604 | C42: 2.1.4.1.1.16.1 | D42: 2.2-C15 | E42: Seg. 2.2-C15 - Escavação, carga e transporte de material 1ª categoria | F42: m³ | H42: P | I42: 0 | J42: =IFERROR((I43/I42),"-") -> - | L42: P | M42: =_xlfn.XLOOKUP($N$8,$P$8:$V$8,$P42:$V42) -> 0 | N42: =IFERROR((M43/M42),"-") -> - | P42: 0 | Q42: 0 | R42: 0 | S42: 0 | T42: 0 | U42: 0 | V42: 0 | X42: =SUMIFS(P42:V42,$P$8:$V$8,">="&$P$8,$P$8:$V$8,"<="&$N$8) -> 0 | Y42: =IFERROR((X43/X42),"-") -> - | AA42: 0 | AB42: 0 | AC42: 0 | AD42: =IFERROR((AC42/AB42),"-") -> - | AF42: 0 | AG42: 0 | AH42: 0 | AK42: =AF42+AG42+AH42+AI42+AJ42+AC42 -> 0 | AL42: 614.36 | AM42: =IFERROR((AK42/AL42),"-") -> 0 | AO42: 614.36 | AP42: =AO42-AK42 -> 614.36 | AV42: =IF(AX42="Y",LEFT(E42,20),IF(AX42="x",E42,AV41)) -> Escavação 1ª e 2ª categoria | AW42: =IF(E42<>"",E42,AW41) -> Seg. 2.2-C15 - Escavação, carga e transporte de material 1ª categoria
A43: =A42 -> N | D43: 2.2-C15 | H43: R | I43: 0 | L43: R | M43: =_xlfn.XLOOKUP($N$8,$P$8:$V$8,$P43:$V43) -> 0 | P43: 0 | Q43: 0 | R43: 0 | S43: 0 | T43: 0 | U43: 0 | V43: 0 | X43: =SUMIFS(P43:V43,$P$8:$V$8,">="&$P$8,$P$8:$V$8,"<="&$N$8) -> 0 | AV43: =IF(AX43="Y",LEFT(E43,20),IF(AX43="x",E43,AV42)) -> Escavação 1ª e 2ª categoria | AW43: =IF(E43<>"",E43,AW42) -> Seg. 2.2-C15 - Escavação, carga e transporte de material 1ª categoria
A44: =IF(SUM(P44:V45)>0,"S","N") -> N | B44: 1060926 | C44: 2.2.1.1.1.5.1 | D44: 2.2-AC.114+740 | E44: Escavação, carga e transporte de material 1ª/2ª categoria - Seg.2.2B acesso km114+740 | F44: m³ | H44: P | I44: 0 | J44: =IFERROR((I45/I44),"-") -> - | L44: P | M44: =_xlfn.XLOOKUP($N$8,$P$8:$V$8,$P44:$V44) -> 0 | N44: =IFERROR((M45/M44),"-") -> - | P44: 0 | Q44: 0 | R44: 0 | S44: 0 | T44: 0 | U44: 0 | V44: 0 | X44: =SUMIFS(P44:V44,$P$8:$V$8,">="&$P$8,$P$8:$V$8,"<="&$N$8) -> 0 | Y44: =IFERROR((X45/X44),"-") -> - | AA44: 0 | AB44: 0 | AC44: 0 | AD44: =IFERROR((AC44/AB44),"-") -> - | AF44: 0 | AG44: 914.946 | AH44: 0 | AI44: 1202.64 | AK44: =AF44+AG44+AH44+AI44+AJ44+AC44 -> 2117.586 | AL44: 2118 | AM44: =IFERROR((AK44/AL44),"-") -> 0.99980453 | AO44: 9443.24 | AP44: =AO44-AK44 -> 7325.654 | AV44: =IF(AX44="Y",LEFT(E44,20),IF(AX44="x",E44,AV43)) -> Escavação 1ª e 2ª categoria | AW44: =IF(E44<>"",E44,AW43) -> Escavação, carga e transporte de material 1ª/2ª categoria - Seg.2.2B acesso km114+740
A45: =A44 -> N | D45: 2.2-AC.114+740 | H45: R | I45: 0 | L45: R | M45: =_xlfn.XLOOKUP($N$8,$P$8:$V$8,$P45:$V45) -> 0 | P45: 0 | Q45: 0 | R45: 0 | S45: 0 | T45: 0 | U45: 0 | V45: 0 | X45: =SUMIFS(P45:V45,$P$8:$V$8,">="&$P$8,$P$8:$V$8,"<="&$N$8) -> 0 | AV45: =IF(AX45="Y",LEFT(E45,20),IF(AX45="x",E45,AV44)) -> Escavação 1ª e 2ª categoria | AW45: =IF(E45<>"",E45,AW44) -> Escavação, carga e transporte de material 1ª/2ª categoria - Seg.2.2B acesso km114+740
A46: =IF(SUM(P46:V47)>0,"S","N") -> N | B46: 1060928 | C46: 2.2.1.1.1.4.1 | D46: 2.2-AC.114+460 | E46: Escavação, carga e transporte de material 1ª/2ª categoria - Seg.2.2B acesso km114+460 | F46: m³ | H46: P | I46: 0 | J46: =IFERROR((I47/I46),"-") -> - | L46: P | M46: =_xlfn.XLOOKUP($N$8,$P$8:$V$8,$P46:$V46) -> 0 | N46: =IFERROR((M47/M46),"-") -> - | P46: 0 | Q46: 0 | R46: 0 | S46: 0 | T46: 0 | U46: 0 | V46: 0 | X46: =SUMIFS(P46:V46,$P$8:$V$8,">="&$P$8,$P$8:$V$8,"<="&$N$8) -> 0 | Y46: =IFERROR((X47/X46),"-") -> - | AA46: 0 | AB46: 0 | AC46: 0 | AD46: =IFERROR((AC46/AB46),"-") -> - | AF46: 0 | AG46: 0 | AH46: 0 | AK46: =AF46+AG46+AH46+AI46+AJ46+AC46 -> 0 | AL46: 0 | AM46: =IFERROR((AK46/AL46),"-") -> - | AO46: 708.89 | AP46: =AO46-AK46 -> 708.89 | AV46: =IF(AX46="Y",LEFT(E46,20),IF(AX46="x",E46,AV45)) -> Escavação 1ª e 2ª categoria | AW46: =IF(E46<>"",E46,AW45) -> Escavação, carga e transporte de material 1ª/2ª categoria - Seg.2.2B acesso km114+460
